.class public final e
.super java.lang.Exception
.implements javax.microedition.lcdui.CommandListener
.implements javax.microedition.lcdui.ItemStateListener

.field private static b:I
.field private static a:Ljava/lang/String;
.field private static b:Ljava/lang/String;
.field private static c:Ljava/lang/String;
.field private static d:Ljava/lang/String;
.field private static e:Ljava/lang/String;
.field private static f:Ljava/lang/String;
.field private static g:Ljava/lang/String;
.field private static final a:[B
.field private static final b:[B
.field private static final c:[B
.field private static final h:Ljava/lang/String;
.field private static final i:Ljava/lang/String;
.field private static final j:Ljava/lang/String;
.field private static final k:Ljava/lang/String;
.field private static final l:Ljava/lang/String;
.field private static final m:Ljava/lang/String;
.field private static final n:Ljava/lang/String;
.field private static final o:Ljava/lang/String;
.field private static final p:Ljava/lang/String;
.field private static final q:Ljava/lang/String;
.field private static final r:Ljava/lang/String;
.field private static final s:Ljava/lang/String;
.field public static a:Z
.field public static b:Z
.field public static c:Z
.field public static d:Z
.field public static e:Z
.field public static a:I
.field private final a:[Ljava/lang/String;
.field private static t:Ljava/lang/String;
.field private static u:Ljava/lang/String;
.field private static v:Ljava/lang/String;
.field private static b:[Ljava/lang/String;
.field private static c:[Ljava/lang/String;
.field private static w:Ljava/lang/String;
.field private static x:Ljava/lang/String;
.field private y:Ljava/lang/String;
.field private c:I
.field private a:Ljava/util/Hashtable;
.field private f:Z
.field private static final b:Ljava/util/Hashtable;
.field private static final d:[Ljava/lang/String;
.field private static a:Ljavax/microedition/midlet/MIDlet;
.field private static z:Ljava/lang/String;
.field private static A:Ljava/lang/String;
.field private static B:Ljava/lang/String;
.field private static g:Z
.field private static C:Ljava/lang/String;
.field private static c:Ljava/util/Hashtable;
.field private static a:Le;
.field private static d:I
.field private static h:Z
.field private volatile e:I
.field private a:Ljavax/microedition/lcdui/Form;
.field private a:Ljavax/microedition/lcdui/ChoiceGroup;
.field private a:Ljavax/microedition/lcdui/Command;
.field private b:Ljavax/microedition/lcdui/Command;
.field private e:[Ljava/lang/String;
.field private volatile f:I
.field private static D:Ljava/lang/String;
.field private static f:[Ljava/lang/String;

.method private <init>()V
    .limit stack 5
    .limit locals 1
    aload_0
    invokespecial java/lang/Exception-><init>()V
    aload_0
    iconst_2
    anewarray java/lang/String
    dup
    iconst_0
    ldc ''
    aastore
    dup
    iconst_1
    ldc ''
    aastore
    putfield e->a:[Ljava/lang/String;
    aload_0
    aconst_null
    putfield e->y:Ljava/lang/String;
    aload_0
    iconst_0
    putfield e->c:I
    aload_0
    new java/util/Hashtable
    dup
    invokespecial java/util/Hashtable-><init>()V
    putfield e->a:Ljava/util/Hashtable;
    aload_0
    iconst_0
    putfield e->f:Z
    aload_0
    iconst_0
    putfield e->e:I
    aload_0
    aconst_null
    putfield e->a:Ljavax/microedition/lcdui/Form;
    aload_0
    aconst_null
    putfield e->a:Ljavax/microedition/lcdui/ChoiceGroup;
    aload_0
    aconst_null
    putfield e->a:Ljavax/microedition/lcdui/Command;
    aload_0
    aconst_null
    putfield e->b:Ljavax/microedition/lcdui/Command;
    aload_0
    aconst_null
    putfield e->e:[Ljava/lang/String;
    aload_0
    iconst_0
    putfield e->f:I
    return
.end method

.method private <init>(Ljava/lang/String;Ljava/lang/String;Ljava/lang/String;Ljava/lang/String;)V
    .limit stack 5
    .limit locals 5
    aload_0
    invokespecial java/lang/Exception-><init>()V
    aload_0
    iconst_2
    anewarray java/lang/String
    dup
    iconst_0
    ldc ''
    aastore
    dup
    iconst_1
    ldc ''
    aastore
    putfield e->a:[Ljava/lang/String;
    aload_0
    aconst_null
    putfield e->y:Ljava/lang/String;
    aload_0
    iconst_0
    putfield e->c:I
    aload_0
    new java/util/Hashtable
    dup
    invokespecial java/util/Hashtable-><init>()V
    putfield e->a:Ljava/util/Hashtable;
    aload_0
    iconst_0
    putfield e->f:Z
    aload_0
    iconst_0
    putfield e->e:I
    aload_0
    aconst_null
    putfield e->a:Ljavax/microedition/lcdui/Form;
    aload_0
    aconst_null
    putfield e->a:Ljavax/microedition/lcdui/ChoiceGroup;
    aload_0
    aconst_null
    putfield e->a:Ljavax/microedition/lcdui/Command;
    aload_0
    aconst_null
    putfield e->b:Ljavax/microedition/lcdui/Command;
    aload_0
    aconst_null
    putfield e->e:[Ljava/lang/String;
    aload_0
    iconst_0
    putfield e->f:I
    aload_0
    getfield e->a:[Ljava/lang/String;
    iconst_0
    aload_1
    aastore
    aload_0
    getfield e->a:[Ljava/lang/String;
    iconst_1
    aload_2
    aastore
    return
.end method

.method public static final a(Ljavax/microedition/midlet/MIDlet;[Ljava/lang/String;[Ljava/lang/String;Ljava/lang/String;Ljava/lang/String;Ljava/lang/String;ZZILjava/lang/String;)V
    .limit stack 5
    .limit locals 10
    aload_0
    putstatic e->a:Ljavax/microedition/midlet/MIDlet;
    aload_1
    putstatic e->b:[Ljava/lang/String;
    aload_2
    putstatic e->c:[Ljava/lang/String;
    aload_3
    putstatic e->z:Ljava/lang/String;
    aload 0x4
    putstatic e->A:Ljava/lang/String;
    aload 0x5
    putstatic e->B:Ljava/lang/String;
    iload 0x6
    ifeq 0x8
    ldc 'GET'
    goto 0x5
    ldc 'POST'
    putstatic e->x:Ljava/lang/String;
    iload 0x7
    putstatic e->e:Z
    iconst_2
    putstatic e->a:I
    aload 0x9
    astore_0
    aload_0
    bipush 0x25
    invokestatic a->a(Ljava/lang/String;C)[Ljava/lang/String;
    dup
    astore_0
    ifnull 0x38
    iconst_0
    istore_1
    iload_1
    aload_0
    arraylength
    if_icmpge 0x30
    aload_0
    iload_1
    aaload
    bipush 0x3d
    invokevirtual java/lang/String->indexOf(I)I
    dup
    istore_2
    iflt 0x1d
    aload_0
    iload_1
    aaload
    iconst_0
    iload_2
    invokevirtual java/lang/String->substring(II)Ljava/lang/String;
    aload_0
    iload_1
    aaload
    iload_2
    iconst_1
    iadd
    aload_0
    iload_1
    aaload
    invokevirtual java/lang/String->length()I
    invokevirtual java/lang/String->substring(II)Ljava/lang/String;
    invokestatic a->a(Ljava/lang/String;Ljava/lang/String;)V
    iinc 0x1 0x1
    goto -0x30
    goto 0x4
    pop
    getstatic e->l:Ljava/lang/String;
    invokestatic a->a(Ljava/lang/String;)Ljava/lang/String;
    putstatic e->t:Ljava/lang/String;
    getstatic e->m:Ljava/lang/String;
    invokestatic a->a(Ljava/lang/String;)Ljava/lang/String;
    putstatic e->u:Ljava/lang/String;
    getstatic e->n:Ljava/lang/String;
    invokestatic a->a(Ljava/lang/String;)Ljava/lang/String;
    putstatic e->v:Ljava/lang/String;
    getstatic e->q:Ljava/lang/String;
    iconst_1
    invokestatic a->a(Ljava/lang/String;Z)Z
    putstatic e->a:Z
    getstatic e->r:Ljava/lang/String;
    iconst_1
    invokestatic a->a(Ljava/lang/String;Z)Z
    putstatic e->b:Z
    getstatic e->s:Ljava/lang/String;
    iconst_1
    invokestatic a->a(Ljava/lang/String;Z)Z
    putstatic e->c:Z
    getstatic a->a:Ljava/util/Hashtable;
    getstatic e->l:Ljava/lang/String;
    invokevirtual java/util/Hashtable->remove(Ljava/lang/Object;)Ljava/lang/Object;
    pop
    getstatic a->a:Ljava/util/Hashtable;
    getstatic e->m:Ljava/lang/String;
    invokevirtual java/util/Hashtable->remove(Ljava/lang/Object;)Ljava/lang/Object;
    pop
    getstatic a->a:Ljava/util/Hashtable;
    getstatic e->n:Ljava/lang/String;
    invokevirtual java/util/Hashtable->remove(Ljava/lang/Object;)Ljava/lang/Object;
    pop
    getstatic a->a:Ljava/util/Hashtable;
    getstatic e->q:Ljava/lang/String;
    invokevirtual java/util/Hashtable->remove(Ljava/lang/Object;)Ljava/lang/Object;
    pop
    getstatic a->a:Ljava/util/Hashtable;
    getstatic e->r:Ljava/lang/String;
    invokevirtual java/util/Hashtable->remove(Ljava/lang/Object;)Ljava/lang/Object;
    pop
    getstatic a->a:Ljava/util/Hashtable;
    getstatic e->s:Ljava/lang/String;
    invokevirtual java/util/Hashtable->remove(Ljava/lang/Object;)Ljava/lang/Object;
    pop
    new java/lang/StringBuffer
    dup
    invokespecial java/lang/StringBuffer-><init>()V
    getstatic e->A:Ljava/lang/String;
    invokevirtual java/lang/StringBuffer->append(Ljava/lang/String;)Ljava/lang/StringBuffer;
    getstatic e->B:Ljava/lang/String;
    invokevirtual java/lang/StringBuffer->append(Ljava/lang/String;)Ljava/lang/StringBuffer;
    ldc 'yc'
    invokevirtual java/lang/StringBuffer->append(Ljava/lang/String;)Ljava/lang/StringBuffer;
    getstatic e->e:Z
    ifeq 0x8
    ldc 'h'
    goto 0x5
    ldc ''
    invokevirtual java/lang/StringBuffer->append(Ljava/lang/String;)Ljava/lang/StringBuffer;
    invokevirtual java/lang/StringBuffer->toString()Ljava/lang/String;
    putstatic e->w:Ljava/lang/String;
    aconst_null
    putstatic e->C:Ljava/lang/String;
    aconst_null
    putstatic e->c:Ljava/util/Hashtable;
    aconst_null
    putstatic e->a:Le;
    iconst_1
    putstatic e->g:Z
    invokestatic e->d()V
    invokestatic e->f()V
    getstatic e->j:Ljava/lang/String;
    invokestatic a->a(Ljava/lang/String;)Ljava/lang/String;
    ifnull 0x3a
    iconst_1
    putstatic e->d:Z
    getstatic e->b:Z
    ifeq 0x19
    getstatic e->d:[Ljava/lang/String;
    iconst_0
    aaload
    invokevirtual java/lang/String->length()I
    ifeq 0xe
    getstatic e->d:[Ljava/lang/String;
    iconst_1
    aaload
    invokevirtual java/lang/String->length()I
    ifne 0x1e
    getstatic e->d:[Ljava/lang/String;
    iconst_0
    getstatic e->j:Ljava/lang/String;
    invokestatic a->a(Ljava/lang/String;)Ljava/lang/String;
    aastore
    getstatic e->d:[Ljava/lang/String;
    iconst_1
    getstatic e->k:Ljava/lang/String;
    invokestatic a->a(Ljava/lang/String;)Ljava/lang/String;
    aastore
    return
    iconst_0
    putstatic e->d:Z
    return
.end method

.method public static final a()Z
    .limit stack 1
    .limit locals 0
    getstatic e->g:Z
    ireturn
.end method

.method public static final b()Z
    .limit stack 3
    .limit locals 0
    getstatic e->C:Ljava/lang/String;
    ifnull 0x13
    getstatic e->C:Ljava/lang/String;
    getstatic e->d:[Ljava/lang/String;
    iconst_0
    aaload
    invokevirtual java/lang/String->equals(Ljava/lang/Object;)Z
    ifeq 0x5
    iconst_1
    ireturn
    iconst_0
    ireturn
.end method

.method public static a()Le;
    .limit stack 6
    .limit locals 0
    invokestatic e->b()Z
    ifeq 0x2a
    getstatic e->a:Le;
    ifnonnull 0x20
    new e
    dup
    getstatic e->d:[Ljava/lang/String;
    iconst_0
    aaload
    getstatic e->d:[Ljava/lang/String;
    iconst_1
    aaload
    aconst_null
    aconst_null
    invokespecial e-><init>(Ljava/lang/String;Ljava/lang/String;Ljava/lang/String;Ljava/lang/String;)V
    dup
    putstatic e->a:Le;
    getstatic e->c:Ljava/util/Hashtable;
    putfield e->a:Ljava/util/Hashtable;
    getstatic e->a:Le;
    areturn
    aconst_null
    areturn
.end method

.method public static a(Z)Le;
    .limit stack 6
    .limit locals 5
    getstatic e->g:Z
    ifne 0x5
    aconst_null
    areturn
    getstatic e->a:Z
    ifne 0x5
    iconst_0
    istore_0
    new e
    dup
    invokespecial e-><init>()V
    astore_1
    getstatic e->d:Z
    ifeq 0x56
    getstatic e->b:Z
    ifne 0x50
    aload_1
    dup
    astore_2
    getfield e->a:[Ljava/lang/String;
    iconst_0
    getstatic e->d:[Ljava/lang/String;
    iconst_0
    aaload
    aastore
    aload_2
    getfield e->a:[Ljava/lang/String;
    iconst_1
    getstatic e->d:[Ljava/lang/String;
    iconst_1
    aaload
    aastore
    aload_2
    getfield e->a:[Ljava/lang/String;
    iconst_0
    aaload
    ifnull 0x28
    aload_2
    getfield e->a:[Ljava/lang/String;
    iconst_0
    aaload
    invokevirtual java/lang/String->length()I
    ifle 0x1c
    aload_2
    getfield e->a:[Ljava/lang/String;
    iconst_1
    aaload
    ifnull 0x13
    aload_2
    getfield e->a:[Ljava/lang/String;
    iconst_1
    aaload
    invokevirtual java/lang/String->length()I
    ifle 0x7
    iconst_1
    goto 0x4
    iconst_0
    ifeq 0x15b
    goto 0x13
    aload_1
    iload_0
    ifeq 0x7
    iconst_1
    goto 0x4
    iconst_0
    invokespecial e->a(B)Z
    ifeq 0x148
    iload_0
    ifeq 0x13e
    aload_1
    astore_2
    iconst_m1
    istore_0
    aload_2
    getstatic e->d:Ljava/lang/String;
    invokespecial e->a(Ljava/lang/String;)Ljava/lang/String;
    astore_3
    aload_2
    getstatic e->e:Ljava/lang/String;
    invokespecial e->a(Ljava/lang/String;)Ljava/lang/String;
    astore 0x4
    aload_2
    getstatic e->u:Ljava/lang/String;
    ldc 'register'
    new java/lang/StringBuffer
    dup
    invokespecial java/lang/StringBuffer-><init>()V
    aload_3
    ifnull 0x20
    aload_3
    invokevirtual java/lang/String->length()I
    ifle 0x19
    new java/lang/StringBuffer
    dup
    invokespecial java/lang/StringBuffer-><init>()V
    ldc '&email='
    invokevirtual java/lang/StringBuffer->append(Ljava/lang/String;)Ljava/lang/StringBuffer;
    aload_3
    invokevirtual java/lang/StringBuffer->append(Ljava/lang/String;)Ljava/lang/StringBuffer;
    invokevirtual java/lang/StringBuffer->toString()Ljava/lang/String;
    goto 0x5
    ldc ''
    invokevirtual java/lang/StringBuffer->append(Ljava/lang/String;)Ljava/lang/StringBuffer;
    aload 0x4
    ifnull 0x22
    aload 0x4
    invokevirtual java/lang/String->length()I
    ifle 0x1a
    new java/lang/StringBuffer
    dup
    invokespecial java/lang/StringBuffer-><init>()V
    ldc '&phone='
    invokevirtual java/lang/StringBuffer->append(Ljava/lang/String;)Ljava/lang/StringBuffer;
    aload 0x4
    invokevirtual java/lang/StringBuffer->append(Ljava/lang/String;)Ljava/lang/StringBuffer;
    invokevirtual java/lang/StringBuffer->toString()Ljava/lang/String;
    goto 0x5
    ldc ''
    invokevirtual java/lang/StringBuffer->append(Ljava/lang/String;)Ljava/lang/StringBuffer;
    invokevirtual java/lang/StringBuffer->toString()Ljava/lang/String;
    iconst_0
    invokespecial e->a(Ljava/lang/String;Ljava/lang/String;Ljava/lang/String;I)[B
    dup
    astore_3
    ifnull 0x3f
    new java/io/DataInputStream
    dup
    new java/io/ByteArrayInputStream
    dup
    aload_3
    invokespecial java/io/ByteArrayInputStream-><init>([B)V
    invokespecial java/io/DataInputStream-><init>(Ljava/io/InputStream;)V
    dup
    astore_3
    invokevirtual java/io/DataInputStream->readInt()I
    dup
    istore_0
    ifne 0x22
    aload_2
    getfield e->a:Ljava/util/Hashtable;
    invokevirtual java/util/Hashtable->clear()V
    aload_2
    getfield e->a:Ljava/util/Hashtable;
    getstatic e->c:Ljava/lang/String;
    getstatic e->a:I
    newarray 0x8
    invokevirtual java/util/Hashtable->put(Ljava/lang/Object;Ljava/lang/Object;)Ljava/lang/Object;
    pop
    aload_2
    aload_3
    invokevirtual java/io/DataInputStream->readUTF()Ljava/lang/String;
    invokespecial e->a(Ljava/lang/String;)V
    aload_3
    invokevirtual java/io/DataInputStream->close()V
    aload_2
    iload_0
    invokespecial e->a(I)V
    aload_2
    getfield e->c:I
    ifne 0x76
    aload_2
    getstatic e->a:Ljava/lang/String;
    invokespecial e->a(Ljava/lang/String;)Ljava/lang/String;
    ifnonnull 0x10
    aload_2
    getfield e->a:Ljava/util/Hashtable;
    getstatic e->a:Ljava/lang/String;
    ldc '0'
    invokevirtual java/util/Hashtable->put(Ljava/lang/Object;Ljava/lang/Object;)Ljava/lang/Object;
    pop
    aload_2
    invokespecial e->e()V
    goto 0x5f
    pop
    aload_2
    iload_0
    invokespecial e->a(I)V
    aload_2
    getfield e->c:I
    ifne 0x4b
    aload_2
    getstatic e->a:Ljava/lang/String;
    invokespecial e->a(Ljava/lang/String;)Ljava/lang/String;
    ifnonnull 0x10
    aload_2
    getfield e->a:Ljava/util/Hashtable;
    getstatic e->a:Ljava/lang/String;
    ldc '0'
    invokevirtual java/util/Hashtable->put(Ljava/lang/Object;Ljava/lang/Object;)Ljava/lang/Object;
    pop
    aload_2
    invokespecial e->e()V
    goto 0x34
    astore_1
    aload_2
    iload_0
    invokespecial e->a(I)V
    aload_2
    getfield e->c:I
    ifne 0x1e
    aload_2
    getstatic e->a:Ljava/lang/String;
    invokespecial e->a(Ljava/lang/String;)Ljava/lang/String;
    ifnonnull 0x10
    aload_2
    getfield e->a:Ljava/util/Hashtable;
    getstatic e->a:Ljava/lang/String;
    ldc '0'
    invokevirtual java/util/Hashtable->put(Ljava/lang/Object;Ljava/lang/Object;)Ljava/lang/Object;
    pop
    aload_2
    invokespecial e->e()V
    aload_1
    athrow
    goto 0x7
    aload_1
    invokespecial e->b()V
    aload_1
    areturn
    aconst_null
    areturn
.end method

.method public static c()Z
    .limit stack 5
    .limit locals 3
    getstatic e->g:Z
    ifne 0x5
    iconst_0
    ireturn
    new e
    dup
    invokespecial e-><init>()V
    dup
    astore_0
    iconst_2
    invokespecial e->a(B)Z
    ifeq 0x57
    aload_0
    astore_0
    iconst_m1
    istore_1
    aload_0
    getstatic e->u:Ljava/lang/String;
    ldc 'auth_mail'
    aconst_null
    iconst_2
    invokespecial e->a(Ljava/lang/String;Ljava/lang/String;Ljava/lang/String;I)[B
    dup
    astore_2
    ifnull 0x28
    new java/io/DataInputStream
    dup
    new java/io/ByteArrayInputStream
    dup
    aload_2
    invokespecial java/io/ByteArrayInputStream-><init>([B)V
    invokespecial java/io/DataInputStream-><init>(Ljava/io/InputStream;)V
    dup
    astore_2
    invokevirtual java/io/DataInputStream->readInt()I
    dup
    istore_1
    ifne 0xb
    aload_0
    aload_2
    invokevirtual java/io/DataInputStream->readUTF()Ljava/lang/String;
    invokespecial e->a(Ljava/lang/String;)V
    aload_2
    invokevirtual java/io/DataInputStream->close()V
    aload_0
    iload_1
    invokespecial e->a(I)V
    goto 0x14
    pop
    aload_0
    iload_1
    invokespecial e->a(I)V
    goto 0xb
    astore_2
    aload_0
    iload_1
    invokespecial e->a(I)V
    aload_2
    athrow
    iconst_1
    ireturn
    iconst_0
    ireturn
.end method

.method public static a()V
    .limit stack 1
    .limit locals 0
    aconst_null
    putstatic e->a:Le;
    return
.end method

.method private b()V
    .limit stack 5
    .limit locals 5
    iconst_m1
    istore_1
    aload_0
    getstatic e->u:Ljava/lang/String;
    ldc 'auth'
    ldc '&get_achievements'
    iconst_1
    invokespecial e->a(Ljava/lang/String;Ljava/lang/String;Ljava/lang/String;I)[B
    dup
    astore_2
    ifnull 0x64
    new java/io/DataInputStream
    dup
    new java/io/ByteArrayInputStream
    dup
    aload_2
    invokespecial java/io/ByteArrayInputStream-><init>([B)V
    invokespecial java/io/DataInputStream-><init>(Ljava/io/InputStream;)V
    dup
    astore_2
    invokevirtual java/io/DataInputStream->readInt()I
    dup
    istore_1
    ifne 0x47
    aload_2
    invokevirtual java/io/DataInputStream->readInt()I
    dup
    istore_3
    ifle 0x2f
    getstatic e->a:I
    newarray 0x8
    astore_3
    iconst_0
    istore 0x4
    iload 0x4
    getstatic e->a:I
    if_icmpge 0x12
    aload_3
    iload 0x4
    aload_2
    invokevirtual java/io/DataInputStream->read()I
    i2b
    bastore
    iinc 0x4 0x1
    goto -0x14
    aload_0
    getfield e->a:Ljava/util/Hashtable;
    getstatic e->c:Ljava/lang/String;
    aload_3
    invokevirtual java/util/Hashtable->put(Ljava/lang/Object;Ljava/lang/Object;)Ljava/lang/Object;
    pop
    aload_0
    aload_2
    invokevirtual java/io/DataInputStream->readUTF()Ljava/lang/String;
    invokespecial e->a(Ljava/lang/String;)V
    goto 0x7
    pop
    ldc 1000019
    istore_1
    aload_2
    invokevirtual java/io/DataInputStream->close()V
    aload_0
    iload_1
    invokespecial e->a(I)V
    aload_0
    getfield e->c:I
    ifne 0x2d
    aload_0
    invokespecial e->e()V
    return
    pop
    aload_0
    iload_1
    invokespecial e->a(I)V
    aload_0
    getfield e->c:I
    ifne 0x1b
    aload_0
    invokespecial e->e()V
    return
    astore_2
    aload_0
    iload_1
    invokespecial e->a(I)V
    aload_0
    getfield e->c:I
    ifne 0x7
    aload_0
    invokespecial e->e()V
    aload_2
    athrow
    return
.end method

.method public final a(Ljava/lang/String;Ljava/lang/String;II)[Ljava/lang/String;
    .limit stack 5
    .limit locals 5
    iconst_m1
    istore_3
    aconst_null
    astore 0x4
    new java/lang/StringBuffer
    dup
    invokespecial java/lang/StringBuffer-><init>()V
    ldc '&fields='
    invokevirtual java/lang/StringBuffer->append(Ljava/lang/String;)Ljava/lang/StringBuffer;
    aload_1
    invokestatic e->b(Ljava/lang/String;)Ljava/lang/String;
    invokevirtual java/lang/StringBuffer->append(Ljava/lang/String;)Ljava/lang/StringBuffer;
    ldc '&sort='
    invokevirtual java/lang/StringBuffer->append(Ljava/lang/String;)Ljava/lang/StringBuffer;
    aload_2
    invokevirtual java/lang/StringBuffer->append(Ljava/lang/String;)Ljava/lang/StringBuffer;
    new java/lang/StringBuffer
    dup
    invokespecial java/lang/StringBuffer-><init>()V
    ldc '&offset='
    invokevirtual java/lang/StringBuffer->append(Ljava/lang/String;)Ljava/lang/StringBuffer;
    iconst_0
    invokevirtual java/lang/StringBuffer->append(I)Ljava/lang/StringBuffer;
    ldc '&count='
    invokevirtual java/lang/StringBuffer->append(Ljava/lang/String;)Ljava/lang/StringBuffer;
    sipush 0x3e8
    invokevirtual java/lang/StringBuffer->append(I)Ljava/lang/StringBuffer;
    invokevirtual java/lang/StringBuffer->toString()Ljava/lang/String;
    invokevirtual java/lang/StringBuffer->append(Ljava/lang/String;)Ljava/lang/StringBuffer;
    invokevirtual java/lang/StringBuffer->toString()Ljava/lang/String;
    astore_1
    aload_0
    getstatic e->t:Ljava/lang/String;
    ldc 'list'
    aload_1
    iconst_1
    invokespecial e->a(Ljava/lang/String;Ljava/lang/String;Ljava/lang/String;I)[B
    dup
    astore_1
    ifnull 0x51
    new java/io/DataInputStream
    dup
    new java/io/ByteArrayInputStream
    dup
    aload_1
    invokespecial java/io/ByteArrayInputStream-><init>([B)V
    invokespecial java/io/DataInputStream-><init>(Ljava/io/InputStream;)V
    dup
    astore_1
    invokevirtual java/io/DataInputStream->readInt()I
    dup
    istore_3
    ifne 0x34
    aload_1
    invokevirtual java/io/DataInputStream->readInt()I
    dup
    istore_2
    anewarray java/lang/String
    astore 0x4
    iconst_0
    istore_2
    iload_2
    aload 0x4
    arraylength
    if_icmpge 0x11
    aload 0x4
    iload_2
    aload_1
    invokevirtual java/io/DataInputStream->readUTF()Ljava/lang/String;
    aastore
    iinc 0x2 0x1
    goto -0x12
    aload_0
    aload_1
    invokevirtual java/io/DataInputStream->readUTF()Ljava/lang/String;
    invokespecial e->a(Ljava/lang/String;)V
    goto 0x7
    pop
    ldc 1000010
    istore_3
    aload_1
    invokevirtual java/io/DataInputStream->close()V
    aload_0
    iload_3
    invokespecial e->a(I)V
    goto 0x14
    pop
    aload_0
    iload_3
    invokespecial e->a(I)V
    goto 0xb
    astore_1
    aload_0
    iload_3
    invokespecial e->a(I)V
    aload_1
    athrow
    aload 0x4
    areturn
.end method

.method public final a(I)[B
    .limit stack 5
    .limit locals 5
    iconst_m1
    istore_2
    aconst_null
    astore_3
    aload_0
    getstatic e->t:Ljava/lang/String;
    ldc 'download'
    new java/lang/StringBuffer
    dup
    invokespecial java/lang/StringBuffer-><init>()V
    ldc '&id='
    invokevirtual java/lang/StringBuffer->append(Ljava/lang/String;)Ljava/lang/StringBuffer;
    iload_1
    invokevirtual java/lang/StringBuffer->append(I)Ljava/lang/StringBuffer;
    invokevirtual java/lang/StringBuffer->toString()Ljava/lang/String;
    iconst_1
    invokespecial e->a(Ljava/lang/String;Ljava/lang/String;Ljava/lang/String;I)[B
    dup
    astore_1
    ifnull 0x3e
    new java/io/DataInputStream
    dup
    new java/io/ByteArrayInputStream
    dup
    aload_1
    invokespecial java/io/ByteArrayInputStream-><init>([B)V
    invokespecial java/io/DataInputStream-><init>(Ljava/io/InputStream;)V
    dup
    astore_1
    invokevirtual java/io/DataInputStream->readInt()I
    dup
    istore_2
    ifne 0x21
    aload_1
    invokevirtual java/io/DataInputStream->readInt()I
    dup
    istore 0x4
    newarray 0x8
    astore_3
    aload_1
    aload_3
    invokevirtual java/io/DataInputStream->readFully([B)V
    aload_0
    aload_1
    invokevirtual java/io/DataInputStream->readUTF()Ljava/lang/String;
    invokespecial e->a(Ljava/lang/String;)V
    goto 0x7
    pop
    ldc 1000011
    istore_2
    aload_1
    invokevirtual java/io/DataInputStream->close()V
    aload_0
    iload_2
    invokespecial e->a(I)V
    goto 0x14
    pop
    aload_0
    iload_2
    invokespecial e->a(I)V
    goto 0xb
    astore_1
    aload_0
    iload_2
    invokespecial e->a(I)V
    aload_1
    athrow
    aload_3
    areturn
.end method

.method public final a(Z)I
    .limit stack 4
    .limit locals 3
    iconst_0
    istore_2
    getstatic e->e:Z
    ifne 0x20
    iload_1
    ifne 0xd
    aload_0
    getstatic e->a:Ljava/lang/String;
    invokespecial e->a(Ljava/lang/String;)Ljava/lang/String;
    ifnonnull 0x7
    aload_0
    invokespecial e->b()V
    aload_0
    getstatic e->a:Ljava/lang/String;
    invokespecial e->a(Ljava/lang/String;)Ljava/lang/String;
    astore_1
    goto 0x10
    getstatic e->b:Ljava/util/Hashtable;
    aload_0
    getfield e->a:[Ljava/lang/String;
    iconst_0
    aaload
    invokevirtual java/util/Hashtable->get(Ljava/lang/Object;)Ljava/lang/Object;
    astore_1
    aload_1
    invokevirtual java/lang/Object->toString()Ljava/lang/String;
    invokestatic java/lang/Integer->parseInt(Ljava/lang/String;)I
    istore_2
    goto 0x4
    pop
    aload_0
    getfield e->a:Ljava/util/Hashtable;
    getstatic e->a:Ljava/lang/String;
    new java/lang/StringBuffer
    dup
    invokespecial java/lang/StringBuffer-><init>()V
    ldc ''
    invokevirtual java/lang/StringBuffer->append(Ljava/lang/String;)Ljava/lang/StringBuffer;
    iload_2
    invokevirtual java/lang/StringBuffer->append(I)Ljava/lang/StringBuffer;
    invokevirtual java/lang/StringBuffer->toString()Ljava/lang/String;
    invokevirtual java/util/Hashtable->put(Ljava/lang/Object;Ljava/lang/Object;)Ljava/lang/Object;
    pop
    iload_2
    ireturn
.end method

.method private b(Z)I
    .limit stack 2
    .limit locals 2
    iconst_m1
    istore_1
    aload_0
    getstatic e->b:Ljava/lang/String;
    invokespecial e->a(Ljava/lang/String;)Ljava/lang/String;
    ifnonnull 0x7
    aload_0
    invokespecial e->b()V
    aload_0
    getstatic e->b:Ljava/lang/String;
    invokespecial e->a(Ljava/lang/String;)Ljava/lang/String;
    invokestatic java/lang/Integer->parseInt(Ljava/lang/String;)I
    istore_1
    goto 0x4
    pop
    iload_1
    ireturn
.end method

.method public final a()Ljava/lang/String;
    .limit stack 3
    .limit locals 1
    getstatic e->e:Z
    ifeq 0x6
    ldc ''
    areturn
    new java/lang/StringBuffer
    dup
    invokespecial java/lang/StringBuffer-><init>()V
    ldc ''
    invokevirtual java/lang/StringBuffer->append(Ljava/lang/String;)Ljava/lang/StringBuffer;
    aload_0
    iconst_0
    invokespecial e->b(Z)I
    invokevirtual java/lang/StringBuffer->append(I)Ljava/lang/StringBuffer;
    invokevirtual java/lang/StringBuffer->toString()Ljava/lang/String;
    areturn
.end method

.method public final a(I)I
    .limit stack 4
    .limit locals 3
    iconst_0
    istore_2
    getstatic e->e:Z
    ifeq 0x3a
    aload_0
    iconst_0
    invokevirtual e->a(Z)I
    istore_2
    goto 0x4
    pop
    iload_2
    iload_1
    iadd
    dup
    istore_2
    ifge 0x5
    iconst_0
    istore_2
    getstatic e->b:Ljava/util/Hashtable;
    aload_0
    getfield e->a:[Ljava/lang/String;
    iconst_0
    aaload
    new java/lang/StringBuffer
    dup
    invokespecial java/lang/StringBuffer-><init>()V
    ldc ''
    invokevirtual java/lang/StringBuffer->append(Ljava/lang/String;)Ljava/lang/StringBuffer;
    iload_2
    invokevirtual java/lang/StringBuffer->append(I)Ljava/lang/StringBuffer;
    invokevirtual java/lang/StringBuffer->toString()Ljava/lang/String;
    invokevirtual java/util/Hashtable->put(Ljava/lang/Object;Ljava/lang/Object;)Ljava/lang/Object;
    pop
    invokestatic e->c()V
    iload_2
    ireturn
.end method

.method public final a([B)[B
    .limit stack 7
    .limit locals 5
    iconst_m1
    istore_2
    getstatic e->a:I
    newarray 0x8
    astore_3
    aload_0
    getstatic e->u:Ljava/lang/String;
    ldc 'achievements'
    aload_1
    ifnull 0x2e
    aload_1
    arraylength
    getstatic e->a:I
    if_icmpne 0x26
    new java/lang/StringBuffer
    dup
    invokespecial java/lang/StringBuffer-><init>()V
    ldc '&achievements='
    invokevirtual java/lang/StringBuffer->append(Ljava/lang/String;)Ljava/lang/StringBuffer;
    new java/lang/String
    dup
    aload_1
    invokestatic b->a([B)[C
    invokespecial java/lang/String-><init>([C)V
    invokestatic e->b(Ljava/lang/String;)Ljava/lang/String;
    invokevirtual java/lang/StringBuffer->append(Ljava/lang/String;)Ljava/lang/StringBuffer;
    invokevirtual java/lang/StringBuffer->toString()Ljava/lang/String;
    goto 0x5
    ldc ''
    iconst_1
    invokespecial e->a(Ljava/lang/String;Ljava/lang/String;Ljava/lang/String;I)[B
    dup
    astore_1
    ifnull 0x5f
    new java/io/DataInputStream
    dup
    new java/io/ByteArrayInputStream
    dup
    aload_1
    invokespecial java/io/ByteArrayInputStream-><init>([B)V
    invokespecial java/io/DataInputStream-><init>(Ljava/io/InputStream;)V
    dup
    astore_1
    invokevirtual java/io/DataInputStream->readInt()I
    dup
    istore_2
    ifne 0x42
    aload_1
    invokevirtual java/io/DataInputStream->readInt()I
    dup
    istore 0x4
    ifle 0x1d
    iconst_0
    istore 0x4
    iload 0x4
    getstatic e->a:I
    if_icmpge 0x12
    aload_3
    iload 0x4
    aload_1
    invokevirtual java/io/DataInputStream->read()I
    i2b
    bastore
    iinc 0x4 0x1
    goto -0x14
    aload_0
    getfield e->a:Ljava/util/Hashtable;
    getstatic e->c:Ljava/lang/String;
    aload_3
    invokevirtual java/util/Hashtable->put(Ljava/lang/Object;Ljava/lang/Object;)Ljava/lang/Object;
    pop
    aload_0
    aload_1
    invokevirtual java/io/DataInputStream->readUTF()Ljava/lang/String;
    invokespecial e->a(Ljava/lang/String;)V
    goto 0x7
    pop
    ldc 1000013
    istore_2
    aload_1
    invokevirtual java/io/DataInputStream->close()V
    aload_0
    iload_2
    invokespecial e->a(I)V
    goto 0x14
    pop
    aload_0
    iload_2
    invokespecial e->a(I)V
    goto 0xb
    astore_1
    aload_0
    iload_2
    invokespecial e->a(I)V
    aload_1
    athrow
    aload_3
    areturn
.end method

.method public final a(I)Z
    .limit stack 3
    .limit locals 3
    aload_0
    aconst_null
    invokevirtual e->a([B)[B
    dup
    astore_2
    iload_1
    baload
    iconst_1
    if_icmpeq 0xf
    aload_2
    iload_1
    iconst_1
    bastore
    aload_0
    aload_2
    invokevirtual e->a([B)[B
    pop
    iconst_1
    ireturn
    iconst_0
    ireturn
.end method

.method public final a(Z)[B
    .limit stack 2
    .limit locals 2
    aload_0
    getfield e->a:Ljava/util/Hashtable;
    getstatic e->c:Ljava/lang/String;
    invokevirtual java/util/Hashtable->get(Ljava/lang/Object;)Ljava/lang/Object;
    ifnonnull 0x9
    aload_0
    aconst_null
    invokevirtual e->a([B)[B
    pop
    aload_0
    getfield e->a:Ljava/util/Hashtable;
    getstatic e->c:Ljava/lang/String;
    invokevirtual java/util/Hashtable->get(Ljava/lang/Object;)Ljava/lang/Object;
    checkcast [B
    dup
    astore_1
    ifnull 0xb
    aload_1
    arraylength
    getstatic e->a:I
    if_icmpeq 0x9
    getstatic e->a:I
    newarray 0x8
    astore_1
    aload_1
    areturn
.end method

.method public final b()Ljava/lang/String;
    .limit stack 4
    .limit locals 3
    getstatic e->o:Ljava/lang/String;
    invokestatic a->a(Ljava/lang/String;)Ljava/lang/String;
    dup
    astore_1
    ifnull 0x4b
    aload_1
    ldc '[L]'
    aload_0
    getfield e->a:[Ljava/lang/String;
    iconst_0
    aaload
    invokestatic e->b(Ljava/lang/String;)Ljava/lang/String;
    invokestatic a->a(Ljava/lang/String;Ljava/lang/String;Ljava/lang/String;)Ljava/lang/String;
    dup
    astore_1
    ldc '[P]'
    aload_0
    getfield e->a:[Ljava/lang/String;
    iconst_1
    aaload
    invokestatic e->b(Ljava/lang/String;)Ljava/lang/String;
    invokestatic a->a(Ljava/lang/String;Ljava/lang/String;Ljava/lang/String;)Ljava/lang/String;
    dup
    astore_1
    ldc '[PP]'
    invokevirtual java/lang/String->indexOf(Ljava/lang/String;)I
    iflt 0x22
    aconst_null
    astore_2
    aload_0
    iconst_1
    invokespecial e->a(Z)Ljava/lang/String;
    astore_2
    goto 0x4
    pop
    aload_0
    getfield e->a:Ljava/util/Hashtable;
    getstatic e->f:Ljava/lang/String;
    invokevirtual java/util/Hashtable->remove(Ljava/lang/Object;)Ljava/lang/Object;
    pop
    aload_1
    ldc '[PP]'
    aload_2
    invokestatic a->a(Ljava/lang/String;Ljava/lang/String;Ljava/lang/String;)Ljava/lang/String;
    astore_1
    aload_1
    areturn
.end method

.method private a(Ljava/lang/String;)Ljava/lang/String;
    .limit stack 2
    .limit locals 2
    aload_0
    getfield e->a:Ljava/util/Hashtable;
    aload_1
    invokevirtual java/util/Hashtable->get(Ljava/lang/Object;)Ljava/lang/Object;
    checkcast java/lang/String
    areturn
.end method

.method public final getMessage()Ljava/lang/String;
    .limit stack 1
    .limit locals 1
    aload_0
    getfield e->y:Ljava/lang/String;
    areturn
.end method

.method public final a()I
    .limit stack 1
    .limit locals 1
    aload_0
    getfield e->c:I
    ireturn
.end method

.method private static c()V
    .limit stack 4
    .limit locals 5
    getstatic e->g:Z
    ifne 0x4
    return
    getstatic e->w:Ljava/lang/String;
    invokestatic javax/microedition/rms/RecordStore->deleteRecordStore(Ljava/lang/String;)V
    goto 0x4
    pop
    getstatic e->w:Ljava/lang/String;
    iconst_1
    invokestatic javax/microedition/rms/RecordStore->openRecordStore(Ljava/lang/String;Z)Ljavax/microedition/rms/RecordStore;
    astore_0
    new java/io/ByteArrayOutputStream
    dup
    invokespecial java/io/ByteArrayOutputStream-><init>()V
    astore_1
    new java/io/DataOutputStream
    dup
    aload_1
    invokespecial java/io/DataOutputStream-><init>(Ljava/io/OutputStream;)V
    dup
    astore_2
    getstatic e->d:[Ljava/lang/String;
    iconst_0
    aaload
    invokestatic e->a(Ljava/io/DataOutputStream;Ljava/lang/String;)V
    aload_2
    getstatic e->d:[Ljava/lang/String;
    iconst_1
    aaload
    invokestatic e->a(Ljava/io/DataOutputStream;Ljava/lang/String;)V
    aload_2
    getstatic e->d:I
    invokevirtual java/io/DataOutputStream->writeInt(I)V
    getstatic e->e:Z
    ifeq 0x40
    aload_2
    getstatic e->b:Ljava/util/Hashtable;
    invokevirtual java/util/Hashtable->size()I
    invokevirtual java/io/DataOutputStream->writeByte(I)V
    getstatic e->b:Ljava/util/Hashtable;
    invokevirtual java/util/Hashtable->keys()Ljava/util/Enumeration;
    astore_3
    aload_3
    invokeinterface java/util/Enumeration->hasMoreElements()Z
    ifeq 0x26
    aload_3
    invokeinterface java/util/Enumeration->nextElement()Ljava/lang/Object;
    checkcast java/lang/String
    astore 0x4
    aload_2
    aload 0x4
    invokestatic e->a(Ljava/io/DataOutputStream;Ljava/lang/String;)V
    aload_2
    getstatic e->b:Ljava/util/Hashtable;
    aload 0x4
    invokevirtual java/util/Hashtable->get(Ljava/lang/Object;)Ljava/lang/Object;
    invokevirtual java/lang/Object->toString()Ljava/lang/String;
    invokestatic e->a(Ljava/io/DataOutputStream;Ljava/lang/String;)V
    goto -0x29
    aload_1
    invokevirtual java/io/ByteArrayOutputStream->toByteArray()[B
    astore_3
    aload_2
    invokevirtual java/io/DataOutputStream->close()V
    aload_0
    aload_3
    iconst_0
    aload_3
    arraylength
    invokevirtual javax/microedition/rms/RecordStore->addRecord([BII)I
    pop
    aload_0
    invokevirtual javax/microedition/rms/RecordStore->closeRecordStore()V
    return
    pop
    return
.end method

.method private static d()V
    .limit stack 3
    .limit locals 5
    getstatic e->g:Z
    ifne 0x4
    return
    getstatic e->w:Ljava/lang/String;
    iconst_1
    invokestatic javax/microedition/rms/RecordStore->openRecordStore(Ljava/lang/String;Z)Ljavax/microedition/rms/RecordStore;
    dup
    astore_0
    invokevirtual javax/microedition/rms/RecordStore->getNumRecords()I
    ifle 0x71
    aload_0
    iconst_1
    invokevirtual javax/microedition/rms/RecordStore->getRecord(I)[B
    astore_1
    new java/io/ByteArrayInputStream
    dup
    aload_1
    invokespecial java/io/ByteArrayInputStream-><init>([B)V
    astore_1
    new java/io/DataInputStream
    dup
    aload_1
    invokespecial java/io/DataInputStream-><init>(Ljava/io/InputStream;)V
    astore_1
    getstatic e->d:[Ljava/lang/String;
    iconst_0
    aload_1
    invokestatic e->a(Ljava/io/DataInputStream;)Ljava/lang/String;
    aastore
    getstatic e->d:[Ljava/lang/String;
    iconst_1
    aload_1
    invokestatic e->a(Ljava/io/DataInputStream;)Ljava/lang/String;
    aastore
    aload_1
    invokevirtual java/io/DataInputStream->readInt()I
    putstatic e->d:I
    getstatic e->e:Z
    ifeq 0x32
    aload_1
    invokevirtual java/io/DataInputStream->readByte()B
    dup
    istore_2
    ifle 0x29
    getstatic e->b:Ljava/util/Hashtable;
    invokevirtual java/util/Hashtable->clear()V
    iconst_0
    istore_3
    iload_3
    iload_2
    if_icmpge 0x1c
    aload_1
    invokestatic e->a(Ljava/io/DataInputStream;)Ljava/lang/String;
    astore 0x4
    getstatic e->b:Ljava/util/Hashtable;
    aload 0x4
    aload_1
    invokestatic e->a(Ljava/io/DataInputStream;)Ljava/lang/String;
    invokevirtual java/util/Hashtable->put(Ljava/lang/Object;Ljava/lang/Object;)Ljava/lang/Object;
    pop
    iinc 0x3 0x1
    goto -0x1b
    goto 0x4
    pop
    aload_1
    invokevirtual java/io/DataInputStream->close()V
    aload_0
    invokevirtual javax/microedition/rms/RecordStore->closeRecordStore()V
    return
    pop
    return
.end method

.method private a(Z)Ljava/lang/String;
    .limit stack 3
    .limit locals 2
    aload_0
    iload_1
    invokespecial e->b(Z)Ljava/lang/String;
    dup
    astore_1
    ifnull 0x22
    new java/lang/StringBuffer
    dup
    invokespecial java/lang/StringBuffer-><init>()V
    aload_1
    invokevirtual java/lang/StringBuffer->append(Ljava/lang/String;)Ljava/lang/StringBuffer;
    aload_0
    getfield e->a:[Ljava/lang/String;
    iconst_1
    aaload
    invokevirtual java/lang/StringBuffer->append(Ljava/lang/String;)Ljava/lang/StringBuffer;
    invokevirtual java/lang/StringBuffer->toString()Ljava/lang/String;
    iconst_0
    invokestatic e->a(Ljava/lang/String;Z)[B
    invokestatic d->a([B)Ljava/lang/String;
    areturn
    aconst_null
    areturn
.end method

.method private b(Z)Ljava/lang/String;
    .limit stack 5
    .limit locals 5
    aload_0
    getstatic e->f:Ljava/lang/String;
    invokespecial e->a(Ljava/lang/String;)Ljava/lang/String;
    astore_2
    lconst_0
    lstore_3
    aload_0
    getstatic e->g:Ljava/lang/String;
    invokespecial e->a(Ljava/lang/String;)Ljava/lang/String;
    invokestatic java/lang/Long->parseLong(Ljava/lang/String;)J
    lstore_3
    goto 0x4
    pop
    iload_1
    ifne 0x16
    aload_2
    ifnull 0x12
    invokestatic java/lang/System->currentTimeMillis()J
    lload_3
    lsub
    invokestatic java/lang/Math->abs(J)J
    ldc2_w 600000
    lcmp
    ifle 0x5f
    aconst_null
    astore_2
    aload_0
    getfield e->a:Ljava/util/Hashtable;
    getstatic e->f:Ljava/lang/String;
    invokevirtual java/util/Hashtable->remove(Ljava/lang/Object;)Ljava/lang/Object;
    pop
    aload_0
    getfield e->a:Ljava/util/Hashtable;
    getstatic e->g:Ljava/lang/String;
    invokevirtual java/util/Hashtable->remove(Ljava/lang/Object;)Ljava/lang/Object;
    pop
    aload_0
    getstatic e->v:Ljava/lang/String;
    aconst_null
    aconst_null
    iconst_2
    invokespecial e->a(Ljava/lang/String;Ljava/lang/String;Ljava/lang/String;I)[B
    dup
    astore_1
    ifnull 0x38
    new java/lang/String
    dup
    aload_1
    invokespecial java/lang/String-><init>([B)V
    astore_2
    aload_0
    getfield e->a:Ljava/util/Hashtable;
    getstatic e->f:Ljava/lang/String;
    aload_2
    invokevirtual java/util/Hashtable->put(Ljava/lang/Object;Ljava/lang/Object;)Ljava/lang/Object;
    pop
    aload_0
    getfield e->a:Ljava/util/Hashtable;
    getstatic e->g:Ljava/lang/String;
    new java/lang/StringBuffer
    dup
    invokespecial java/lang/StringBuffer-><init>()V
    ldc ''
    invokevirtual java/lang/StringBuffer->append(Ljava/lang/String;)Ljava/lang/StringBuffer;
    invokestatic java/lang/System->currentTimeMillis()J
    invokevirtual java/lang/StringBuffer->append(J)Ljava/lang/StringBuffer;
    invokevirtual java/lang/StringBuffer->toString()Ljava/lang/String;
    invokevirtual java/util/Hashtable->put(Ljava/lang/Object;Ljava/lang/Object;)Ljava/lang/Object;
    pop
    aload_2
    areturn
.end method

.method private a(Ljava/lang/String;Ljava/lang/String;Ljava/lang/String;I)[B
    .limit stack 5
    .limit locals 7
    getstatic e->g:Z
    ifeq 0x7
    aload_1
    ifnonnull 0x5
    aconst_null
    areturn
    getstatic e->p:Ljava/lang/String;
    invokestatic a->a(Ljava/lang/String;)Ljava/lang/String;
    dup
    astore 0x5
    ifnull 0x11
    aload 0x5
    invokevirtual java/lang/String->trim()Ljava/lang/String;
    invokevirtual java/lang/String->length()I
    ifne 0x6
    aconst_null
    astore 0x5
    aconst_null
    astore 0x6
    iload 0x4
    ifne 0x11
    aload_0
    getfield e->a:[Ljava/lang/String;
    iconst_1
    aaload
    invokestatic e->b(Ljava/lang/String;)Ljava/lang/String;
    astore 0x6
    goto 0x1c
    iload 0x4
    iconst_1
    if_icmpne 0x16
    aload_0
    iconst_0
    invokespecial e->a(Z)Ljava/lang/String;
    dup
    astore 0x6
    ifnonnull 0xb
    new java/lang/Exception
    dup
    invokespecial java/lang/Exception-><init>()V
    athrow
    new java/lang/StringBuffer
    dup
    invokespecial java/lang/StringBuffer-><init>()V
    ldc 'login='
    invokevirtual java/lang/StringBuffer->append(Ljava/lang/String;)Ljava/lang/StringBuffer;
    aload_0
    getfield e->a:[Ljava/lang/String;
    iconst_0
    aaload
    invokestatic e->b(Ljava/lang/String;)Ljava/lang/String;
    invokevirtual java/lang/StringBuffer->append(Ljava/lang/String;)Ljava/lang/StringBuffer;
    aload_1
    getstatic e->v:Ljava/lang/String;
    if_acmpne 0x8
    ldc ''
    goto 0x82
    new java/lang/StringBuffer
    dup
    invokespecial java/lang/StringBuffer-><init>()V
    ldc '&app='
    invokevirtual java/lang/StringBuffer->append(Ljava/lang/String;)Ljava/lang/StringBuffer;
    getstatic e->A:Ljava/lang/String;
    invokestatic e->b(Ljava/lang/String;)Ljava/lang/String;
    invokevirtual java/lang/StringBuffer->append(Ljava/lang/String;)Ljava/lang/StringBuffer;
    ldc '&language='
    invokevirtual java/lang/StringBuffer->append(Ljava/lang/String;)Ljava/lang/StringBuffer;
    getstatic e->z:Ljava/lang/String;
    invokevirtual java/lang/StringBuffer->append(Ljava/lang/String;)Ljava/lang/StringBuffer;
    ldc '&uid='
    invokevirtual java/lang/StringBuffer->append(Ljava/lang/String;)Ljava/lang/StringBuffer;
    getstatic e->d:I
    invokevirtual java/lang/StringBuffer->append(I)Ljava/lang/StringBuffer;
    ldc '&game_id='
    invokevirtual java/lang/StringBuffer->append(Ljava/lang/String;)Ljava/lang/StringBuffer;
    getstatic e->B:Ljava/lang/String;
    invokevirtual java/lang/StringBuffer->append(Ljava/lang/String;)Ljava/lang/StringBuffer;
    aload 0x6
    ifnonnull 0x8
    ldc ''
    goto 0x17
    new java/lang/StringBuffer
    dup
    invokespecial java/lang/StringBuffer-><init>()V
    ldc '&password='
    invokevirtual java/lang/StringBuffer->append(Ljava/lang/String;)Ljava/lang/StringBuffer;
    aload 0x6
    invokevirtual java/lang/StringBuffer->append(Ljava/lang/String;)Ljava/lang/StringBuffer;
    invokevirtual java/lang/StringBuffer->toString()Ljava/lang/String;
    invokevirtual java/lang/StringBuffer->append(Ljava/lang/String;)Ljava/lang/StringBuffer;
    getstatic e->e:Z
    ifeq 0x1d
    new java/lang/StringBuffer
    dup
    invokespecial java/lang/StringBuffer-><init>()V
    ldc '&ec='
    invokevirtual java/lang/StringBuffer->append(Ljava/lang/String;)Ljava/lang/StringBuffer;
    aload_0
    iconst_0
    invokevirtual e->a(Z)I
    invokevirtual java/lang/StringBuffer->append(I)Ljava/lang/StringBuffer;
    invokevirtual java/lang/StringBuffer->toString()Ljava/lang/String;
    goto 0x5
    ldc ''
    invokevirtual java/lang/StringBuffer->append(Ljava/lang/String;)Ljava/lang/StringBuffer;
    invokevirtual java/lang/StringBuffer->toString()Ljava/lang/String;
    invokevirtual java/lang/StringBuffer->append(Ljava/lang/String;)Ljava/lang/StringBuffer;
    aload_2
    ifnonnull 0x8
    ldc ''
    goto 0x16
    new java/lang/StringBuffer
    dup
    invokespecial java/lang/StringBuffer-><init>()V
    ldc '&action='
    invokevirtual java/lang/StringBuffer->append(Ljava/lang/String;)Ljava/lang/StringBuffer;
    aload_2
    invokevirtual java/lang/StringBuffer->append(Ljava/lang/String;)Ljava/lang/StringBuffer;
    invokevirtual java/lang/StringBuffer->toString()Ljava/lang/String;
    invokevirtual java/lang/StringBuffer->append(Ljava/lang/String;)Ljava/lang/StringBuffer;
    aload 0x5
    ifnonnull 0x8
    ldc ''
    goto 0x17
    new java/lang/StringBuffer
    dup
    invokespecial java/lang/StringBuffer-><init>()V
    ldc '&system='
    invokevirtual java/lang/StringBuffer->append(Ljava/lang/String;)Ljava/lang/StringBuffer;
    aload 0x5
    invokevirtual java/lang/StringBuffer->append(Ljava/lang/String;)Ljava/lang/StringBuffer;
    invokevirtual java/lang/StringBuffer->toString()Ljava/lang/String;
    invokevirtual java/lang/StringBuffer->append(Ljava/lang/String;)Ljava/lang/StringBuffer;
    aload_3
    ifnonnull 0x8
    ldc ''
    goto 0x4
    aload_3
    invokevirtual java/lang/StringBuffer->append(Ljava/lang/String;)Ljava/lang/StringBuffer;
    invokevirtual java/lang/StringBuffer->toString()Ljava/lang/String;
    astore 0x5
    aconst_null
    astore 0x6
    getstatic e->x:Ljava/lang/String;
    ldc 'GET'
    if_acmpne 0x2e
    new java/lang/StringBuffer
    dup
    invokespecial java/lang/StringBuffer-><init>()V
    aload_1
    invokevirtual java/lang/StringBuffer->append(Ljava/lang/String;)Ljava/lang/StringBuffer;
    aload_1
    ldc '?'
    invokevirtual java/lang/String->indexOf(Ljava/lang/String;)I
    iconst_m1
    if_icmpne 0x8
    ldc '?'
    goto 0x5
    ldc '&'
    invokevirtual java/lang/StringBuffer->append(Ljava/lang/String;)Ljava/lang/StringBuffer;
    aload 0x5
    invokevirtual java/lang/StringBuffer->append(Ljava/lang/String;)Ljava/lang/StringBuffer;
    invokevirtual java/lang/StringBuffer->toString()Ljava/lang/String;
    astore_1
    goto 0xa
    aload 0x5
    invokevirtual java/lang/String->getBytes()[B
    astore 0x6
    aload_1
    getstatic e->x:Ljava/lang/String;
    aload 0x6
    invokestatic e->a(Ljava/lang/String;Ljava/lang/String;[B)[B
    astore 0x5
    aload_0
    getfield e->f:Z
    ifne 0x47
    iload 0x4
    iconst_1
    if_icmpne 0x41
    aload 0x5
    ifnull 0x3c
    aload 0x5
    arraylength
    iconst_3
    if_icmple 0x35
    aload 0x5
    iconst_3
    baload
    bipush 0xc
    if_icmpne 0x2c
    aload_0
    getfield e->a:Ljava/util/Hashtable;
    getstatic e->f:Ljava/lang/String;
    invokevirtual java/util/Hashtable->remove(Ljava/lang/Object;)Ljava/lang/Object;
    pop
    aload_0
    iconst_1
    putfield e->f:Z
    aload_0
    aload_1
    aload_2
    aload_3
    iload 0x4
    invokespecial e->a(Ljava/lang/String;Ljava/lang/String;Ljava/lang/String;I)[B
    astore_1
    aload_0
    iconst_0
    putfield e->f:Z
    aload_1
    areturn
    astore_1
    aload_0
    iconst_0
    putfield e->f:Z
    aload_1
    athrow
    aload 0x5
    areturn
.end method

.method private a(Ljava/lang/String;)V
    .limit stack 6
    .limit locals 5
    aload_1
    ifnull 0xd1
    aload_1
    bipush 0x3b
    invokestatic a->a(Ljava/lang/String;C)[Ljava/lang/String;
    astore_1
    iconst_0
    istore_2
    iload_2
    aload_1
    arraylength
    if_icmpge 0xc2
    aload_1
    iload_2
    aaload
    bipush 0x3a
    invokestatic a->a(Ljava/lang/String;C)[Ljava/lang/String;
    dup
    astore_3
    ifnull 0xaf
    aload_3
    arraylength
    iconst_2
    if_icmpne 0xa9
    aload_0
    getfield e->a:Ljava/util/Hashtable;
    aload_3
    iconst_0
    aload_3
    iconst_0
    aaload
    invokevirtual java/lang/String->trim()Ljava/lang/String;
    dup_x2
    aastore
    aload_3
    iconst_1
    aload_3
    iconst_1
    aaload
    invokevirtual java/lang/String->trim()Ljava/lang/String;
    dup_x2
    aastore
    invokevirtual java/util/Hashtable->put(Ljava/lang/Object;Ljava/lang/Object;)Ljava/lang/Object;
    pop
    getstatic e->f:Ljava/lang/String;
    aload_3
    iconst_0
    aaload
    invokevirtual java/lang/String->equals(Ljava/lang/Object;)Z
    ifeq 0x26
    aload_0
    getfield e->a:Ljava/util/Hashtable;
    getstatic e->g:Ljava/lang/String;
    new java/lang/StringBuffer
    dup
    invokespecial java/lang/StringBuffer-><init>()V
    ldc ''
    invokevirtual java/lang/StringBuffer->append(Ljava/lang/String;)Ljava/lang/StringBuffer;
    invokestatic java/lang/System->currentTimeMillis()J
    invokevirtual java/lang/StringBuffer->append(J)Ljava/lang/StringBuffer;
    invokevirtual java/lang/StringBuffer->toString()Ljava/lang/String;
    invokevirtual java/util/Hashtable->put(Ljava/lang/Object;Ljava/lang/Object;)Ljava/lang/Object;
    pop
    goto 0x5e
    getstatic e->e:Z
    ifeq 0x58
    aload_0
    astore 0x4
    getstatic e->C:Ljava/lang/String;
    ifnull 0x17
    getstatic e->C:Ljava/lang/String;
    aload 0x4
    getfield e->a:[Ljava/lang/String;
    iconst_0
    aaload
    invokevirtual java/lang/String->equals(Ljava/lang/Object;)Z
    ifeq 0x7
    iconst_1
    goto 0x4
    iconst_0
    ifeq 0x37
    getstatic e->a:Ljava/lang/String;
    aload_3
    iconst_0
    aaload
    invokevirtual java/lang/String->equals(Ljava/lang/Object;)Z
    ifeq 0x2b
    aload_0
    iconst_0
    invokevirtual e->a(Z)I
    istore 0x4
    getstatic e->b:Ljava/util/Hashtable;
    aload_0
    getfield e->a:[Ljava/lang/String;
    iconst_0
    aaload
    aload_3
    iconst_1
    aaload
    invokevirtual java/util/Hashtable->put(Ljava/lang/Object;Ljava/lang/Object;)Ljava/lang/Object;
    pop
    iload 0x4
    aload_0
    iconst_0
    invokevirtual e->a(Z)I
    if_icmpeq 0x6
    invokestatic e->c()V
    goto 0x4
    pop
    iinc 0x2 0x1
    goto -0xc2
    return
.end method

.method private final e()V
    .limit stack 4
    .limit locals 1
    aload_0
    getfield e->a:[Ljava/lang/String;
    iconst_0
    aaload
    putstatic e->C:Ljava/lang/String;
    aload_0
    getfield e->a:Ljava/util/Hashtable;
    putstatic e->c:Ljava/util/Hashtable;
    getstatic e->d:[Ljava/lang/String;
    iconst_0
    aload_0
    getfield e->a:[Ljava/lang/String;
    iconst_0
    aaload
    aastore
    getstatic e->d:[Ljava/lang/String;
    iconst_1
    aload_0
    getfield e->a:[Ljava/lang/String;
    iconst_1
    aaload
    aastore
    getstatic e->e:Z
    ifeq 0x17
    getstatic e->b:Ljava/util/Hashtable;
    aload_0
    getfield e->a:[Ljava/lang/String;
    iconst_0
    aaload
    aload_0
    getstatic e->a:Ljava/lang/String;
    invokespecial e->a(Ljava/lang/String;)Ljava/lang/String;
    invokevirtual java/util/Hashtable->put(Ljava/lang/Object;Ljava/lang/Object;)Ljava/lang/Object;
    pop
    invokestatic e->c()V
    return
.end method

.method private a(I)V
    .limit stack 3
    .limit locals 2
    aload_0
    aconst_null
    putfield e->y:Ljava/lang/String;
    aload_0
    iload_1
    putfield e->c:I
    iload_1
    ifne 0x4
    return
    iload_1
    iconst_m1
    if_icmpne 0x5
    iconst_0
    istore_1
    iload_1
    iconst_3
    if_icmpeq 0x13
    iload_1
    bipush 0xc
    if_icmpeq 0xd
    iload_1
    iconst_1
    if_icmpeq 0x8
    iload_1
    iconst_m1
    if_icmpne 0xe
    aload_0
    getfield e->a:Ljava/util/Hashtable;
    getstatic e->f:Ljava/lang/String;
    invokevirtual java/util/Hashtable->remove(Ljava/lang/Object;)Ljava/lang/Object;
    pop
    aload_0
    getstatic e->b:[Ljava/lang/String;
    iload_1
    aaload
    putfield e->y:Ljava/lang/String;
    goto 0x4
    pop
    aload_0
    getfield e->y:Ljava/lang/String;
    ifnull 0xd
    aload_0
    getfield e->y:Ljava/lang/String;
    invokevirtual java/lang/String->length()I
    ifgt 0x1a
    aload_0
    new java/lang/StringBuffer
    dup
    invokespecial java/lang/StringBuffer-><init>()V
    ldc ''
    invokevirtual java/lang/StringBuffer->append(Ljava/lang/String;)Ljava/lang/StringBuffer;
    iload_1
    invokevirtual java/lang/StringBuffer->append(I)Ljava/lang/StringBuffer;
    invokevirtual java/lang/StringBuffer->toString()Ljava/lang/String;
    putfield e->y:Ljava/lang/String;
    aload_0
    athrow
.end method

.method private static final f()V
    .limit stack 8
    .limit locals 4
    getstatic e->a:Ljavax/microedition/midlet/MIDlet;
    new java/lang/StringBuffer
    dup
    invokespecial java/lang/StringBuffer-><init>()V
    new java/lang/String
    dup
    getstatic e->a:[B
    invokespecial java/lang/String-><init>([B)V
    invokevirtual java/lang/StringBuffer->append(Ljava/lang/String;)Ljava/lang/StringBuffer;
    new java/lang/String
    dup
    iconst_1
    newarray 0x8
    dup
    iconst_0
    bipush 0x50
    bastore
    invokespecial java/lang/String-><init>([B)V
    invokevirtual java/lang/StringBuffer->append(Ljava/lang/String;)Ljava/lang/StringBuffer;
    invokevirtual java/lang/StringBuffer->toString()Ljava/lang/String;
    invokevirtual javax/microedition/midlet/MIDlet->getAppProperty(Ljava/lang/String;)Ljava/lang/String;
    dup
    astore_0
    ifnonnull 0x62
    aconst_null
    astore_1
    new java/lang/String
    dup
    getstatic e->c:[B
    invokespecial java/lang/String-><init>([B)V
    invokestatic a->a(Ljava/lang/String;)Ljava/io/InputStream;
    astore_1
    new java/lang/StringBuffer
    dup
    invokespecial java/lang/StringBuffer-><init>()V
    astore_2
    aload_1
    invokevirtual java/io/InputStream->read()I
    dup
    istore_3
    iconst_m1
    if_icmpeq 0xd
    aload_2
    iload_3
    i2c
    invokevirtual java/lang/StringBuffer->append(C)Ljava/lang/StringBuffer;
    pop
    goto -0x11
    aload_2
    invokevirtual java/lang/StringBuffer->toString()Ljava/lang/String;
    astore_0
    aload_1
    ifnull 0x2d
    aload_1
    invokevirtual java/io/InputStream->close()V
    goto 0x26
    pop
    goto 0x22
    pop
    aload_1
    ifnull 0x1d
    aload_1
    invokevirtual java/io/InputStream->close()V
    goto 0x16
    pop
    goto 0x12
    astore_0
    aload_1
    ifnull 0xb
    aload_1
    invokevirtual java/io/InputStream->close()V
    goto 0x4
    pop
    aload_0
    athrow
    aload_0
    ifnull 0x2b
    aload_0
    invokestatic e->a(Ljava/lang/String;)[B
    astore_1
    new java/io/DataInputStream
    dup
    new java/io/ByteArrayInputStream
    dup
    aload_1
    invokespecial java/io/ByteArrayInputStream-><init>([B)V
    invokespecial java/io/DataInputStream-><init>(Ljava/io/InputStream;)V
    astore_2
    aload_2
    invokevirtual java/io/DataInputStream->readUTF()Ljava/lang/String;
    astore_3
    aload_2
    invokevirtual java/io/DataInputStream->readUTF()Ljava/lang/String;
    astore_0
    aload_3
    aload_0
    invokestatic a->a(Ljava/lang/String;Ljava/lang/String;)V
    goto -0xf
    pop
    return
    pop
    return
.end method

.method private static a(Ljava/lang/String;)[B
    .limit stack 3
    .limit locals 4
    aload_0
    invokestatic b->a(Ljava/lang/String;)[B
    dup
    astore_0
    arraylength
    newarray 0x8
    astore_1
    bipush 0x31
    istore_2
    iconst_0
    istore_3
    iload_3
    aload_0
    arraylength
    if_icmpge 0x18
    iload_2
    aload_0
    iload_3
    baload
    ixor
    i2b
    istore_2
    aload_1
    iload_3
    iload_2
    bastore
    aload_0
    iload_3
    baload
    istore_2
    iinc 0x3 0x1
    goto -0x18
    aload_1
    areturn
.end method

.method private static a(Ljava/io/DataOutputStream;Ljava/lang/String;)V
    .limit stack 5
    .limit locals 5
    aload_0
    aload_1
    iconst_0
    invokestatic e->a(Ljava/lang/String;Z)[B
    getstatic e->b:I
    istore_1
    dup
    astore_0
    ifnonnull 0x7
    aconst_null
    goto 0x4a
    new java/lang/StringBuffer
    dup
    iconst_2
    aload_0
    arraylength
    imul
    invokespecial java/lang/StringBuffer-><init>(I)V
    astore_2
    iconst_0
    istore 0x4
    iload 0x4
    aload_0
    arraylength
    if_icmpge 0x30
    aload_0
    iload 0x4
    baload
    iload_1
    ixor
    i2b
    istore_3
    aload_2
    getstatic e->D:Ljava/lang/String;
    iload_3
    sipush 0xf0
    iand
    iconst_4
    ishr
    invokevirtual java/lang/String->charAt(I)C
    invokevirtual java/lang/StringBuffer->append(C)Ljava/lang/StringBuffer;
    getstatic e->D:Ljava/lang/String;
    iload_3
    bipush 0xf
    iand
    invokevirtual java/lang/String->charAt(I)C
    invokevirtual java/lang/StringBuffer->append(C)Ljava/lang/StringBuffer;
    pop
    iinc 0x4 0x1
    goto -0x31
    aload_2
    invokevirtual java/lang/StringBuffer->toString()Ljava/lang/String;
    invokevirtual java/io/DataOutputStream->writeUTF(Ljava/lang/String;)V
    return
.end method

.method private static a(Ljava/io/DataInputStream;)Ljava/lang/String;
    .limit stack 7
    .limit locals 1
    new java/io/DataInputStream
    dup
    new java/io/ByteArrayInputStream
    dup
    aload_0
    invokevirtual java/io/DataInputStream->readUTF()Ljava/lang/String;
    getstatic e->b:I
    iconst_1
    invokestatic e->a(Ljava/lang/String;IZ)[B
    invokespecial java/io/ByteArrayInputStream-><init>([B)V
    invokespecial java/io/DataInputStream-><init>(Ljava/io/InputStream;)V
    invokevirtual java/io/DataInputStream->readUTF()Ljava/lang/String;
    areturn
.end method

.method public static a(Ljava/lang/String;Ljava/lang/String;[B)[B
    .limit stack 3
    .limit locals 6
    aconst_null
    astore_3
    aconst_null
    astore 0x4
    aconst_null
    astore 0x5
    aload_0
    iconst_3
    istore_0
    dup
    astore_0
    iconst_3
    invokestatic javax/microedition/io/Connector->open(Ljava/lang/String;I)Ljavax/microedition/io/Connection;
    checkcast javax/microedition/io/HttpConnection
    dup
    astore 0x4
    aload_1
    invokeinterface javax/microedition/io/HttpConnection->setRequestMethod(Ljava/lang/String;)V
    aload_1
    ldc 'POST'
    if_acmpne 0xe
    aload 0x4
    ldc 'Content-type'
    ldc 'application/x-www-form-urlencoded'
    invokeinterface javax/microedition/io/HttpConnection->setRequestProperty(Ljava/lang/String;Ljava/lang/String;)V
    aload 0x4
    ldc 'Connection'
    ldc 'close'
    invokeinterface javax/microedition/io/HttpConnection->setRequestProperty(Ljava/lang/String;Ljava/lang/String;)V
    aload_2
    ifnull 0x14
    aload 0x4
    invokeinterface javax/microedition/io/OutputConnection->openDataOutputStream()Ljava/io/DataOutputStream;
    dup
    astore_0
    aload_2
    invokevirtual java/io/OutputStream->write([B)V
    aload_0
    invokevirtual java/io/DataOutputStream->close()V
    aload 0x4
    invokeinterface javax/microedition/io/HttpConnection->getResponseCode()I
    sipush 0xc8
    if_icmpne 0x52
    aload 0x4
    invokeinterface javax/microedition/io/ContentConnection->getLength()J
    l2i
    istore_0
    aload 0x4
    invokeinterface javax/microedition/io/InputConnection->openDataInputStream()Ljava/io/DataInputStream;
    astore 0x5
    iload_0
    ifge 0x2e
    new java/io/ByteArrayOutputStream
    dup
    invokespecial java/io/ByteArrayOutputStream-><init>()V
    astore_0
    new java/io/DataOutputStream
    dup
    aload_0
    invokespecial java/io/DataOutputStream-><init>(Ljava/io/OutputStream;)V
    astore_1
    aload 0x5
    invokevirtual java/io/DataInputStream->read()I
    dup
    istore_2
    iflt 0xb
    aload_1
    iload_2
    invokevirtual java/io/DataOutputStream->write(I)V
    goto -0xf
    aload_0
    invokevirtual java/io/ByteArrayOutputStream->toByteArray()[B
    astore_3
    goto 0x11
    iload_0
    ifle 0xd
    iload_0
    newarray 0x8
    astore_3
    aload 0x5
    aload_3
    invokevirtual java/io/DataInputStream->readFully([B)V
    aload 0x5
    ifnull 0x8
    aload 0x5
    invokevirtual java/io/DataInputStream->close()V
    aload 0x4
    ifnull 0x29
    aload 0x4
    invokeinterface javax/microedition/io/Connection->close()V
    goto 0x1f
    dup
    astore_0
    athrow
    astore_0
    aload 0x5
    ifnull 0x8
    aload 0x5
    invokevirtual java/io/DataInputStream->close()V
    aload 0x4
    ifnull 0xa
    aload 0x4
    invokeinterface javax/microedition/io/Connection->close()V
    aload_0
    athrow
    aload_3
    areturn
.end method

.method private static b(Ljava/lang/String;)Ljava/lang/String;
    .limit stack 5
    .limit locals 5
    aload_0
    ifnonnull 0x5
    aconst_null
    areturn
    new java/lang/StringBuffer
    dup
    invokespecial java/lang/StringBuffer-><init>()V
    astore_1
    aload_0
    invokevirtual java/lang/String->length()I
    istore_2
    iconst_0
    istore_3
    iload_3
    iload_2
    if_icmpge 0x133
    aload_0
    iload_3
    invokevirtual java/lang/String->charAt(I)C
    istore 0x4
    bipush 0x41
    iload 0x4
    if_icmpgt 0x15
    iload 0x4
    bipush 0x5a
    if_icmpgt 0xe
    aload_1
    iload 0x4
    i2c
    invokevirtual java/lang/StringBuffer->append(C)Ljava/lang/StringBuffer;
    pop
    goto 0x10d
    bipush 0x61
    iload 0x4
    if_icmpgt 0x15
    iload 0x4
    bipush 0x7a
    if_icmpgt 0xe
    aload_1
    iload 0x4
    i2c
    invokevirtual java/lang/StringBuffer->append(C)Ljava/lang/StringBuffer;
    pop
    goto 0xf4
    bipush 0x30
    iload 0x4
    if_icmpgt 0x15
    iload 0x4
    bipush 0x39
    if_icmpgt 0xe
    aload_1
    iload 0x4
    i2c
    invokevirtual java/lang/StringBuffer->append(C)Ljava/lang/StringBuffer;
    pop
    goto 0xdb
    iload 0x4
    bipush 0x20
    if_icmpne 0xd
    aload_1
    bipush 0x2b
    invokevirtual java/lang/StringBuffer->append(C)Ljava/lang/StringBuffer;
    pop
    goto 0xca
    iload 0x4
    bipush 0x2d
    if_icmpeq 0x3b
    iload 0x4
    bipush 0x5f
    if_icmpeq 0x34
    iload 0x4
    bipush 0x2e
    if_icmpeq 0x2d
    iload 0x4
    bipush 0x21
    if_icmpeq 0x26
    iload 0x4
    bipush 0x7e
    if_icmpeq 0x1f
    iload 0x4
    bipush 0x2a
    if_icmpeq 0x18
    iload 0x4
    bipush 0x27
    if_icmpeq 0x11
    iload 0x4
    bipush 0x28
    if_icmpeq 0xa
    iload 0x4
    bipush 0x29
    if_icmpne 0xe
    aload_1
    iload 0x4
    i2c
    invokevirtual java/lang/StringBuffer->append(C)Ljava/lang/StringBuffer;
    pop
    goto 0x80
    iload 0x4
    bipush 0x7f
    if_icmpgt 0x11
    aload_1
    getstatic e->f:[Ljava/lang/String;
    iload 0x4
    aaload
    invokevirtual java/lang/StringBuffer->append(Ljava/lang/String;)Ljava/lang/StringBuffer;
    pop
    goto 0x6b
    iload 0x4
    sipush 0x7ff
    if_icmpgt 0x2a
    aload_1
    getstatic e->f:[Ljava/lang/String;
    sipush 0xc0
    iload 0x4
    bipush 0x6
    ishr
    ior
    aaload
    invokevirtual java/lang/StringBuffer->append(Ljava/lang/String;)Ljava/lang/StringBuffer;
    pop
    aload_1
    getstatic e->f:[Ljava/lang/String;
    sipush 0x80
    iload 0x4
    bipush 0x3f
    iand
    ior
    aaload
    invokevirtual java/lang/StringBuffer->append(Ljava/lang/String;)Ljava/lang/StringBuffer;
    pop
    goto 0x3c
    aload_1
    getstatic e->f:[Ljava/lang/String;
    sipush 0xe0
    iload 0x4
    bipush 0xc
    ishr
    ior
    aaload
    invokevirtual java/lang/StringBuffer->append(Ljava/lang/String;)Ljava/lang/StringBuffer;
    pop
    aload_1
    getstatic e->f:[Ljava/lang/String;
    sipush 0x80
    iload 0x4
    bipush 0x6
    ishr
    bipush 0x3f
    iand
    ior
    aaload
    invokevirtual java/lang/StringBuffer->append(Ljava/lang/String;)Ljava/lang/StringBuffer;
    pop
    aload_1
    getstatic e->f:[Ljava/lang/String;
    sipush 0x80
    iload 0x4
    bipush 0x3f
    iand
    ior
    aaload
    invokevirtual java/lang/StringBuffer->append(Ljava/lang/String;)Ljava/lang/StringBuffer;
    pop
    iinc 0x3 0x1
    goto -0x132
    aload_1
    invokevirtual java/lang/StringBuffer->toString()Ljava/lang/String;
    areturn
.end method

.method private static a()[Ljava/lang/String;
    .limit stack 4
    .limit locals 3
    sipush 0x100
    anewarray java/lang/String
    astore_0
    new java/lang/StringBuffer
    dup
    invokespecial java/lang/StringBuffer-><init>()V
    astore_1
    iconst_0
    istore_2
    iload_2
    aload_0
    arraylength
    if_icmpge 0x3d
    aload_1
    iconst_0
    invokevirtual java/lang/StringBuffer->setLength(I)V
    aload_1
    bipush 0x25
    invokevirtual java/lang/StringBuffer->append(C)Ljava/lang/StringBuffer;
    pop
    aload_1
    getstatic e->D:Ljava/lang/String;
    iload_2
    sipush 0xf0
    iand
    iconst_4
    ishr
    invokevirtual java/lang/String->charAt(I)C
    invokevirtual java/lang/StringBuffer->append(C)Ljava/lang/StringBuffer;
    pop
    aload_1
    getstatic e->D:Ljava/lang/String;
    iload_2
    bipush 0xf
    iand
    invokevirtual java/lang/String->charAt(I)C
    invokevirtual java/lang/StringBuffer->append(C)Ljava/lang/StringBuffer;
    pop
    aload_0
    iload_2
    aload_1
    invokevirtual java/lang/StringBuffer->toString()Ljava/lang/String;
    aastore
    iinc 0x2 0x1
    goto -0x3d
    aload_0
    areturn
.end method

.method private static b(I)I
    .limit stack 2
    .limit locals 1
    iload_0
    bipush 0x30
    if_icmplt 0xe
    iload_0
    bipush 0x39
    if_icmpgt 0x8
    iload_0
    bipush 0x30
    isub
    ireturn
    iload_0
    bipush 0x41
    if_icmplt 0x11
    iload_0
    bipush 0x5a
    if_icmpgt 0xb
    iload_0
    bipush 0x41
    isub
    bipush 0xa
    iadd
    ireturn
    iload_0
    bipush 0x61
    if_icmplt 0x11
    iload_0
    bipush 0x7a
    if_icmpgt 0xb
    iload_0
    bipush 0x61
    isub
    bipush 0xa
    iadd
    ireturn
    iconst_0
    ireturn
.end method

.method public static a(Ljava/lang/String;IZ)[B
    .limit stack 5
    .limit locals 7
    iconst_0
    istore_3
    aload_0
    invokevirtual java/lang/String->length()I
    iconst_1
    ishr
    istore 0x4
    iload_2
    ifeq 0x5
    iconst_2
    istore_3
    iload 0x4
    iload_3
    iadd
    newarray 0x8
    astore 0x5
    iload_2
    ifeq 0x18
    aload 0x5
    iconst_0
    iload 0x4
    bipush 0x8
    ishr
    sipush 0xff
    iand
    i2b
    bastore
    aload 0x5
    iconst_1
    iload 0x4
    i2b
    bastore
    iconst_0
    istore_2
    iload_3
    istore_3
    iload_2
    aload_0
    invokevirtual java/lang/String->length()I
    if_icmpge 0x37
    aload_0
    iload_2
    invokevirtual java/lang/String->charAt(I)C
    invokestatic e->b(I)I
    iconst_4
    ishl
    istore 0x4
    aload_0
    iload_2
    iconst_1
    iadd
    invokevirtual java/lang/String->charAt(I)C
    invokestatic e->b(I)I
    istore 0x6
    aload 0x5
    iload_3
    iload 0x4
    sipush 0xf0
    iand
    iload 0x6
    bipush 0xf
    iand
    ior
    iload_1
    ixor
    i2b
    bastore
    iinc 0x2 0x2
    iinc 0x3 0x1
    goto -0x39
    aload 0x5
    areturn
.end method

.method private static a(Ljava/lang/String;Z)[B
    .limit stack 5
    .limit locals 4
    aload_0
    ifnonnull 0x6
    ldc ''
    astore_0
    aconst_null
    astore_1
    new java/io/ByteArrayOutputStream
    dup
    invokespecial java/io/ByteArrayOutputStream-><init>()V
    astore_2
    new java/io/DataOutputStream
    dup
    aload_2
    invokespecial java/io/DataOutputStream-><init>(Ljava/io/OutputStream;)V
    dup
    astore_3
    aload_0
    invokevirtual java/io/DataOutputStream->writeUTF(Ljava/lang/String;)V
    aload_2
    invokevirtual java/io/ByteArrayOutputStream->toByteArray()[B
    astore_1
    aload_3
    invokevirtual java/io/DataOutputStream->close()V
    aload_2
    invokevirtual java/io/ByteArrayOutputStream->close()V
    goto 0x4
    pop
    aload_1
    arraylength
    iconst_2
    isub
    newarray 0x8
    astore_0
    aload_1
    iconst_2
    aload_0
    iconst_0
    aload_0
    arraylength
    invokestatic java/lang/System->arraycopy(Ljava/lang/Object;ILjava/lang/Object;II)V
    aload_0
    areturn
.end method

.method public final commandAction(Ljavax/microedition/lcdui/Command;Ljavax/microedition/lcdui/Displayable;)V
    .limit stack 4
    .limit locals 3
    aload_2
    aload_0
    getfield e->a:Ljavax/microedition/lcdui/Form;
    if_acmpne 0xb2
    aload_1
    aload_0
    getfield e->a:Ljavax/microedition/lcdui/Command;
    if_acmpne 0x98
    aload_0
    getfield e->a:Ljavax/microedition/lcdui/Form;
    invokevirtual javax/microedition/lcdui/Form->size()I
    aload_0
    getfield e->f:I
    iconst_2
    if_icmpne 0x7
    iconst_0
    goto 0x4
    iconst_1
    isub
    istore_1
    aload_0
    iload_1
    anewarray java/lang/String
    putfield e->e:[Ljava/lang/String;
    iconst_0
    istore_1
    iload_1
    aload_0
    getfield e->e:[Ljava/lang/String;
    arraylength
    if_icmpge 0x20
    aload_0
    getfield e->e:[Ljava/lang/String;
    iload_1
    aload_0
    getfield e->a:Ljavax/microedition/lcdui/Form;
    iload_1
    invokevirtual javax/microedition/lcdui/Form->get(I)Ljavax/microedition/lcdui/Item;
    checkcast javax/microedition/lcdui/TextField
    invokevirtual javax/microedition/lcdui/TextField->getString()Ljava/lang/String;
    invokevirtual java/lang/String->trim()Ljava/lang/String;
    aastore
    iinc 0x1 0x1
    goto -0x23
    aload_0
    getfield e->e:[Ljava/lang/String;
    iconst_0
    aaload
    invokevirtual java/lang/String->length()I
    ifle 0x40
    aload_0
    getfield e->f:I
    iconst_2
    if_icmpeq 0xf
    aload_0
    getfield e->e:[Ljava/lang/String;
    iconst_1
    aaload
    invokevirtual java/lang/String->length()I
    ifle 0x2c
    aload_0
    getfield e->f:I
    ifeq 0x1d
    aload_0
    getfield e->f:I
    iconst_2
    if_icmpeq 0x15
    aload_0
    getfield e->e:[Ljava/lang/String;
    iconst_1
    aaload
    aload_0
    getfield e->e:[Ljava/lang/String;
    iconst_2
    aaload
    invokevirtual java/lang/String->equals(Ljava/lang/Object;)Z
    ifeq 0xb
    aload_0
    iconst_1
    putfield e->e:I
    goto 0x1b
    aload_0
    aconst_null
    putfield e->e:[Ljava/lang/String;
    return
    aload_1
    aload_0
    getfield e->b:Ljavax/microedition/lcdui/Command;
    if_acmpne 0xd
    aload_0
    aconst_null
    putfield e->e:[Ljava/lang/String;
    aload_0
    iconst_2
    putfield e->e:I
    return
.end method

.method public final itemStateChanged(Ljavax/microedition/lcdui/Item;)V
    .limit stack 3
    .limit locals 3
    aload_1
    aload_0
    getfield e->a:Ljavax/microedition/lcdui/ChoiceGroup;
    if_acmpne 0x60
    aload_0
    getfield e->a:Ljavax/microedition/lcdui/Form;
    ifnull 0x59
    aload_0
    getfield e->f:I
    iconst_2
    if_icmpeq 0x51
    aload_0
    getfield e->a:Ljavax/microedition/lcdui/ChoiceGroup;
    iconst_0
    invokevirtual javax/microedition/lcdui/ChoiceGroup->isSelected(I)Z
    putstatic e->h:Z
    iconst_1
    istore_1
    iload_1
    aload_0
    getfield e->f:I
    ifne 0x7
    iconst_2
    goto 0x4
    iconst_3
    if_icmpge 0x34
    aload_0
    getfield e->a:Ljavax/microedition/lcdui/Form;
    iload_1
    invokevirtual javax/microedition/lcdui/Form->get(I)Ljavax/microedition/lcdui/Item;
    checkcast javax/microedition/lcdui/TextField
    dup
    astore_2
    getstatic e->h:Z
    ifeq 0xd
    aload_2
    invokevirtual javax/microedition/lcdui/TextField->getConstraints()I
    ldc -65537
    iand
    goto 0xa
    aload_2
    invokevirtual javax/microedition/lcdui/TextField->getConstraints()I
    ldc 65536
    ior
    invokevirtual javax/microedition/lcdui/TextField->setConstraints(I)V
    goto 0x4
    pop
    iinc 0x1 0x1
    goto -0x3e
    return
.end method

.method private a(B)Z
    .limit stack 10
    .limit locals 6
    ldc '*'
    astore_2
    aload_0
    iconst_0
    putfield e->e:I
    aload_0
    iload_1
    putfield e->f:I
    aconst_null
    astore_3
    aconst_null
    astore 0x4
    aconst_null
    astore 0x5
    iload_1
    ifne 0x1a
    getstatic e->c:[Ljava/lang/String;
    iconst_0
    aaload
    astore_3
    getstatic e->d:[Ljava/lang/String;
    iconst_0
    aaload
    astore 0x4
    getstatic e->d:[Ljava/lang/String;
    iconst_1
    aaload
    astore 0x5
    goto 0x2d
    iload_1
    iconst_1
    if_icmpne 0x14
    getstatic e->c:[Ljava/lang/String;
    iconst_1
    aaload
    astore_3
    ldc ''
    astore 0x4
    ldc ''
    astore 0x5
    goto 0x17
    iload_1
    iconst_2
    if_icmpne 0x12
    getstatic e->c:[Ljava/lang/String;
    bipush 0x9
    aaload
    astore_3
    aload_0
    getfield e->a:[Ljava/lang/String;
    iconst_0
    aaload
    astore 0x4
    aload_0
    new javax/microedition/lcdui/Form
    dup
    aload_3
    invokespecial javax/microedition/lcdui/Form-><init>(Ljava/lang/String;)V
    putfield e->a:Ljavax/microedition/lcdui/Form;
    new javax/microedition/lcdui/TextField
    dup
    new java/lang/StringBuffer
    dup
    invokespecial java/lang/StringBuffer-><init>()V
    getstatic e->c:[Ljava/lang/String;
    iconst_4
    aaload
    invokevirtual java/lang/StringBuffer->append(Ljava/lang/String;)Ljava/lang/StringBuffer;
    aload_2
    invokevirtual java/lang/StringBuffer->append(Ljava/lang/String;)Ljava/lang/StringBuffer;
    invokevirtual java/lang/StringBuffer->toString()Ljava/lang/String;
    aload 0x4
    bipush 0x19
    ldc 786432
    getstatic e->d:Z
    ifeq 0x8
    ldc 131072
    goto 0x4
    iconst_0
    ior
    invokespecial javax/microedition/lcdui/TextField-><init>(Ljava/lang/String;Ljava/lang/String;II)V
    dup
    astore_3
    sipush 0x801
    invokevirtual javax/microedition/lcdui/Item->setLayout(I)V
    aload_0
    getfield e->a:Ljavax/microedition/lcdui/Form;
    aload_3
    invokevirtual javax/microedition/lcdui/Form->append(Ljavax/microedition/lcdui/Item;)I
    pop
    iload_1
    ifeq 0x8
    iload_1
    iconst_1
    if_icmpne 0x44
    new javax/microedition/lcdui/TextField
    dup
    new java/lang/StringBuffer
    dup
    invokespecial java/lang/StringBuffer-><init>()V
    getstatic e->c:[Ljava/lang/String;
    iconst_5
    aaload
    invokevirtual java/lang/StringBuffer->append(Ljava/lang/String;)Ljava/lang/StringBuffer;
    aload_2
    invokevirtual java/lang/StringBuffer->append(Ljava/lang/String;)Ljava/lang/StringBuffer;
    invokevirtual java/lang/StringBuffer->toString()Ljava/lang/String;
    aload 0x5
    bipush 0x19
    ldc 786432
    getstatic e->h:Z
    ifeq 0x7
    iconst_0
    goto 0x5
    ldc 65536
    ior
    invokespecial javax/microedition/lcdui/TextField-><init>(Ljava/lang/String;Ljava/lang/String;II)V
    dup
    astore_3
    sipush 0x801
    invokevirtual javax/microedition/lcdui/Item->setLayout(I)V
    aload_0
    getfield e->a:Ljavax/microedition/lcdui/Form;
    aload_3
    invokevirtual javax/microedition/lcdui/Form->append(Ljavax/microedition/lcdui/Item;)I
    pop
    iload_1
    iconst_1
    if_icmpne 0x45
    new javax/microedition/lcdui/TextField
    dup
    new java/lang/StringBuffer
    dup
    invokespecial java/lang/StringBuffer-><init>()V
    getstatic e->c:[Ljava/lang/String;
    bipush 0x6
    aaload
    invokevirtual java/lang/StringBuffer->append(Ljava/lang/String;)Ljava/lang/StringBuffer;
    aload_2
    invokevirtual java/lang/StringBuffer->append(Ljava/lang/String;)Ljava/lang/StringBuffer;
    invokevirtual java/lang/StringBuffer->toString()Ljava/lang/String;
    ldc ''
    bipush 0x19
    ldc 786432
    getstatic e->h:Z
    ifeq 0x7
    iconst_0
    goto 0x5
    ldc 65536
    ior
    invokespecial javax/microedition/lcdui/TextField-><init>(Ljava/lang/String;Ljava/lang/String;II)V
    dup
    astore_3
    sipush 0x801
    invokevirtual javax/microedition/lcdui/Item->setLayout(I)V
    aload_0
    getfield e->a:Ljavax/microedition/lcdui/Form;
    aload_3
    invokevirtual javax/microedition/lcdui/Form->append(Ljavax/microedition/lcdui/Item;)I
    pop
    iload_1
    iconst_1
    if_icmpne 0x27
    new javax/microedition/lcdui/TextField
    dup
    getstatic e->c:[Ljava/lang/String;
    bipush 0x7
    aaload
    ldc ''
    bipush 0x19
    ldc 786433
    invokespecial javax/microedition/lcdui/TextField-><init>(Ljava/lang/String;Ljava/lang/String;II)V
    dup
    astore_3
    sipush 0x801
    invokevirtual javax/microedition/lcdui/Item->setLayout(I)V
    aload_0
    getfield e->a:Ljavax/microedition/lcdui/Form;
    aload_3
    invokevirtual javax/microedition/lcdui/Form->append(Ljavax/microedition/lcdui/Item;)I
    pop
    iload_1
    iconst_1
    if_icmpne 0x27
    new javax/microedition/lcdui/TextField
    dup
    getstatic e->c:[Ljava/lang/String;
    bipush 0xa
    aaload
    ldc ''
    bipush 0xc
    ldc 786435
    invokespecial javax/microedition/lcdui/TextField-><init>(Ljava/lang/String;Ljava/lang/String;II)V
    dup
    astore_3
    sipush 0x801
    invokevirtual javax/microedition/lcdui/Item->setLayout(I)V
    aload_0
    getfield e->a:Ljavax/microedition/lcdui/Form;
    aload_3
    invokevirtual javax/microedition/lcdui/Form->append(Ljavax/microedition/lcdui/Item;)I
    pop
    iload_1
    ifeq 0x8
    iload_1
    iconst_1
    if_icmpne 0x3f
    aload_0
    new javax/microedition/lcdui/ChoiceGroup
    dup
    aconst_null
    iconst_2
    iconst_1
    anewarray java/lang/String
    dup
    iconst_0
    getstatic e->c:[Ljava/lang/String;
    bipush 0x8
    aaload
    aastore
    aconst_null
    invokespecial javax/microedition/lcdui/ChoiceGroup-><init>(Ljava/lang/String;I[Ljava/lang/String;[Ljavax/microedition/lcdui/Image;)V
    putfield e->a:Ljavax/microedition/lcdui/ChoiceGroup;
    aload_0
    getfield e->a:Ljavax/microedition/lcdui/ChoiceGroup;
    sipush 0x801
    invokevirtual javax/microedition/lcdui/Item->setLayout(I)V
    aload_0
    getfield e->a:Ljavax/microedition/lcdui/ChoiceGroup;
    iconst_0
    getstatic e->h:Z
    invokevirtual javax/microedition/lcdui/ChoiceGroup->setSelectedIndex(IZ)V
    aload_0
    getfield e->a:Ljavax/microedition/lcdui/Form;
    aload_0
    getfield e->a:Ljavax/microedition/lcdui/ChoiceGroup;
    invokevirtual javax/microedition/lcdui/Form->append(Ljavax/microedition/lcdui/Item;)I
    pop
    getstatic e->h:Z
    istore_2
    aload_0
    new javax/microedition/lcdui/Command
    dup
    getstatic e->c:[Ljava/lang/String;
    iconst_2
    aaload
    iconst_4
    iconst_1
    invokespecial javax/microedition/lcdui/Command-><init>(Ljava/lang/String;II)V
    putfield e->a:Ljavax/microedition/lcdui/Command;
    aload_0
    new javax/microedition/lcdui/Command
    dup
    getstatic e->c:[Ljava/lang/String;
    iconst_3
    aaload
    iconst_3
    iconst_2
    invokespecial javax/microedition/lcdui/Command-><init>(Ljava/lang/String;II)V
    putfield e->b:Ljavax/microedition/lcdui/Command;
    aload_0
    getfield e->a:Ljavax/microedition/lcdui/Form;
    aload_0
    getfield e->a:Ljavax/microedition/lcdui/Command;
    invokevirtual javax/microedition/lcdui/Displayable->addCommand(Ljavax/microedition/lcdui/Command;)V
    aload_0
    getfield e->a:Ljavax/microedition/lcdui/Form;
    aload_0
    getfield e->b:Ljavax/microedition/lcdui/Command;
    invokevirtual javax/microedition/lcdui/Displayable->addCommand(Ljavax/microedition/lcdui/Command;)V
    aload_0
    getfield e->a:Ljavax/microedition/lcdui/Form;
    aload_0
    invokevirtual javax/microedition/lcdui/Displayable->setCommandListener(Ljavax/microedition/lcdui/CommandListener;)V
    aload_0
    getfield e->a:Ljavax/microedition/lcdui/Form;
    aload_0
    invokevirtual javax/microedition/lcdui/Form->setItemStateListener(Ljavax/microedition/lcdui/ItemStateListener;)V
    getstatic e->a:Ljavax/microedition/midlet/MIDlet;
    invokestatic javax/microedition/lcdui/Display->getDisplay(Ljavax/microedition/midlet/MIDlet;)Ljavax/microedition/lcdui/Display;
    dup
    astore_3
    invokevirtual javax/microedition/lcdui/Display->getCurrent()Ljavax/microedition/lcdui/Displayable;
    astore 0x4
    invokestatic java/lang/Thread->yield()V
    aload_3
    aload_0
    getfield e->a:Ljavax/microedition/lcdui/Form;
    invokevirtual javax/microedition/lcdui/Display->setCurrent(Ljavax/microedition/lcdui/Displayable;)V
    aload_0
    getfield e->e:I
    ifne 0xc
    ldc2_w 30
    invokestatic a->a(J)V
    goto -0xd
    aload_3
    aload 0x4
    invokevirtual javax/microedition/lcdui/Display->setCurrent(Ljavax/microedition/lcdui/Displayable;)V
    aload_0
    aconst_null
    putfield e->a:Ljavax/microedition/lcdui/Form;
    aload_0
    aconst_null
    putfield e->a:Ljavax/microedition/lcdui/ChoiceGroup;
    aload_0
    aload_0
    aconst_null
    dup_x1
    putfield e->b:Ljavax/microedition/lcdui/Command;
    putfield e->a:Ljavax/microedition/lcdui/Command;
    invokestatic a->e()V
    aload_0
    getfield e->e:I
    iconst_1
    if_icmpne 0x7e
    aload_0
    getfield e->e:[Ljava/lang/String;
    ifnull 0x77
    iload_1
    ifne 0x1e
    aload_0
    getfield e->a:[Ljava/lang/String;
    iconst_0
    aload_0
    getfield e->e:[Ljava/lang/String;
    iconst_0
    aaload
    aastore
    aload_0
    getfield e->a:[Ljava/lang/String;
    iconst_1
    aload_0
    getfield e->e:[Ljava/lang/String;
    iconst_1
    aaload
    aastore
    goto 0x56
    iload_1
    iconst_1
    if_icmpne 0x40
    aload_0
    getfield e->a:[Ljava/lang/String;
    iconst_0
    aload_0
    getfield e->e:[Ljava/lang/String;
    iconst_0
    aaload
    aastore
    aload_0
    getfield e->a:[Ljava/lang/String;
    iconst_1
    aload_0
    getfield e->e:[Ljava/lang/String;
    iconst_1
    aaload
    aastore
    aload_0
    getfield e->a:Ljava/util/Hashtable;
    getstatic e->d:Ljava/lang/String;
    aload_0
    getfield e->e:[Ljava/lang/String;
    iconst_3
    aaload
    invokevirtual java/util/Hashtable->put(Ljava/lang/Object;Ljava/lang/Object;)Ljava/lang/Object;
    pop
    aload_0
    getfield e->a:Ljava/util/Hashtable;
    getstatic e->e:Ljava/lang/String;
    aload_0
    getfield e->e:[Ljava/lang/String;
    iconst_4
    aaload
    invokevirtual java/util/Hashtable->put(Ljava/lang/Object;Ljava/lang/Object;)Ljava/lang/Object;
    pop
    goto 0x14
    iload_1
    iconst_2
    if_icmpne 0xf
    aload_0
    getfield e->a:[Ljava/lang/String;
    iconst_0
    aload_0
    getfield e->e:[Ljava/lang/String;
    iconst_0
    aaload
    aastore
    iconst_1
    ireturn
    iload_2
    putstatic e->h:Z
    iconst_0
    ireturn
.end method

.method static <clinit>()V
    .limit stack 7
    .limit locals 0
    sipush 0xe2
    putstatic e->b:I
    ldc 'account'
    putstatic e->a:Ljava/lang/String;
    ldc 'user_id'
    putstatic e->b:Ljava/lang/String;
    ldc 'cur_ach'
    putstatic e->c:Ljava/lang/String;
    ldc 'cur_email'
    putstatic e->d:Ljava/lang/String;
    ldc 'cur_phone'
    putstatic e->e:Ljava/lang/String;
    ldc 'sess'
    putstatic e->f:Ljava/lang/String;
    ldc 'sess_t'
    putstatic e->g:Ljava/lang/String;
    iconst_3
    newarray 0x8
    dup
    iconst_0
    bipush 0x48
    bastore
    dup
    iconst_1
    bipush 0x43
    bastore
    dup
    iconst_2
    bipush 0x2d
    bastore
    putstatic e->a:[B
    iconst_3
    newarray 0x8
    dup
    iconst_0
    bipush 0x59
    bastore
    dup
    iconst_1
    bipush 0x43
    bastore
    dup
    iconst_2
    bipush 0x2d
    bastore
    putstatic e->b:[B
    iconst_4
    newarray 0x8
    dup
    iconst_0
    bipush 0x2f
    bastore
    dup
    iconst_1
    bipush 0x72
    bastore
    dup
    iconst_2
    bipush 0x73
    bastore
    dup
    iconst_3
    bipush 0x75
    bastore
    putstatic e->c:[B
    new java/lang/String
    dup
    getstatic e->a:[B
    invokespecial java/lang/String-><init>([B)V
    putstatic e->h:Ljava/lang/String;
    new java/lang/String
    dup
    getstatic e->b:[B
    invokespecial java/lang/String-><init>([B)V
    putstatic e->i:Ljava/lang/String;
    new java/lang/StringBuffer
    dup
    invokespecial java/lang/StringBuffer-><init>()V
    getstatic e->h:Ljava/lang/String;
    invokevirtual java/lang/StringBuffer->append(Ljava/lang/String;)Ljava/lang/StringBuffer;
    ldc 'uid'
    invokevirtual java/lang/StringBuffer->append(Ljava/lang/String;)Ljava/lang/StringBuffer;
    invokevirtual java/lang/StringBuffer->toString()Ljava/lang/String;
    pop
    new java/lang/StringBuffer
    dup
    invokespecial java/lang/StringBuffer-><init>()V
    getstatic e->h:Ljava/lang/String;
    invokevirtual java/lang/StringBuffer->append(Ljava/lang/String;)Ljava/lang/StringBuffer;
    ldc 'l'
    invokevirtual java/lang/StringBuffer->append(Ljava/lang/String;)Ljava/lang/StringBuffer;
    invokevirtual java/lang/StringBuffer->toString()Ljava/lang/String;
    putstatic e->j:Ljava/lang/String;
    new java/lang/StringBuffer
    dup
    invokespecial java/lang/StringBuffer-><init>()V
    getstatic e->h:Ljava/lang/String;
    invokevirtual java/lang/StringBuffer->append(Ljava/lang/String;)Ljava/lang/StringBuffer;
    ldc 'p'
    invokevirtual java/lang/StringBuffer->append(Ljava/lang/String;)Ljava/lang/StringBuffer;
    invokevirtual java/lang/StringBuffer->toString()Ljava/lang/String;
    putstatic e->k:Ljava/lang/String;
    new java/lang/StringBuffer
    dup
    invokespecial java/lang/StringBuffer-><init>()V
    getstatic e->i:Ljava/lang/String;
    invokevirtual java/lang/StringBuffer->append(Ljava/lang/String;)Ljava/lang/StringBuffer;
    ldc 'url_ugc'
    invokevirtual java/lang/StringBuffer->append(Ljava/lang/String;)Ljava/lang/StringBuffer;
    invokevirtual java/lang/StringBuffer->toString()Ljava/lang/String;
    putstatic e->l:Ljava/lang/String;
    new java/lang/StringBuffer
    dup
    invokespecial java/lang/StringBuffer-><init>()V
    getstatic e->i:Ljava/lang/String;
    invokevirtual java/lang/StringBuffer->append(Ljava/lang/String;)Ljava/lang/StringBuffer;
    ldc 'url_users'
    invokevirtual java/lang/StringBuffer->append(Ljava/lang/String;)Ljava/lang/StringBuffer;
    invokevirtual java/lang/StringBuffer->toString()Ljava/lang/String;
    putstatic e->m:Ljava/lang/String;
    new java/lang/StringBuffer
    dup
    invokespecial java/lang/StringBuffer-><init>()V
    getstatic e->i:Ljava/lang/String;
    invokevirtual java/lang/StringBuffer->append(Ljava/lang/String;)Ljava/lang/StringBuffer;
    ldc 'url_sess'
    invokevirtual java/lang/StringBuffer->append(Ljava/lang/String;)Ljava/lang/StringBuffer;
    invokevirtual java/lang/StringBuffer->toString()Ljava/lang/String;
    putstatic e->n:Ljava/lang/String;
    new java/lang/StringBuffer
    dup
    invokespecial java/lang/StringBuffer-><init>()V
    getstatic e->i:Ljava/lang/String;
    invokevirtual java/lang/StringBuffer->append(Ljava/lang/String;)Ljava/lang/StringBuffer;
    ldc 'url_prof'
    invokevirtual java/lang/StringBuffer->append(Ljava/lang/String;)Ljava/lang/StringBuffer;
    invokevirtual java/lang/StringBuffer->toString()Ljava/lang/String;
    putstatic e->o:Ljava/lang/String;
    new java/lang/StringBuffer
    dup
    invokespecial java/lang/StringBuffer-><init>()V
    getstatic e->i:Ljava/lang/String;
    invokevirtual java/lang/StringBuffer->append(Ljava/lang/String;)Ljava/lang/StringBuffer;
    ldc 'sys'
    invokevirtual java/lang/StringBuffer->append(Ljava/lang/String;)Ljava/lang/StringBuffer;
    invokevirtual java/lang/StringBuffer->toString()Ljava/lang/String;
    putstatic e->p:Ljava/lang/String;
    new java/lang/StringBuffer
    dup
    invokespecial java/lang/StringBuffer-><init>()V
    getstatic e->i:Ljava/lang/String;
    invokevirtual java/lang/StringBuffer->append(Ljava/lang/String;)Ljava/lang/StringBuffer;
    ldc 'isreg'
    invokevirtual java/lang/StringBuffer->append(Ljava/lang/String;)Ljava/lang/StringBuffer;
    invokevirtual java/lang/StringBuffer->toString()Ljava/lang/String;
    putstatic e->q:Ljava/lang/String;
    new java/lang/StringBuffer
    dup
    invokespecial java/lang/StringBuffer-><init>()V
    getstatic e->i:Ljava/lang/String;
    invokevirtual java/lang/StringBuffer->append(Ljava/lang/String;)Ljava/lang/StringBuffer;
    ldc 'islog'
    invokevirtual java/lang/StringBuffer->append(Ljava/lang/String;)Ljava/lang/StringBuffer;
    invokevirtual java/lang/StringBuffer->toString()Ljava/lang/String;
    putstatic e->r:Ljava/lang/String;
    new java/lang/StringBuffer
    dup
    invokespecial java/lang/StringBuffer-><init>()V
    getstatic e->i:Ljava/lang/String;
    invokevirtual java/lang/StringBuffer->append(Ljava/lang/String;)Ljava/lang/StringBuffer;
    ldc 'isinfo'
    invokevirtual java/lang/StringBuffer->append(Ljava/lang/String;)Ljava/lang/StringBuffer;
    invokevirtual java/lang/StringBuffer->toString()Ljava/lang/String;
    putstatic e->s:Ljava/lang/String;
    iconst_0
    putstatic e->a:Z
    iconst_0
    putstatic e->b:Z
    iconst_0
    putstatic e->c:Z
    iconst_0
    putstatic e->d:Z
    iconst_0
    putstatic e->e:Z
    iconst_0
    putstatic e->a:I
    aconst_null
    putstatic e->t:Ljava/lang/String;
    aconst_null
    putstatic e->u:Ljava/lang/String;
    aconst_null
    putstatic e->v:Ljava/lang/String;
    bipush 0x7
    anewarray [B
    dup
    iconst_0
    bipush 0x19
    newarray 0x8
    dup
    iconst_0
    bipush 0x68
    bastore
    dup
    iconst_1
    bipush 0x74
    bastore
    dup
    iconst_2
    bipush 0x74
    bastore
    dup
    iconst_3
    bipush 0x70
    bastore
    dup
    iconst_4
    bipush 0x3a
    bastore
    dup
    iconst_5
    bipush 0x2f
    bastore
    dup
    bipush 0x6
    bipush 0x2f
    bastore
    dup
    bipush 0x7
    bipush 0x77
    bastore
    dup
    bipush 0x8
    bipush 0x61
    bastore
    dup
    bipush 0x9
    bipush 0x70
    bastore
    dup
    bipush 0xa
    bipush 0x2e
    bastore
    dup
    bipush 0xb
    bipush 0x68
    bastore
    dup
    bipush 0xc
    bipush 0x65
    bastore
    dup
    bipush 0xd
    bipush 0x72
    bastore
    dup
    bipush 0xe
    bipush 0x6f
    bastore
    dup
    bipush 0xf
    bipush 0x63
    bastore
    dup
    bipush 0x10
    bipush 0x72
    bastore
    dup
    bipush 0x11
    bipush 0x61
    bastore
    dup
    bipush 0x12
    bipush 0x66
    bastore
    dup
    bipush 0x13
    bipush 0x74
    bastore
    dup
    bipush 0x14
    bipush 0x2e
    bastore
    dup
    bipush 0x15
    bipush 0x63
    bastore
    dup
    bipush 0x16
    bipush 0x6f
    bastore
    dup
    bipush 0x17
    bipush 0x6d
    bastore
    dup
    bipush 0x18
    bipush 0x2f
    bastore
    aastore
    dup
    iconst_1
    bipush 0x7
    newarray 0x8
    dup
    iconst_0
    bipush 0x75
    bastore
    dup
    iconst_1
    bipush 0x67
    bastore
    dup
    iconst_2
    bipush 0x63
    bastore
    dup
    iconst_3
    bipush 0x2f
    bastore
    dup
    iconst_4
    bipush 0x61
    bastore
    dup
    iconst_5
    bipush 0x70
    bastore
    dup
    bipush 0x6
    bipush 0x69
    bastore
    aastore
    dup
    iconst_2
    bipush 0x9
    newarray 0x8
    dup
    iconst_0
    bipush 0x75
    bastore
    dup
    iconst_1
    bipush 0x73
    bastore
    dup
    iconst_2
    bipush 0x65
    bastore
    dup
    iconst_3
    bipush 0x72
    bastore
    dup
    iconst_4
    bipush 0x73
    bastore
    dup
    iconst_5
    bipush 0x2f
    bastore
    dup
    bipush 0x6
    bipush 0x61
    bastore
    dup
    bipush 0x7
    bipush 0x70
    bastore
    dup
    bipush 0x8
    bipush 0x69
    bastore
    aastore
    dup
    iconst_3
    bipush 0xf
    newarray 0x8
    dup
    iconst_0
    bipush 0x61
    bastore
    dup
    iconst_1
    bipush 0x70
    bastore
    dup
    iconst_2
    bipush 0x69
    bastore
    dup
    iconst_3
    bipush 0x2f
    bastore
    dup
    iconst_4
    bipush 0x67
    bastore
    dup
    iconst_5
    bipush 0x65
    bastore
    dup
    bipush 0x6
    bipush 0x74
    bastore
    dup
    bipush 0x7
    bipush 0x5f
    bastore
    dup
    bipush 0x8
    bipush 0x73
    bastore
    dup
    bipush 0x9
    bipush 0x65
    bastore
    dup
    bipush 0xa
    bipush 0x73
    bastore
    dup
    bipush 0xb
    bipush 0x73
    bastore
    dup
    bipush 0xc
    bipush 0x69
    bastore
    dup
    bipush 0xd
    bipush 0x6f
    bastore
    dup
    bipush 0xe
    bipush 0x6e
    bastore
    aastore
    dup
    iconst_4
    bipush 0x7
    newarray 0x8
    dup
    iconst_0
    bipush 0x68
    bastore
    dup
    iconst_1
    bipush 0x65
    bastore
    dup
    iconst_2
    bipush 0x72
    bastore
    dup
    iconst_3
    bipush 0x6f
    bastore
    dup
    iconst_4
    bipush 0x65
    bastore
    dup
    iconst_5
    bipush 0x73
    bastore
    dup
    bipush 0x6
    bipush 0x2f
    bastore
    aastore
    dup
    iconst_5
    bipush 0x11
    newarray 0x8
    dup
    iconst_0
    bipush 0x2f
    bastore
    dup
    iconst_1
    bipush 0x3f
    bastore
    dup
    iconst_2
    bipush 0x61
    bastore
    dup
    iconst_3
    bipush 0x70
    bastore
    dup
    iconst_4
    bipush 0x70
    bastore
    dup
    iconst_5
    bipush 0x3d
    bastore
    dup
    bipush 0x6
    bipush 0x31
    bastore
    dup
    bipush 0x7
    bipush 0x26
    bastore
    dup
    bipush 0x8
    bipush 0x70
    bastore
    dup
    bipush 0x9
    bipush 0x61
    bastore
    dup
    bipush 0xa
    bipush 0x73
    bastore
    dup
    bipush 0xb
    bipush 0x73
    bastore
    dup
    bipush 0xc
    bipush 0x77
    bastore
    dup
    bipush 0xd
    bipush 0x6f
    bastore
    dup
    bipush 0xe
    bipush 0x72
    bastore
    dup
    bipush 0xf
    bipush 0x64
    bastore
    dup
    bipush 0x10
    bipush 0x3d
    bastore
    aastore
    bipush 0x6
    bipush 0x7
    newarray 0x8
    dup
    iconst_0
    bipush 0x26
    bastore
    dup
    iconst_1
    bipush 0x6c
    bastore
    dup
    iconst_2
    bipush 0x6f
    bastore
    dup
    iconst_3
    bipush 0x67
    bastore
    dup
    iconst_4
    bipush 0x69
    bastore
    dup
    iconst_5
    bipush 0x6e
    bastore
    dup
    bipush 0x6
    bipush 0x3d
    bastore
    aastore
    aconst_null
    putstatic e->b:[Ljava/lang/String;
    aconst_null
    putstatic e->c:[Ljava/lang/String;
    aconst_null
    putstatic e->w:Ljava/lang/String;
    ldc 'GET'
    putstatic e->x:Ljava/lang/String;
    new java/util/Hashtable
    dup
    invokespecial java/util/Hashtable-><init>()V
    putstatic e->b:Ljava/util/Hashtable;
    iconst_2
    anewarray java/lang/String
    dup
    iconst_0
    ldc ''
    aastore
    dup
    iconst_1
    ldc ''
    aastore
    putstatic e->d:[Ljava/lang/String;
    aconst_null
    putstatic e->a:Ljavax/microedition/midlet/MIDlet;
    aconst_null
    putstatic e->z:Ljava/lang/String;
    aconst_null
    putstatic e->A:Ljava/lang/String;
    aconst_null
    putstatic e->B:Ljava/lang/String;
    iconst_0
    putstatic e->g:Z
    aconst_null
    putstatic e->C:Ljava/lang/String;
    aconst_null
    putstatic e->c:Ljava/util/Hashtable;
    aconst_null
    putstatic e->a:Le;
    invokestatic java/lang/System->currentTimeMillis()J
    ldc2_w 2147483647
    land
    l2i
    putstatic e->d:I
    iconst_0
    putstatic e->h:Z
    ldc '0123456789ABCDEF'
    putstatic e->D:Ljava/lang/String;
    invokestatic e->a()[Ljava/lang/String;
    putstatic e->f:[Ljava/lang/String;
    return
.end method
