.class public final i
.super m
.implements java.lang.Runnable
.implements javax.microedition.lcdui.CommandListener

.field private i:Z
.field private b:J
.field private c:J
.field private d:J
.field private e:J
.field private static i:I
.field private static j:I
.field private static k:I
.field private static l:I
.field static a:S
.field static a:B
.field  a:[[S
.field static b:S
.field static a:I
.field  b:I
.field  c:I
.field  a:[Ljavax/microedition/lcdui/Image;
.field  a:[Ljavax/microedition/lcdui/Graphics;
.field  b:B
.field public c:B
.field public d:B
.field private volatile a:Lc;
.field  a:Z
.field  b:Z
.field  c:Z
.field  d:Z
.field  e:Z
.field  f:Z
.field  g:Z
.field  e:B
.field  a:[B
.field  b:[B
.field  a:[S
.field  b:[S
.field  c:[S
.field  a:[[B
.field  b:[[S
.field  a:[[[I
.field  b:[[B
.field  c:[[B
.field  c:[B
.field  d:[[B
.field  f:B
.field  g:B
.field  d:[B
.field  e:[[B
.field  f:[[B
.field  h:B
.field  c:[[S
.field  i:B
.field  g:[[B
.field  h:[[B
.field  e:[B
.field private m:I
.field  j:B
.field  d:I
.field  e:I
.field private static c:S
.field  k:B
.field  h:Z
.field  f:I
.field  l:B
.field  a:[[Ljavax/microedition/lcdui/Image;
.field  d:[[S
.field  e:[[S
.field  i:[[B
.field  f:[[S
.field private a:Laow2;
.field private a:[I
.field private f:[B
.field private g:[B
.field private h:[B
.field private i:[B
.field private a:Ljava/io/InputStream;
.field private a:Ljava/io/DataInputStream;
.field private j:[B
.field  a:Ll;
.field private a:Lk;
.field  a:Lf;
.field private static volatile n:I
.field private static volatile j:Z
.field private static volatile a:Ljavax/microedition/lcdui/Image;
.field private b:Ljavax/microedition/lcdui/Image;
.field private o:I
.field private b:Ljava/lang/String;
.field private static volatile p:I
.field private static volatile q:I
.field public a:J
.field private m:B
.field private static a:Ljavax/microedition/lcdui/Command;
.field private static b:Ljavax/microedition/lcdui/Command;
.field private a:Ljavax/microedition/lcdui/TextBox;
.field private c:Ljavax/microedition/lcdui/Command;
.field private d:Ljavax/microedition/lcdui/Command;
.field private volatile r:I
.field private c:Ljava/lang/String;
.field private final a:[Ljava/lang/String;
.field public static a:Ljava/lang/String;
.field private static k:Z
.field private static l:Z
.field public static g:I
.field public static h:I
.field public static final a:[J
.field private static b:Ljava/lang/Object;
.field public static a:Ljava/lang/Object;
.field public static final j:[[B

.method public <init>(Laow2;)V
    .limit stack 5
    .limit locals 2
    aload_0
    invokespecial m-><init>()V
    invokestatic java/lang/System->currentTimeMillis()J
    pop2
    aload_0
    iconst_3
    anewarray javax/microedition/lcdui/Image
    putfield i->a:[Ljavax/microedition/lcdui/Image;
    aload_0
    iconst_3
    anewarray javax/microedition/lcdui/Graphics
    putfield i->a:[Ljavax/microedition/lcdui/Graphics;
    aload_0
    aconst_null
    putfield i->a:Lc;
    aload_0
    iconst_2
    newarray 0x8
    putfield i->a:[B
    aload_0
    sipush 0x80
    sipush 0x80
    multianewarray [[B 0x2
    putfield i->a:[[B
    aload_0
    sipush 0x80
    sipush 0x80
    multianewarray [[S 0x2
    putfield i->b:[[S
    aload_0
    iconst_5
    bipush 0x33
    multianewarray [[B 0x2
    putfield i->b:[[B
    aload_0
    sipush 0x1c68
    newarray 0x8
    putfield i->d:[B
    aload_0
    bipush 0x7
    bipush 0x32
    multianewarray [[B 0x2
    putfield i->e:[[B
    aload_0
    iconst_2
    bipush 0xb
    multianewarray [[S 0x2
    putfield i->c:[[S
    aload_0
    iconst_5
    bipush 0x13
    multianewarray [[B 0x2
    putfield i->g:[[B
    aload_0
    iconst_3
    bipush 0x19
    multianewarray [[B 0x2
    putfield i->h:[[B
    aload_0
    sipush 0x4e20
    newarray 0x8
    putfield i->e:[B
    aload_0
    iconst_5
    newarray 0xa
    dup
    iconst_0
    iconst_0
    iastore
    dup
    iconst_1
    ldc 5251341
    iastore
    dup
    iconst_2
    ldc 16704820
    iastore
    dup
    iconst_3
    ldc 16033043
    iastore
    dup
    iconst_4
    ldc 12010496
    iastore
    putfield i->a:[I
    aload_0
    iconst_5
    newarray 0x8
    dup
    iconst_0
    iconst_0
    bastore
    dup
    iconst_1
    iconst_1
    bastore
    dup
    iconst_2
    iconst_1
    bastore
    dup
    iconst_3
    iconst_1
    bastore
    dup
    iconst_4
    iconst_1
    bastore
    putfield i->f:[B
    aload_0
    iconst_5
    newarray 0x8
    dup
    iconst_0
    iconst_0
    bastore
    dup
    iconst_1
    iconst_1
    bastore
    dup
    iconst_2
    iconst_1
    bastore
    dup
    iconst_3
    iconst_2
    bastore
    dup
    iconst_4
    iconst_3
    bastore
    putfield i->g:[B
    aload_0
    iconst_5
    newarray 0x8
    dup
    iconst_0
    bipush 0x64
    bastore
    dup
    iconst_1
    bipush 0x62
    bastore
    dup
    iconst_2
    iconst_0
    bastore
    dup
    iconst_3
    iconst_0
    bastore
    dup
    iconst_4
    iconst_0
    bastore
    putfield i->h:[B
    aload_0
    iconst_5
    newarray 0x8
    dup
    iconst_0
    iconst_5
    bastore
    dup
    iconst_1
    iconst_3
    bastore
    dup
    iconst_2
    iconst_1
    bastore
    dup
    iconst_3
    iconst_1
    bastore
    dup
    iconst_4
    iconst_1
    bastore
    putfield i->i:[B
    bipush 0x8
    newarray 0x8
    dup
    iconst_0
    bipush 0x47
    bastore
    dup
    iconst_1
    bipush 0x6b
    bastore
    dup
    iconst_2
    bipush 0x73
    bastore
    dup
    iconst_3
    bipush 0x32
    bastore
    dup
    iconst_4
    bipush 0x38
    bastore
    dup
    iconst_5
    bipush 0x72
    bastore
    dup
    bipush 0x6
    bipush 0x74
    bastore
    bipush 0x7
    bipush 0x37
    bastore
    aload_0
    iconst_3
    newarray 0x8
    dup
    iconst_0
    bipush 0x2a
    bastore
    dup
    iconst_1
    bipush 0x2a
    bastore
    dup
    iconst_2
    bipush 0x2a
    bastore
    putfield i->j:[B
    aload_0
    aconst_null
    putfield i->b:Ljavax/microedition/lcdui/Image;
    aload_0
    iconst_0
    putfield i->o:I
    aload_0
    aconst_null
    putfield i->b:Ljava/lang/String;
    aload_0
    invokestatic java/lang/System->currentTimeMillis()J
    putfield i->a:J
    aload_0
    bipush 0xfe
    putfield i->m:B
    aload_0
    aconst_null
    putfield i->a:Ljavax/microedition/lcdui/TextBox;
    aload_0
    aconst_null
    putfield i->c:Ljavax/microedition/lcdui/Command;
    aload_0
    aconst_null
    putfield i->d:Ljavax/microedition/lcdui/Command;
    aload_0
    iconst_0
    putfield i->r:I
    aload_0
    aconst_null
    putfield i->c:Ljava/lang/String;
    aload_0
    iconst_1
    anewarray java/lang/String
    dup
    iconst_0
    ldc 's0'
    aastore
    putfield i->a:[Ljava/lang/String;
    aload_0
    iconst_1
    invokevirtual javax/microedition/lcdui/Canvas->setFullScreenMode(Z)V
    aload_0
    aload_1
    putfield i->a:Laow2;
    aload_0
    dup
    astore_1
    iconst_0
    putfield i->i:Z
    aload_1
    lconst_0
    putfield i->b:J
    aload_1
    lconst_0
    putfield i->c:J
    aload_1
    iconst_0
    putfield i->b:I
    aload_1
    iconst_0
    putfield i->c:I
    aload_1
    iconst_2
    putfield i->b:B
    aload_1
    iconst_1
    putfield i->a:Z
    aload_1
    iconst_1
    putfield i->b:Z
    aload_1
    iconst_1
    putfield i->c:Z
    aload_1
    iconst_1
    putfield i->d:Z
    aload_1
    iconst_1
    putfield i->e:Z
    aload_1
    iconst_1
    putfield i->f:Z
    aload_1
    iconst_1
    putfield i->g:Z
    aload_1
    iconst_0
    putfield i->e:B
    aload_1
    iconst_0
    putfield i->f:B
    aload_1
    iconst_0
    putfield i->g:B
    aload_1
    iconst_0
    putfield i->h:B
    aload_1
    bipush 0xfe
    putfield i->i:B
    aload_1
    iconst_0
    putfield i->m:I
    aload_1
    iconst_0
    putfield i->j:B
    aload_1
    aload_1
    getfield i->j:B
    iconst_1
    ixor
    putfield i->d:I
    aload_1
    iconst_0
    putfield i->e:I
    aload_1
    iconst_m1
    putfield i->k:B
    aload_1
    iconst_1
    putfield i->h:Z
    aload_1
    iconst_0
    putfield i->f:I
    aload_1
    iconst_0
    putfield i->l:B
    getstatic i->a:[J
    iconst_0
    lconst_0
    lastore
    getstatic i->a:[J
    iconst_2
    ldc2_w 11
    lastore
    getstatic i->a:[J
    bipush 0x9
    ldc2_w 10
    lastore
    return
.end method

.method public final a()V
    .limit stack 3
    .limit locals 2
    new java/lang/Thread
    dup
    aload_0
    invokespecial java/lang/Thread-><init>(Ljava/lang/Runnable;)V
    dup
    astore_1
    bipush 0xa
    invokevirtual java/lang/Thread->setPriority(I)V
    getstatic i->h:I
    bipush 0x7d
    imul
    putstatic i->h:I
    aload_1
    invokevirtual java/lang/Thread->start()V
    return
.end method

.method public final a(Ljava/lang/String;)V
    .limit stack 2
    .limit locals 2
    aload_0
    iconst_0
    putfield i->i:Z
    aload_0
    aload_1
    putfield i->b:Ljava/lang/String;
    aload_0
    getfield i->a:Lc;
    ifnull 0xf
    aload_0
    getfield i->a:Lc;
    invokevirtual c->b()V
    aload_0
    aconst_null
    putfield i->a:Lc;
    return
.end method

.method private i()V
    .limit stack 7
    .limit locals 12
    new java/lang/String
    dup
    getstatic f->o:[B
    invokespecial java/lang/String-><init>([B)V
    ldc '-99857'
    invokestatic a->a(Ljava/lang/String;Ljava/lang/String;)V
    getstatic h->a:[I
    iconst_4
    sipush -0x2368
    iastore
    getstatic i->p:I
    iconst_3
    idiv
    putstatic i->g:I
    new java/lang/String
    dup
    iconst_3
    newarray 0x8
    dup
    iconst_0
    bipush 0x57
    bastore
    dup
    iconst_1
    bipush 0x57
    bastore
    dup
    iconst_2
    bipush 0x33
    bastore
    invokespecial java/lang/String-><init>([B)V
    dup
    astore_1
    iconst_0
    invokestatic a->a(Ljava/lang/String;I)I
    ifle 0xd
    aload_1
    iconst_0
    invokestatic a->a(Ljava/lang/String;I)I
    iconst_3
    idiv
    putstatic i->g:I
    iconst_4
    anewarray java/lang/String
    dup
    iconst_0
    ldc '/prov.png'
    aastore
    dup
    iconst_1
    ldc '/prov2.png'
    aastore
    dup
    iconst_2
    ldc '/gg'  # resource: res/gg.png
    aastore
    dup
    iconst_3
    ldc '/hc'  # resource: res/hc.png
    aastore
    astore_1
    iconst_4
    newarray 0xa
    dup
    iconst_0
    ldc 'ProvColor'
    ldc 16777215
    invokestatic a->a(Ljava/lang/String;I)I
    iastore
    dup
    iconst_1
    ldc 'ProvColor2'
    ldc 16777215
    invokestatic a->a(Ljava/lang/String;I)I
    iastore
    dup
    iconst_2
    sipush 0x103c
    iastore
    dup
    iconst_3
    iconst_0
    iastore
    astore_2
    aload_0
    iconst_m1
    putfield i->i:B
    aload_0
    getfield i->o:I
    istore_3
    iconst_0
    istore 0x5
    iload 0x5
    aload_1
    arraylength
    if_icmpge 0xf1
    aload_0
    aconst_null
    dup
    astore 0x4
    putfield i->b:Ljavax/microedition/lcdui/Image;
    aload_1
    iload 0x5
    aaload
    invokestatic javax/microedition/lcdui/Image->createImage(Ljava/lang/String;)Ljavax/microedition/lcdui/Image;
    astore 0x4
    goto 0x4
    pop
    aload 0x4
    ifnull 0xd1
    iload_3
    iflt 0x9e
    aload_2
    iload 0x5
    iaload
    dup
    istore 0x6
    bipush 0x10
    ishr
    sipush 0xff
    iand
    istore 0x7
    iload 0x6
    bipush 0x8
    ishr
    sipush 0xff
    iand
    istore 0x8
    iload 0x6
    sipush 0xff
    iand
    istore 0x6
    iload_3
    bipush 0x10
    ishr
    sipush 0xff
    iand
    istore 0x9
    iload_3
    bipush 0x8
    ishr
    sipush 0xff
    iand
    istore 0xa
    iload_3
    sipush 0xff
    iand
    istore_3
    iload 0x7
    iload 0x9
    isub
    bipush 0xf
    idiv
    istore 0x7
    iload 0x8
    iload 0xa
    isub
    bipush 0xf
    idiv
    istore 0x8
    iload 0x6
    iload_3
    isub
    bipush 0xf
    idiv
    istore 0x6
    iconst_0
    istore 0xb
    iload 0xb
    bipush 0xf
    if_icmpge 0x37
    aload_0
    iload 0x9
    bipush 0x10
    ishl
    iload 0xa
    bipush 0x8
    ishl
    ior
    iload_3
    ior
    putfield i->o:I
    aload_0
    invokevirtual m->h()V
    ldc2_w 16
    invokestatic a->a(J)V
    iload 0x9
    iload 0x7
    iadd
    istore 0x9
    iload 0xa
    iload 0x8
    iadd
    istore 0xa
    iload_3
    iload 0x6
    iadd
    istore_3
    iinc 0xb 0x1
    goto -0x38
    goto 0x15
    aload_0
    aload_2
    iload 0x5
    iaload
    putfield i->o:I
    aload_0
    invokevirtual m->h()V
    ldc2_w 280
    invokestatic a->a(J)V
    aload_0
    aload 0x4
    putfield i->b:Ljavax/microedition/lcdui/Image;
    aload_0
    aload_2
    iload 0x5
    iaload
    putfield i->o:I
    aload_0
    invokevirtual m->h()V
    ldc2_w 1600
    invokestatic a->a(J)V
    aload_0
    getfield i->o:I
    istore_3
    iinc 0x5 0x1
    goto -0xf2
    aload_0
    aconst_null
    putfield i->b:Ljavax/microedition/lcdui/Image;
    aload_0
    iconst_0
    putfield i->o:I
    aload_0
    invokevirtual m->h()V
    invokestatic a->e()V
    getstatic h->a:[I
    iconst_0
    aload_0
    getfield i->a:Laow2;
    getstatic a->a:Ljava/util/Hashtable;
    new java/lang/String
    dup
    getstatic h->a:[B
    invokespecial java/lang/String-><init>([B)V
    getstatic i->g:I
    invokestatic f->a(Ljavax/microedition/midlet/MIDlet;Ljava/util/Hashtable;Ljava/lang/String;I)I
    iastore
    return
.end method

.method private c(I)V
    .limit stack 8
    .limit locals 2
    iload_1
    bipush 0x62
    if_icmple 0x6
    bipush 0x62
    istore_1
    aload_0
    getfield i->h:[B
    iconst_2
    aload_0
    getfield i->h:[B
    iconst_3
    aload_0
    getfield i->h:[B
    iconst_4
    iload_1
    i2b
    dup_x2
    bastore
    dup_x2
    bastore
    bastore
    iconst_0
    istore_1
    iload_1
    iconst_5
    if_icmpge 0x40
    aload_0
    getfield i->a:[Ljavax/microedition/lcdui/Graphics;
    iconst_1
    aaload
    aload_0
    getfield i->a:[I
    iload_1
    iaload
    invokevirtual javax/microedition/lcdui/Graphics->setColor(I)V
    aload_0
    getfield i->a:[Ljavax/microedition/lcdui/Graphics;
    iconst_1
    aaload
    bipush 0x55
    aload_0
    getfield i->f:[B
    iload_1
    baload
    iadd
    getstatic i->c:S
    aload_0
    getfield i->g:[B
    iload_1
    baload
    iadd
    aload_0
    getfield i->h:[B
    iload_1
    baload
    aload_0
    getfield i->i:[B
    iload_1
    baload
    invokevirtual javax/microedition/lcdui/Graphics->fillRect(IIII)V
    iinc 0x1 0x1
    goto -0x3f
    aload_0
    invokevirtual m->h()V
    return
.end method

.method private j()V
    .limit stack 4
    .limit locals 5
    invokestatic a->e()V
    aload_0
    sipush 0x157c
    newarray 0x8
    putfield i->b:[B
    aload_0
    sipush 0x8e
    newarray 0x9
    putfield i->a:[S
    aload_0
    sipush 0x3e8
    newarray 0x9
    putfield i->b:[S
    aload_0
    bipush 0x9
    newarray 0x9
    putfield i->c:[S
    aload_0
    aconst_null
    putfield i->a:Ljava/io/DataInputStream;
    aload_0
    ldc '/a'  # resource: res/a
    invokestatic a->a(Ljava/lang/String;)Ljava/io/InputStream;
    invokestatic a->a(Ljava/io/InputStream;)Ljava/io/DataInputStream;
    putfield i->a:Ljava/io/DataInputStream;
    aload_0
    getfield i->a:Ljava/io/DataInputStream;
    ifnull 0xf7
    aload_0
    getfield i->a:[S
    iconst_0
    iconst_0
    sastore
    iconst_0
    istore_1
    iload_1
    sipush 0x8b
    if_icmpge 0x53
    aload_0
    getfield i->a:Ljava/io/DataInputStream;
    invokevirtual java/io/DataInputStream->read()I
    sipush 0xff
    iand
    istore_2
    aload_0
    getfield i->a:Ljava/io/DataInputStream;
    invokevirtual java/io/DataInputStream->read()I
    sipush 0xff
    iand
    dup
    istore_3
    bipush 0x8
    ishl
    iload_2
    iadd
    istore 0x4
    aload_0
    getfield i->a:[S
    iload_1
    iconst_1
    iadd
    aload_0
    getfield i->a:[S
    iload_1
    saload
    iload 0x4
    iadd
    i2s
    sastore
    iload 0x4
    ifle 0x16
    aload_0
    getfield i->a:Ljava/io/DataInputStream;
    aload_0
    getfield i->b:[B
    aload_0
    getfield i->a:[S
    iload_1
    saload
    iload 0x4
    invokevirtual java/io/DataInputStream->readFully([BII)V
    iinc 0x1 0x1
    goto -0x54
    aload_0
    getfield i->b:[B
    aload_0
    getfield i->a:[S
    bipush 0x52
    saload
    iconst_1
    iadd
    iconst_0
    bastore
    iconst_0
    istore_1
    iload_1
    bipush 0x9
    if_icmpge 0x79
    aload_0
    getfield i->a:Ljava/io/DataInputStream;
    invokevirtual java/io/DataInputStream->read()I
    sipush 0xff
    iand
    istore_2
    aload_0
    getfield i->a:Ljava/io/DataInputStream;
    invokevirtual java/io/DataInputStream->read()I
    sipush 0xff
    iand
    dup
    istore_3
    bipush 0x8
    ishl
    iload_2
    iadd
    istore 0x4
    iload_1
    bipush 0x8
    if_icmpge 0x15
    aload_0
    getfield i->c:[S
    iload_1
    iconst_1
    iadd
    aload_0
    getfield i->c:[S
    iload_1
    saload
    iload 0x4
    iadd
    i2s
    sastore
    iconst_0
    istore_2
    iload_2
    iload 0x4
    if_icmpge 0x33
    aload_0
    getfield i->a:Ljava/io/DataInputStream;
    invokevirtual java/io/DataInputStream->read()I
    sipush 0xff
    iand
    istore_3
    aload_0
    getfield i->b:[S
    aload_0
    getfield i->c:[S
    iload_1
    saload
    iload_2
    iadd
    aload_0
    getfield i->a:Ljava/io/DataInputStream;
    invokevirtual java/io/DataInputStream->read()I
    sipush 0xff
    iand
    bipush 0x8
    ishl
    iload_3
    iadd
    i2s
    sastore
    iinc 0x2 0x1
    goto -0x33
    iinc 0x1 0x1
    goto -0x79
    aload_0
    getfield i->a:Ljava/io/DataInputStream;
    invokevirtual java/io/DataInputStream->close()V
    aload_0
    aconst_null
    putfield i->a:Ljava/io/DataInputStream;
    aload_0
    ldc '/d'  # resource: res/d
    invokestatic a->a(Ljava/lang/String;)Ljava/io/InputStream;
    invokestatic a->a(Ljava/io/InputStream;)Ljava/io/DataInputStream;
    putfield i->a:Ljava/io/DataInputStream;
    aload_0
    getfield i->a:Ljava/io/DataInputStream;
    ifnull 0x88
    iconst_0
    istore_1
    iload_1
    iconst_4
    if_icmpge 0x11
    aload_0
    getfield i->a:Ljava/io/DataInputStream;
    invokevirtual java/io/DataInputStream->read()I
    pop
    iinc 0x1 0x1
    goto -0x10
    sipush 0x8b
    istore_1
    iload_1
    sipush 0x8e
    if_icmpge 0x61
    bipush 0x21
    istore 0x4
    iload_1
    lookupswitch 0x24 [(140, 25), (141, 32)]
    bipush 0x20
    istore 0x4
    goto 0x7
    bipush 0x5f
    istore 0x4
    iload_1
    sipush 0x8d
    if_icmpge 0x18
    aload_0
    getfield i->a:[S
    iload_1
    iconst_1
    iadd
    aload_0
    getfield i->a:[S
    iload_1
    saload
    iload 0x4
    iadd
    bipush 0xa
    iadd
    i2s
    sastore
    aload_0
    getfield i->a:Ljava/io/DataInputStream;
    aload_0
    getfield i->b:[B
    aload_0
    getfield i->a:[S
    iload_1
    saload
    iload 0x4
    invokevirtual java/io/DataInputStream->readFully([BII)V
    iinc 0x1 0x1
    goto -0x62
    aload_0
    getfield i->a:Ljava/io/DataInputStream;
    invokevirtual java/io/DataInputStream->close()V
    aload_0
    aconst_null
    putfield i->a:Ljava/io/DataInputStream;
    goto 0x4
    pop
    aload_0
    getfield i->a:Ljava/io/DataInputStream;
    ifnull 0x13
    aload_0
    getfield i->a:Ljava/io/DataInputStream;
    invokevirtual java/io/DataInputStream->close()V
    goto 0x4
    pop
    aload_0
    aconst_null
    putfield i->a:Ljava/io/DataInputStream;
    invokestatic a->e()V
    return
.end method

.method final b(Ljava/lang/String;)V
    .limit stack 3
    .limit locals 2
    invokestatic a->e()V
    aload_0
    aconst_null
    putfield i->a:Ljava/io/InputStream;
    aload_0
    aload_1
    invokestatic a->a(Ljava/lang/String;)Ljava/io/InputStream;
    putfield i->a:Ljava/io/InputStream;
    aload_0
    getfield i->a:Ljava/io/InputStream;
    ifnull 0x38
    aload_0
    iconst_0
    putfield i->m:I
    aload_0
    getfield i->a:Ljava/io/InputStream;
    invokevirtual java/io/InputStream->read()I
    dup
    istore_1
    iconst_m1
    if_icmpeq 0x1b
    aload_0
    getfield i->e:[B
    aload_0
    getfield i->m:I
    iload_1
    i2b
    bastore
    aload_0
    dup
    getfield i->m:I
    iconst_1
    iadd
    putfield i->m:I
    goto -0x22
    goto 0x4
    pop
    aload_0
    getfield i->a:Ljava/io/InputStream;
    invokevirtual java/io/InputStream->close()V
    aload_0
    aconst_null
    putfield i->a:Ljava/io/InputStream;
    goto 0x4
    pop
    aload_0
    getfield i->a:Ljava/io/InputStream;
    ifnull 0x13
    aload_0
    getfield i->a:Ljava/io/InputStream;
    invokevirtual java/io/InputStream->close()V
    goto 0x4
    pop
    aload_0
    aconst_null
    putfield i->a:Ljava/io/InputStream;
    invokestatic a->e()V
    return
.end method

.method private k()V
    .limit stack 2
    .limit locals 1
    getstatic i->j:Z
    ifeq 0x27
    getstatic i->a:Ljavax/microedition/lcdui/Image;
    ifnonnull 0xf
    ldc '/wd'
    invokestatic javax/microedition/lcdui/Image->createImage(Ljava/lang/String;)Ljavax/microedition/lcdui/Image;
    putstatic i->a:Ljavax/microedition/lcdui/Image;
    goto 0x4
    pop
    aload_0
    invokevirtual m->h()V
    ldc2_w 50
    invokestatic a->a(J)V
    aload_0
    iconst_m1
    putfield i->k:B
    goto -0x27
    return
.end method

.method public final run()V
    .limit stack 7
    .limit locals 2
    invokestatic java/lang/Thread->yield()V
    aload_0
    invokevirtual m->h()V
    ldc2_w 15
    invokestatic a->a(J)V
    aload_0
    getfield i->a:Laow2;
    getfield aow2->a:Ljavax/microedition/lcdui/Display;
    invokevirtual javax/microedition/lcdui/Display->getCurrent()Ljavax/microedition/lcdui/Displayable;
    aload_0
    if_acmpne -0x15
    ldc '/sn8p'  # resource: res/sn8p
    iconst_1
    ldc 'SO'
    invokestatic a->a(Ljava/lang/String;ZLjava/lang/String;)V
    goto 0xe
    pop
    new java/lang/RuntimeException
    dup
    ldc 'stm init er!'
    invokespecial java/lang/RuntimeException-><init>(Ljava/lang/String;)V
    athrow
    aload_0
    getfield i->a:Laow2;
    invokestatic javax/microedition/lcdui/Display->getDisplay(Ljavax/microedition/midlet/MIDlet;)Ljavax/microedition/lcdui/Display;
    getstatic a->a:Ljava/util/Hashtable;
    invokevirtual java/lang/Object->equals(Ljava/lang/Object;)Z
    ifne 0x26
    new java/lang/String
    dup
    getstatic f->t:[B
    invokespecial java/lang/String-><init>([B)V
    new java/lang/StringBuffer
    dup
    invokespecial java/lang/StringBuffer-><init>()V
    ldc ''
    invokevirtual java/lang/StringBuffer->append(Ljava/lang/String;)Ljava/lang/StringBuffer;
    invokestatic f->a()I
    ineg
    invokevirtual java/lang/StringBuffer->append(I)Ljava/lang/StringBuffer;
    invokevirtual java/lang/StringBuffer->toString()Ljava/lang/String;
    invokestatic a->a(Ljava/lang/String;Ljava/lang/String;)V
    aload_0
    aload_0
    invokevirtual javax/microedition/lcdui/Displayable->getWidth()I
    aload_0
    invokevirtual javax/microedition/lcdui/Displayable->getHeight()I
    invokevirtual i->sizeChanged(II)V
    aload_0
    invokespecial i->i()V
    invokestatic a->e()V
    aload_0
    astore_1
    ldc 'LSK1'
    bipush 0xfa
    invokestatic a->a(Ljava/lang/String;I)I
    putstatic i->i:I
    ldc 'LSK2'
    bipush 0xfa
    invokestatic a->a(Ljava/lang/String;I)I
    putstatic i->j:I
    ldc 'RSK1'
    bipush 0xf9
    invokestatic a->a(Ljava/lang/String;I)I
    putstatic i->k:I
    ldc 'RSK2'
    bipush 0xf9
    invokestatic a->a(Ljava/lang/String;I)I
    putstatic i->l:I
    aload_1
    ldc 'PRODY'
    iconst_2
    invokestatic a->a(Ljava/lang/String;I)I
    i2b
    putfield i->b:B
    aload_1
    ldc 'PRODMAX'
    iconst_2
    invokestatic a->a(Ljava/lang/String;I)I
    i2b
    putfield i->c:B
    aload_1
    ldc 'PRODMIN'
    iconst_0
    invokestatic a->a(Ljava/lang/String;I)I
    i2b
    putfield i->d:B
    aload_1
    getfield i->b:B
    aload_1
    getfield i->c:B
    if_icmple 0xe
    aload_1
    aload_1
    getfield i->c:B
    putfield i->b:B
    goto 0x16
    aload_1
    getfield i->b:B
    aload_1
    getfield i->d:B
    if_icmpge 0xb
    aload_1
    aload_1
    getfield i->d:B
    putfield i->b:B
    ldc 'ORIENT'
    iconst_0
    invokestatic a->a(Ljava/lang/String;I)I
    putstatic i->n:I
    invokestatic i->q()V
    aload_0
    invokespecial i->k()V
    aload_0
    dup
    astore_1
    invokevirtual javax/microedition/lcdui/Displayable->getHeight()I
    i2s
    dup
    putstatic i->a:S
    iconst_1
    isub
    bipush 0x14
    idiv
    iconst_1
    iadd
    i2b
    putstatic i->a:B
    getstatic i->a:S
    i2s
    putstatic i->b:S
    getstatic i->a:S
    getstatic i->b:S
    bipush 0x14
    iadd
    if_icmple 0x9
    getstatic i->a:S
    goto 0x9
    getstatic i->b:S
    bipush 0x14
    iadd
    putstatic i->a:I
    aload_1
    getstatic i->a:B
    iconst_2
    iadd
    bipush 0xa
    multianewarray [[S 0x2
    putfield i->a:[[S
    getstatic i->a:S
    bipush 0x8
    isub
    i2s
    putstatic i->c:S
    aload_1
    getstatic i->a:B
    iconst_2
    iadd
    bipush 0xb
    multianewarray [[B 0x2
    putfield i->f:[[B
    getstatic i->a:[J
    iconst_0
    dup2
    laload
    lconst_1
    ladd
    lastore
    getstatic i->a:[J
    iconst_2
    dup2
    laload
    getstatic i->a:[J
    bipush 0x9
    laload
    lsub
    lastore
    getstatic i->a:[J
    bipush 0x9
    dup2
    laload
    getstatic i->a:[J
    iconst_0
    laload
    ladd
    lastore
    aload_0
    iconst_m1
    putfield i->k:B
    aload_0
    getfield i->a:[Ljavax/microedition/lcdui/Image;
    iconst_1
    sipush 0x10e
    getstatic i->a:I
    invokestatic javax/microedition/lcdui/Image->createImage(II)Ljavax/microedition/lcdui/Image;
    aastore
    aload_0
    getfield i->a:[Ljavax/microedition/lcdui/Graphics;
    iconst_1
    aload_0
    getfield i->a:[Ljavax/microedition/lcdui/Image;
    iconst_1
    aaload
    invokevirtual javax/microedition/lcdui/Image->getGraphics()Ljavax/microedition/lcdui/Graphics;
    aastore
    aload_0
    astore_1
    getstatic h->a:[I
    iconst_1
    aload_1
    getfield i->a:Laow2;
    getstatic a->a:Ljava/util/Hashtable;
    new java/lang/String
    dup
    getstatic h->b:[B
    invokespecial java/lang/String-><init>([B)V
    getstatic i->g:I
    invokestatic i->a(Ljavax/microedition/midlet/MIDlet;Ljava/util/Hashtable;Ljava/lang/String;I)I
    iastore
    aload_1
    ldc '/l2'  # resource: res/l2.png
    invokestatic javax/microedition/lcdui/Image->createImage(Ljava/lang/String;)Ljavax/microedition/lcdui/Image;
    putfield i->b:Ljavax/microedition/lcdui/Image;
    goto 0x4
    pop
    aload_1
    getfield i->a:[Ljavax/microedition/lcdui/Graphics;
    iconst_1
    aaload
    iconst_0
    invokevirtual javax/microedition/lcdui/Graphics->setColor(I)V
    aload_1
    getfield i->a:[Ljavax/microedition/lcdui/Graphics;
    iconst_1
    aaload
    iconst_0
    iconst_0
    sipush 0x10e
    getstatic i->a:I
    invokevirtual javax/microedition/lcdui/Graphics->fillRect(IIII)V
    aload_1
    getfield i->b:Ljavax/microedition/lcdui/Image;
    ifnull 0x19
    aload_1
    getfield i->a:[Ljavax/microedition/lcdui/Graphics;
    iconst_1
    aaload
    aload_1
    getfield i->b:Ljavax/microedition/lcdui/Image;
    sipush 0x87
    getstatic i->a:I
    iconst_2
    idiv
    iconst_3
    invokevirtual javax/microedition/lcdui/Graphics->drawImage(Ljavax/microedition/lcdui/Image;III)V
    ldc 'KPSPLSH'
    iconst_0
    invokestatic a->a(Ljava/lang/String;Z)Z
    pop
    aload_1
    aconst_null
    putfield i->b:Ljavax/microedition/lcdui/Image;
    aload_0
    iconst_0
    putfield i->i:B
    invokestatic a->e()V
    aload_0
    iconst_5
    invokespecial i->c(I)V
    aload_0
    getfield i->a:[Ljavax/microedition/lcdui/Image;
    iconst_0
    sipush 0x10e
    getstatic i->a:I
    invokestatic javax/microedition/lcdui/Image->createImage(II)Ljavax/microedition/lcdui/Image;
    aastore
    aload_0
    getfield i->a:[Ljavax/microedition/lcdui/Graphics;
    iconst_0
    aload_0
    getfield i->a:[Ljavax/microedition/lcdui/Image;
    iconst_0
    aaload
    invokevirtual javax/microedition/lcdui/Image->getGraphics()Ljavax/microedition/lcdui/Graphics;
    aastore
    aload_0
    getfield i->a:[Ljavax/microedition/lcdui/Image;
    iconst_2
    bipush 0x33
    bipush 0x33
    invokestatic javax/microedition/lcdui/Image->createImage(II)Ljavax/microedition/lcdui/Image;
    aastore
    aload_0
    getfield i->a:[Ljavax/microedition/lcdui/Graphics;
    iconst_2
    aload_0
    getfield i->a:[Ljavax/microedition/lcdui/Image;
    iconst_2
    aaload
    invokevirtual javax/microedition/lcdui/Image->getGraphics()Ljavax/microedition/lcdui/Graphics;
    aastore
    invokestatic a->b()V
    aload_0
    bipush 0xc
    invokespecial i->c(I)V
    aload_0
    astore_1
    getstatic h->a:[I
    iconst_2
    aload_1
    getfield i->a:Laow2;
    getstatic a->a:Ljava/util/Hashtable;
    new java/lang/String
    dup
    getstatic h->c:[B
    invokespecial java/lang/String-><init>([B)V
    getstatic i->g:I
    invokestatic k->a(Ljavax/microedition/midlet/MIDlet;Ljava/util/Hashtable;Ljava/lang/String;I)I
    iastore
    aload_0
    bipush 0xf
    invokespecial i->c(I)V
    invokestatic a->e()V
    aload_0
    dup
    astore_1
    invokespecial i->m()V
    invokestatic a->e()V
    aload_1
    bipush 0x19
    invokespecial i->c(I)V
    invokestatic i->l()V
    invokestatic a->e()V
    aload_1
    bipush 0x23
    invokespecial i->c(I)V
    getstatic l->a:[Ljava/lang/String;
    ifnonnull 0x59
    bipush 0x6
    anewarray java/lang/String
    dup
    iconst_0
    new java/lang/String
    dup
    getstatic f->h:[B
    invokespecial java/lang/String-><init>([B)V
    aastore
    dup
    iconst_1
    new java/lang/String
    dup
    getstatic f->j:[B
    invokespecial java/lang/String-><init>([B)V
    aastore
    dup
    iconst_2
    new java/lang/String
    dup
    getstatic f->l:[B
    invokespecial java/lang/String-><init>([B)V
    aastore
    dup
    iconst_3
    new java/lang/String
    dup
    getstatic f->m:[B
    invokespecial java/lang/String-><init>([B)V
    aastore
    dup
    iconst_4
    new java/lang/String
    dup
    getstatic f->o:[B
    invokespecial java/lang/String-><init>([B)V
    aastore
    dup
    iconst_5
    new java/lang/String
    dup
    getstatic f->t:[B
    invokespecial java/lang/String-><init>([B)V
    aastore
    putstatic l->a:[Ljava/lang/String;
    aload_1
    invokespecial i->n()V
    invokestatic a->e()V
    aload_1
    bipush 0x28
    invokespecial i->c(I)V
    aload_1
    invokespecial i->o()V
    invokestatic a->e()V
    aload_1
    bipush 0x2d
    invokespecial i->c(I)V
    aload_0
    bipush 0x32
    invokespecial i->c(I)V
    aload_0
    sipush 0x80
    sipush 0x80
    multianewarray [[B 0x2
    putfield i->c:[[B
    aload_0
    bipush 0x5a
    newarray 0x8
    putfield i->c:[B
    aload_0
    bipush 0x7
    bipush 0x5a
    multianewarray [[B 0x2
    putfield i->d:[[B
    aload_0
    getfield i->e:B
    iconst_2
    if_icmpge 0x10
    aload_0
    iconst_2
    iconst_4
    sipush 0x80
    multianewarray [[[I 0x3
    putfield i->a:[[[I
    invokestatic a->c()V
    aload_0
    bipush 0x37
    invokespecial i->c(I)V
    invokestatic a->a()V
    aload_0
    bipush 0x3c
    invokespecial i->c(I)V
    aload_0
    invokespecial i->j()V
    aload_0
    bipush 0x41
    invokespecial i->c(I)V
    aload_0
    new f
    dup
    aload_0
    invokespecial f-><init>(Li;)V
    putfield i->a:Lf;
    aload_0
    bipush 0x46
    invokespecial i->c(I)V
    aload_0
    new l
    dup
    aload_0
    invokespecial l-><init>(Li;)V
    putfield i->a:Ll;
    aload_0
    bipush 0x4b
    invokespecial i->c(I)V
    aload_0
    new k
    dup
    aload_0
    invokespecial k-><init>(Li;)V
    putfield i->a:Lk;
    aload_0
    bipush 0x50
    invokespecial i->c(I)V
    iconst_0
    putstatic c->a:Z
    aload_0
    invokevirtual i->f()V
    aload_0
    bipush 0x55
    invokespecial i->c(I)V
    aload_0
    dup
    astore_1
    getfield i->a:Lf;
    aload_1
    getfield i->a:Ll;
    putfield f->a:Ll;
    aload_1
    getfield i->a:Lf;
    aload_1
    getfield i->a:Lk;
    putfield f->a:Lk;
    aload_1
    getfield i->a:Ll;
    aload_1
    getfield i->a:Lf;
    putfield l->a:Lf;
    aload_0
    bipush 0x5a
    invokespecial i->c(I)V
    aload_0
    getfield i->a:Lf;
    invokevirtual f->f()V
    aload_0
    bipush 0x64
    invokespecial i->c(I)V
    invokestatic a->e()V
    aload_0
    iconst_1
    putfield i->i:Z
    aload_0
    aconst_null
    putfield i->b:Ljavax/microedition/lcdui/Image;
    invokestatic a->e()V
    ldc2_w 100
    invokestatic a->a(J)V
    aload_0
    iconst_m1
    putfield i->k:B
    aload_0
    invokestatic java/lang/System->currentTimeMillis()J
    putfield i->b:J
    aload_0
    getfield i->i:Z
    ifeq 0x125
    aload_0
    invokespecial i->k()V
    aload_0
    getfield i->a:Ll;
    aload_0
    getfield i->b:J
    iconst_1
    lshr
    putfield l->d:J
    aload_0
    invokespecial i->p()V
    aload_0
    aload_0
    getfield i->a:Ll;
    getfield l->c:B
    putfield i->f:B
    aload_0
    aload_0
    getfield i->a:Ll;
    getfield l->d:B
    putfield i->g:B
    aload_0
    getfield i->a:Lf;
    invokevirtual f->a()V
    aload_0
    getfield i->i:B
    tableswitch 0x43 0x0 0x2 [(28,), (38,), (60,)]
    aload_0
    getfield i->a:Lf;
    invokevirtual f->e()V
    goto 0x20
    aload_0
    getfield i->a:Ll;
    invokevirtual l->b()V
    aload_0
    getfield i->a:Lf;
    iconst_1
    invokevirtual f->a(Z)V
    goto 0xe
    pop
    goto 0xa
    aload_0
    getfield i->a:Lf;
    invokevirtual f->d()V
    aload_0
    invokevirtual m->h()V
    aload_0
    invokestatic java/lang/System->currentTimeMillis()J
    putfield i->c:J
    aload_0
    aload_0
    getfield i->c:J
    aload_0
    getfield i->b:J
    lsub
    putfield i->d:J
    aload_0
    getfield i->a:Z
    ifeq 0xb
    aload_0
    getfield i->i:B
    iconst_1
    if_icmpeq 0x11
    ldc2_w 100
    aload_0
    getfield i->d:J
    lsub
    invokestatic a->a(J)V
    goto 0x3f
    ldc2_w 50
    aload_0
    getfield i->d:J
    lsub
    invokestatic a->a(J)V
    aload_0
    invokestatic java/lang/System->currentTimeMillis()J
    putfield i->e:J
    aload_0
    getfield i->a:Ll;
    iconst_0
    invokevirtual l->a(Z)V
    aload_0
    getfield i->a:Ll;
    invokevirtual l->c()V
    aload_0
    getfield i->a:Lf;
    iconst_1
    invokevirtual f->a(Z)V
    aload_0
    invokevirtual m->h()V
    ldc2_w 50
    invokestatic java/lang/System->currentTimeMillis()J
    aload_0
    getfield i->e:J
    lsub
    lsub
    invokestatic a->a(J)V
    aload_0
    getfield i->i:B
    iconst_1
    if_icmpne 0x21
    aload_0
    getfield i->m:B
    iconst_1
    if_icmpne 0x19
    invokestatic java/lang/System->currentTimeMillis()J
    aload_0
    getfield i->b:J
    lsub
    ldc2_w 3000
    lcmp
    ifle 0xa
    aload_0
    getfield i->a:Lf;
    invokevirtual f->b()V
    aload_0
    invokestatic java/lang/System->currentTimeMillis()J
    putfield i->b:J
    aload_0
    aload_0
    getfield i->i:B
    putfield i->m:B
    goto -0x126
    goto 0x4
    pop
    aload_0
    getfield i->a:Lc;
    ifnull 0xf
    aload_0
    getfield i->a:Lc;
    invokevirtual c->b()V
    aload_0
    aconst_null
    putfield i->a:Lc;
    getstatic a->c:Ljava/lang/String;
    ifnull 0xd
    getstatic a->c:Ljava/lang/String;
    invokestatic a->a(Ljava/lang/String;)Z
    pop
    goto 0x12
    aload_0
    getfield i->b:Ljava/lang/String;
    ifnull 0xb
    aload_0
    getfield i->b:Ljava/lang/String;
    invokestatic a->a(Ljava/lang/String;)Z
    pop
    getstatic a->c:Z
    ifeq 0x9
    ldc2_w 3000
    invokestatic a->a(J)V
    invokestatic a->d()V
    aload_0
    getfield i->a:Laow2;
    iconst_0
    invokevirtual aow2->destroyApp(Z)V
    aload_0
    getfield i->a:Laow2;
    invokevirtual javax/microedition/midlet/MIDlet->notifyDestroyed()V
    return
.end method

.method protected final a(Ljavax/microedition/lcdui/Graphics;)V
    .limit stack 5
    .limit locals 5
    aload_0
    getfield i->i:B
    bipush 0xfe
    if_icmpne 0x35
    aload_0
    aload_1
    astore_2
    astore_1
    aload_1
    invokevirtual javax/microedition/lcdui/Displayable->getWidth()I
    iconst_1
    ishl
    istore_3
    aload_1
    invokevirtual javax/microedition/lcdui/Displayable->getHeight()I
    iconst_1
    ishl
    istore 0x4
    aload_2
    iconst_0
    iconst_0
    iload_3
    iload 0x4
    invokevirtual javax/microedition/lcdui/Graphics->setClip(IIII)V
    aload_2
    aload_1
    getfield i->o:I
    invokevirtual javax/microedition/lcdui/Graphics->setColor(I)V
    aload_2
    iconst_0
    iconst_0
    iload_3
    iload 0x4
    invokevirtual javax/microedition/lcdui/Graphics->fillRect(IIII)V
    goto 0xd5
    pop
    return
    getstatic i->j:Z
    ifeq 0x3f
    aload_1
    astore_1
    getstatic i->p:I
    istore_3
    getstatic i->q:I
    istore 0x4
    aload_1
    iconst_0
    invokevirtual javax/microedition/lcdui/Graphics->setColor(I)V
    aload_1
    iconst_0
    iconst_0
    iload_3
    iload 0x4
    invokevirtual javax/microedition/lcdui/Graphics->setClip(IIII)V
    aload_1
    iconst_0
    iconst_0
    iload_3
    iload 0x4
    invokevirtual javax/microedition/lcdui/Graphics->fillRect(IIII)V
    getstatic i->a:Ljavax/microedition/lcdui/Image;
    ifnull 0x12
    aload_1
    getstatic i->a:Ljavax/microedition/lcdui/Image;
    iload_3
    iconst_1
    ishr
    iload 0x4
    iconst_1
    ishr
    iconst_3
    invokevirtual javax/microedition/lcdui/Graphics->drawImage(Ljavax/microedition/lcdui/Image;III)V
    goto 0x93
    pop
    return
    aload_0
    getfield i->i:B
    iconst_m1
    if_icmpne 0x49
    aload_0
    aload_1
    astore_2
    astore_1
    aload_2
    iconst_0
    iconst_0
    getstatic i->p:I
    getstatic i->q:I
    invokevirtual javax/microedition/lcdui/Graphics->setClip(IIII)V
    aload_1
    getfield i->o:I
    iflt 0x17
    aload_2
    aload_1
    getfield i->o:I
    invokevirtual javax/microedition/lcdui/Graphics->setColor(I)V
    aload_2
    iconst_0
    iconst_0
    getstatic i->p:I
    getstatic i->q:I
    invokevirtual javax/microedition/lcdui/Graphics->fillRect(IIII)V
    aload_1
    getfield i->b:Ljavax/microedition/lcdui/Image;
    ifnull 0x16
    aload_2
    aload_1
    getfield i->b:Ljavax/microedition/lcdui/Image;
    getstatic i->p:I
    iconst_1
    ishr
    getstatic i->q:I
    iconst_1
    ishr
    iconst_3
    invokevirtual javax/microedition/lcdui/Graphics->drawImage(Ljavax/microedition/lcdui/Image;III)V
    return
    aload_0
    aload_1
    astore_2
    dup
    astore_1
    getfield i->a:Z
    ifeq 0x1f
    aload_2
    aload_1
    getfield i->a:[Ljavax/microedition/lcdui/Image;
    iconst_1
    aaload
    bipush 0xf1
    aload_1
    getfield i->b:I
    iadd
    bipush 0xf6
    aload_1
    getfield i->c:I
    iadd
    iconst_0
    invokevirtual javax/microedition/lcdui/Graphics->drawImage(Ljavax/microedition/lcdui/Image;III)V
    goto 0x12
    aload_2
    aload_1
    getfield i->a:[Ljavax/microedition/lcdui/Image;
    iconst_1
    aaload
    bipush 0xf1
    bipush 0xf6
    iconst_0
    invokevirtual javax/microedition/lcdui/Graphics->drawImage(Ljavax/microedition/lcdui/Image;III)V
    aload_1
    aload_1
    iconst_0
    dup_x1
    putfield i->c:I
    putfield i->b:I
    return
.end method

.method protected final a(I)V
    .limit stack 3
    .limit locals 4
    aload_0
    iload_1
    istore_2
    dup
    astore_1
    getfield i->k:B
    istore_3
    aload_1
    aload_1
    iload_2
    invokespecial i->a(I)B
    putfield i->k:B
    aload_1
    getfield i->k:B
    iconst_5
    if_icmpeq 0x25
    aload_1
    getfield i->k:B
    iconst_1
    if_icmpeq 0x1d
    aload_1
    getfield i->k:B
    iconst_3
    if_icmpeq 0x15
    aload_1
    getfield i->k:B
    bipush 0x7
    if_icmpeq 0xc
    aload_1
    getfield i->k:B
    bipush 0x9
    if_icmpne 0x1f
    aload_1
    getfield i->i:B
    iconst_1
    if_icmpne 0x17
    aload_1
    getfield i->l:B
    ifne 0xb
    aload_1
    iconst_3
    putfield i->l:B
    goto 0x8
    aload_1
    iconst_4
    putfield i->l:B
    aload_1
    getfield i->k:B
    iconst_m1
    if_icmpeq 0xe
    aload_1
    iconst_0
    putfield i->h:Z
    aload_1
    iconst_0
    putfield i->f:I
    return
    aload_1
    iload_3
    putfield i->k:B
    return
.end method

.method protected final b(I)V
    .limit stack 3
    .limit locals 3
    aload_0
    iload_1
    istore_2
    dup
    astore_1
    getfield i->k:B
    aload_1
    iload_2
    invokespecial i->a(I)B
    if_icmpne 0x29
    aload_1
    iconst_1
    putfield i->h:Z
    aload_1
    getfield i->f:I
    ifle 0x1d
    aload_1
    getfield i->k:B
    iconst_m1
    if_icmpeq 0x15
    sipush 0xeaa
    iconst_1
    aload_1
    getfield i->k:B
    ishl
    iand
    ifne 0x8
    aload_1
    iconst_m1
    putfield i->k:B
    return
.end method

.method private a(I)B
    .limit stack 2
    .limit locals 3
    iconst_m1
    istore_2
    iload_1
    getstatic i->i:I
    if_icmpeq 0xa
    iload_1
    getstatic i->j:I
    if_icmpne 0x9
    bipush 0xa
    istore_2
    goto 0xc4
    iload_1
    getstatic i->k:I
    if_icmpeq 0xa
    iload_1
    getstatic i->l:I
    if_icmpne 0x9
    bipush 0xb
    istore_2
    goto 0xb0
    iload_1
    tableswitch 0x68 0x30 0x39 [(58,), (63,), (85,), (68,), (96,), (53,), (101,), (73,), (90,), (79,)]
    iconst_5
    istore_2
    goto 0x31
    iconst_0
    istore_2
    goto 0x2c
    iconst_1
    istore_2
    goto 0x27
    iconst_3
    istore_2
    goto 0x22
    bipush 0x7
    istore_2
    goto 0x1c
    bipush 0x9
    istore_2
    goto 0x16
    iconst_2
    istore_2
    goto 0x11
    bipush 0x8
    istore_2
    goto 0xb
    iconst_4
    istore_2
    goto 0x6
    bipush 0x6
    istore_2
    iload_2
    iconst_m1
    if_icmpne 0x42
    aload_0
    iload_1
    invokevirtual javax/microedition/lcdui/Canvas->getGameAction(I)I
    dup
    istore_1
    bipush 0x8
    if_icmpne 0x8
    iconst_5
    istore_2
    goto 0x31
    iload_1
    iconst_1
    if_icmpne 0x8
    iconst_2
    istore_2
    goto 0x27
    iload_1
    bipush 0x6
    if_icmpne 0x9
    bipush 0x8
    istore_2
    goto 0x1b
    iload_1
    iconst_2
    if_icmpne 0x8
    iconst_4
    istore_2
    goto 0x11
    iload_1
    iconst_5
    if_icmpne 0x6
    bipush 0x6
    istore_2
    goto 0x6
    pop
    iconst_m1
    istore_2
    iload_2
    ireturn
.end method

.method public final commandAction(Ljavax/microedition/lcdui/Command;Ljavax/microedition/lcdui/Displayable;)V
    .limit stack 2
    .limit locals 3
    aload_2
    aload_0
    getfield i->a:Ljavax/microedition/lcdui/TextBox;
    if_acmpne 0x3c
    aload_1
    aload_0
    getfield i->c:Ljavax/microedition/lcdui/Command;
    if_acmpne 0x21
    aload_0
    aload_0
    getfield i->a:Ljavax/microedition/lcdui/TextBox;
    invokevirtual javax/microedition/lcdui/TextBox->getString()Ljava/lang/String;
    invokevirtual java/lang/String->trim()Ljava/lang/String;
    putfield i->c:Ljava/lang/String;
    aload_0
    getfield i->c:Ljava/lang/String;
    invokevirtual java/lang/String->length()I
    ifle 0x33
    aload_0
    iconst_1
    putfield i->r:I
    return
    aload_1
    aload_0
    getfield i->d:Ljavax/microedition/lcdui/Command;
    if_acmpne 0x25
    aload_0
    aconst_null
    putfield i->c:Ljava/lang/String;
    aload_0
    iconst_2
    putfield i->r:I
    return
    aload_1
    ifnonnull 0xb
    aload_0
    getstatic i->i:I
    invokevirtual m->keyPressed(I)V
    return
    aload_1
    ifnonnull 0xa
    aload_0
    getstatic i->k:I
    invokevirtual m->keyPressed(I)V
    return
.end method

.method private static l()V
    .limit stack 5
    .limit locals 2
    iconst_0
    istore_0
    iload_0
    getstatic k->a:[Lh;
    arraylength
    if_icmpge 0x26
    getstatic k->a:[Lh;
    iload_0
    new java/lang/StringBuffer
    dup
    invokespecial java/lang/StringBuffer-><init>()V
    ldc '/f'
    invokevirtual java/lang/StringBuffer->append(Ljava/lang/String;)Ljava/lang/StringBuffer;
    iload_0
    invokevirtual java/lang/StringBuffer->append(I)Ljava/lang/StringBuffer;
    invokevirtual java/lang/StringBuffer->toString()Ljava/lang/String;
    iconst_0
    iconst_2
    invokestatic h->a(Ljava/lang/String;II)Lh;
    aastore
    iinc 0x0 0x1
    goto -0x28
    getstatic h->a:Z
    ifeq 0x5a
    getstatic k->a:[Lh;
    iconst_0
    aaload
    invokevirtual h->a()I
    bipush 0x12
    if_icmple 0x8
    bipush 0x7
    goto 0x4
    iconst_5
    istore_0
    iconst_0
    istore_1
    iload_1
    getstatic k->a:[Lh;
    arraylength
    if_icmpge 0x13
    getstatic k->a:[Lh;
    iload_1
    aaload
    iload_0
    ineg
    putfield h->a:I
    iinc 0x1 0x1
    goto -0x15
    getstatic k->a:[Lh;
    iconst_0
    aaload
    ldc 12845055
    putfield h->b:I
    getstatic k->a:[Lh;
    iconst_1
    aaload
    ldc 16766251
    putfield h->b:I
    getstatic k->a:[Lh;
    iconst_2
    aaload
    ldc 51677
    putfield h->b:I
    getstatic k->a:[Lh;
    iconst_3
    aaload
    ldc 16766251
    putfield h->b:I
    return
    getstatic k->a:[Lh;
    iconst_0
    aaload
    invokevirtual h->a()I
    bipush 0x12
    if_icmple 0x7
    iconst_1
    goto 0x4
    iconst_3
    istore_0
    getstatic k->a:[Lh;
    iconst_0
    aaload
    iload_0
    ineg
    putfield h->a:I
    getstatic k->a:[Lh;
    iconst_1
    aaload
    iload_0
    ineg
    putfield h->a:I
    return
.end method

.method private m()V
    .limit stack 8
    .limit locals 12
    aload_0
    getfield i->j:[B
    iconst_0
    baload
    istore_1
    aload_0
    iconst_1
    iload_1
    multianewarray [[Ljavax/microedition/lcdui/Image; 0x2
    putfield i->a:[[Ljavax/microedition/lcdui/Image;
    sipush 0x4407
    newarray 0xa
    astore_3
    sipush 0x4407
    newarray 0x8
    astore 0x4
    ldc 33000
    newarray 0x8
    astore 0x5
    iconst_0
    istore 0x6
    iconst_0
    istore 0x7
    iload 0x7
    ifgt 0x1a0
    aconst_null
    astore 0x8
    new java/lang/StringBuffer
    dup
    invokespecial java/lang/StringBuffer-><init>()V
    ldc '/i'
    invokevirtual java/lang/StringBuffer->append(Ljava/lang/String;)Ljava/lang/StringBuffer;
    iload 0x7
    invokevirtual java/lang/StringBuffer->append(I)Ljava/lang/StringBuffer;
    invokevirtual java/lang/StringBuffer->toString()Ljava/lang/String;
    invokestatic a->a(Ljava/lang/String;)Ljava/io/InputStream;
    invokestatic a->a(Ljava/io/InputStream;)Ljava/io/DataInputStream;
    astore 0x8
    iconst_0
    istore 0x9
    iload 0x9
    iload_1
    iconst_1
    ishl
    if_icmpge 0x136
    iload 0x6
    iload_1
    if_icmpne 0x9
    aload_0
    bipush 0x14
    invokespecial i->c(I)V
    aload 0x8
    invokevirtual java/io/DataInputStream->readByte()B
    sipush 0xff
    iand
    dup
    istore_2
    sipush 0xff
    if_icmpeq 0x119
    aload 0x8
    invokevirtual java/io/DataInputStream->readByte()B
    sipush 0xff
    iand
    istore 0xa
    aload 0x8
    invokevirtual java/io/DataInputStream->readByte()B
    sipush 0xff
    iand
    istore 0xb
    iload_2
    bipush 0x10
    ishl
    iload 0xa
    bipush 0x8
    ishl
    ior
    iload 0xb
    ior
    dup
    istore_2
    ifle 0xc
    aload 0x8
    aload 0x5
    iconst_0
    iload_2
    invokevirtual java/io/DataInputStream->readFully([BII)V
    iload_2
    ifle 0xd1
    iload 0x6
    iconst_1
    iand
    ifne 0x18
    aload_0
    getfield i->a:[[Ljavax/microedition/lcdui/Image;
    iconst_0
    aaload
    iload 0x6
    iconst_1
    ishr
    aload 0x5
    iconst_0
    iload_2
    invokestatic javax/microedition/lcdui/Image->createImage([BII)Ljavax/microedition/lcdui/Image;
    aastore
    goto 0xb9
    aload 0x5
    iconst_0
    iload_2
    invokestatic javax/microedition/lcdui/Image->createImage([BII)Ljavax/microedition/lcdui/Image;
    astore_2
    aload_0
    getfield i->a:[[Ljavax/microedition/lcdui/Image;
    iconst_0
    aaload
    iload 0x6
    iconst_1
    ishr
    aaload
    invokevirtual javax/microedition/lcdui/Image->getWidth()I
    istore 0xa
    aload_0
    getfield i->a:[[Ljavax/microedition/lcdui/Image;
    iconst_0
    aaload
    iload 0x6
    iconst_1
    ishr
    aaload
    invokevirtual javax/microedition/lcdui/Image->getHeight()I
    istore 0xb
    aload_2
    aload_3
    iconst_0
    iload 0xa
    iconst_0
    iconst_0
    iload 0xa
    iload 0xb
    invokevirtual javax/microedition/lcdui/Image->getRGB([IIIIIII)V
    iconst_0
    istore_2
    iload_2
    iload 0xa
    iload 0xb
    imul
    if_icmpge 0x11
    aload 0x4
    iload_2
    aload_3
    iload_2
    iaload
    i2b
    bastore
    iinc 0x2 0x1
    goto -0x14
    aload_0
    getfield i->a:[[Ljavax/microedition/lcdui/Image;
    iconst_0
    aaload
    iload 0x6
    iconst_1
    ishr
    aaload
    aload_3
    iconst_0
    iload 0xa
    iconst_0
    iconst_0
    iload 0xa
    iload 0xb
    invokevirtual javax/microedition/lcdui/Image->getRGB([IIIIIII)V
    iconst_0
    istore_2
    iload_2
    iload 0xa
    iload 0xb
    imul
    if_icmpge 0x1a
    aload_3
    iload_2
    aload 0x4
    iload_2
    baload
    bipush 0x18
    ishl
    aload_3
    iload_2
    iaload
    ldc 16777215
    iand
    ior
    iastore
    iinc 0x2 0x1
    goto -0x1d
    aload_0
    getfield i->a:[[Ljavax/microedition/lcdui/Image;
    iconst_0
    aaload
    iload 0x6
    iconst_1
    ishr
    aconst_null
    aastore
    invokestatic java/lang/System->gc()V
    ldc2_w 20
    invokestatic a->a(J)V
    aload_0
    getfield i->a:[[Ljavax/microedition/lcdui/Image;
    iconst_0
    aaload
    iload 0x6
    iconst_1
    ishr
    aload_3
    iload 0xa
    iload 0xb
    iconst_1
    invokestatic javax/microedition/lcdui/Image->createRGBImage([IIIZ)Ljavax/microedition/lcdui/Image;
    aastore
    goto 0x4
    pop
    invokestatic java/lang/System->gc()V
    invokestatic java/lang/Thread->yield()V
    iinc 0x6 0x1
    iinc 0x9 0x1
    goto -0x138
    invokestatic a->e()V
    aload 0x8
    ifnull 0x32
    aload 0x8
    invokevirtual java/io/DataInputStream->close()V
    goto 0x2a
    pop
    goto 0x26
    pop
    aload 0x8
    ifnull 0x20
    aload 0x8
    invokevirtual java/io/DataInputStream->close()V
    goto 0x18
    pop
    goto 0x14
    astore_1
    aload 0x8
    ifnull 0xc
    aload 0x8
    invokevirtual java/io/DataInputStream->close()V
    goto 0x4
    pop
    aload_1
    athrow
    invokestatic java/lang/System->gc()V
    iinc 0x7 0x1
    goto -0x19f
    return
.end method

.method private n()V
    .limit stack 3
    .limit locals 5
    aconst_null
    astore_1
    ldc '/d0'  # resource: res/d0
    invokestatic a->a(Ljava/lang/String;)Ljava/io/InputStream;
    invokestatic a->a(Ljava/io/InputStream;)Ljava/io/DataInputStream;
    astore_1
    aload_0
    bipush 0x1a
    anewarray [B
    putfield i->i:[[B
    aload_0
    bipush 0x12
    anewarray [S
    putfield i->f:[[S
    iconst_0
    istore_2
    iload_2
    bipush 0x1a
    if_icmpge 0x33
    aload_1
    invokevirtual java/io/DataInputStream->readShort()S
    istore_3
    aload_0
    getfield i->i:[[B
    iload_2
    iload_3
    newarray 0x8
    aastore
    iconst_0
    istore 0x4
    iload 0x4
    iload_3
    if_icmpge 0x16
    aload_0
    getfield i->i:[[B
    iload_2
    aaload
    iload 0x4
    aload_1
    invokevirtual java/io/DataInputStream->readByte()B
    bastore
    iinc 0x4 0x1
    goto -0x16
    iinc 0x2 0x1
    goto -0x33
    iconst_0
    istore_2
    iload_2
    bipush 0x12
    if_icmpge 0x33
    aload_1
    invokevirtual java/io/DataInputStream->readShort()S
    istore_3
    aload_0
    getfield i->f:[[S
    iload_2
    iload_3
    newarray 0x9
    aastore
    iconst_0
    istore 0x4
    iload 0x4
    iload_3
    if_icmpge 0x16
    aload_0
    getfield i->f:[[S
    iload_2
    aaload
    iload 0x4
    aload_1
    invokevirtual java/io/DataInputStream->readShort()S
    sastore
    iinc 0x4 0x1
    goto -0x16
    iinc 0x2 0x1
    goto -0x33
    invokestatic java/lang/Thread->yield()V
    aload_1
    ifnull 0x29
    aload_1
    invokevirtual java/io/DataInputStream->close()V
    goto 0x22
    pop
    return
    pop
    aload_1
    ifnull 0x1b
    aload_1
    invokevirtual java/io/DataInputStream->close()V
    goto 0x14
    pop
    return
    astore_2
    aload_1
    ifnull 0xb
    aload_1
    invokevirtual java/io/DataInputStream->close()V
    goto 0x4
    pop
    aload_2
    athrow
    return
.end method

.method private o()V
    .limit stack 3
    .limit locals 6
    aconst_null
    astore_1
    ldc '/ml'  # resource: res/ml
    invokestatic a->a(Ljava/lang/String;)Ljava/io/InputStream;
    invokestatic a->a(Ljava/io/InputStream;)Ljava/io/DataInputStream;
    dup
    astore_1
    invokevirtual java/io/DataInputStream->readByte()B
    istore_2
    aload_0
    iload_2
    anewarray [S
    putfield i->d:[[S
    aload_0
    iload_2
    bipush 0x1e
    multianewarray [[S 0x2
    putfield i->e:[[S
    iconst_0
    istore_3
    iload_3
    iload_2
    if_icmpge 0x53
    aload_1
    invokevirtual java/io/DataInputStream->readShort()S
    istore 0x4
    aload_0
    getfield i->d:[[S
    iload_3
    iload 0x4
    newarray 0x9
    aastore
    iconst_0
    istore 0x5
    iload 0x5
    iload 0x4
    if_icmpge 0x16
    aload_0
    getfield i->d:[[S
    iload_3
    aaload
    iload 0x5
    aload_1
    invokevirtual java/io/DataInputStream->readShort()S
    sastore
    iinc 0x5 0x1
    goto -0x17
    iconst_0
    istore 0x5
    iload 0x5
    bipush 0x1e
    if_icmpge 0x16
    aload_0
    getfield i->e:[[S
    iload_3
    aaload
    iload 0x5
    aload_1
    invokevirtual java/io/DataInputStream->readShort()S
    sastore
    iinc 0x5 0x1
    goto -0x17
    iinc 0x3 0x1
    goto -0x52
    aload_1
    ifnull 0x2d
    aload_1
    invokevirtual java/io/DataInputStream->close()V
    goto 0x26
    pop
    goto 0x22
    pop
    aload_1
    ifnull 0x1d
    aload_1
    invokevirtual java/io/DataInputStream->close()V
    goto 0x16
    pop
    goto 0x12
    astore_2
    aload_1
    ifnull 0xb
    aload_1
    invokevirtual java/io/DataInputStream->close()V
    goto 0x4
    pop
    aload_2
    athrow
    invokestatic a->e()V
    return
.end method

.method public final hideNotify()V
    .limit stack 1
    .limit locals 1
    aload_0
    invokevirtual i->b()V
    return
.end method

.method public final showNotify()V
    .limit stack 1
    .limit locals 1
    aload_0
    invokevirtual i->c()V
    return
.end method

.method public final b()V
    .limit stack 2
    .limit locals 1
    getstatic i->k:Z
    ifne 0x9
    getstatic i->l:Z
    ifeq 0x4
    return
    iconst_1
    putstatic i->l:Z
    aload_0
    invokevirtual i->g()V
    aload_0
    iconst_m1
    putfield i->k:B
    iconst_1
    putstatic i->k:Z
    return
.end method

.method public final c()V
    .limit stack 2
    .limit locals 1
    aload_0
    iconst_m1
    putfield i->k:B
    iconst_0
    putstatic i->l:Z
    return
.end method

.method final d()V
    .limit stack 1
    .limit locals 1
    iconst_1
    putstatic c->a:Z
    aload_0
    invokevirtual i->f()V
    return
.end method

.method final e()V
    .limit stack 1
    .limit locals 1
    aload_0
    getfield i->a:Lc;
    ifnull 0xa
    aload_0
    getfield i->a:Lc;
    invokevirtual c->a()V
    return
.end method

.method final f()V
    .limit stack 6
    .limit locals 2
    aload_0
    getfield i->a:Lc;
    ifnonnull 0x40
    aload_0
    new c
    dup
    aload_0
    getfield i->a:[Ljava/lang/String;
    ldc 'SMTYPE'
    iconst_0
    invokestatic a->a(Ljava/lang/String;I)I
    invokespecial c-><init>([Ljava/lang/String;I)V
    putfield i->a:Lc;
    invokestatic java/lang/Thread->yield()V
    aload_0
    getfield i->a:Lc;
    ldc 'SMPRIOR'
    invokestatic a->a(Ljava/lang/String;)Ljava/lang/String;
    invokevirtual c->a(Ljava/lang/String;)V
    ldc2_w 20
    invokestatic a->a(J)V
    ldc 'SMLEVEL'
    iconst_m1
    invokestatic a->a(Ljava/lang/String;I)I
    dup
    istore_1
    iflt 0xb
    aload_0
    getfield i->a:Lc;
    iload_1
    invokevirtual c->a(I)V
    getstatic c->a:Z
    ifeq 0x17
    aload_0
    getfield i->a:Lc;
    invokevirtual c->a()Z
    ifne 0xd
    aload_0
    getfield i->a:Lc;
    iconst_0
    iconst_m1
    invokevirtual c->a(II)I
    pop
    return
    pop
    return
.end method

.method final g()V
    .limit stack 2
    .limit locals 1
    aload_0
    getfield i->a:Lc;
    ifnull 0x14
    aload_0
    getfield i->a:Lc;
    invokevirtual c->b()V
    aload_0
    aconst_null
    putfield i->a:Lc;
    invokestatic a->e()V
    return
    pop
    return
.end method

.method private p()V
    .limit stack 2
    .limit locals 1
    getstatic i->k:Z
    ifeq 0x36
    iconst_0
    putstatic i->k:Z
    aload_0
    getfield i->a:Lf;
    invokevirtual f->b()V
    aload_0
    invokevirtual i->g()V
    getstatic i->l:Z
    ifeq 0xc
    ldc2_w 30
    invokestatic a->a(J)V
    goto -0xc
    ldc2_w 300
    invokestatic a->a(J)V
    getstatic i->k:Z
    ifne 0x7
    aload_0
    invokevirtual i->f()V
    aload_0
    iconst_m1
    putfield i->k:B
    return
.end method

.method protected final pointerPressed(II)V
    .limit stack 0
    .limit locals 3
    return
.end method

.method protected final pointerReleased(II)V
    .limit stack 0
    .limit locals 3
    return
.end method

.method protected final pointerDragged(II)V
    .limit stack 0
    .limit locals 3
    return
.end method

.method protected final sizeChanged(II)V
    .limit stack 1
    .limit locals 3
    iload_1
    putstatic i->p:I
    iload_2
    putstatic i->q:I
    invokestatic i->q()V
    return
.end method

.method private static final q()V
    .limit stack 2
    .limit locals 0
    getstatic i->n:I
    iconst_1
    if_icmpne 0xc
    getstatic i->p:I
    getstatic i->q:I
    if_icmpgt 0x13
    getstatic i->n:I
    iconst_2
    if_icmpne 0x11
    getstatic i->q:I
    getstatic i->p:I
    if_icmple 0x8
    iconst_1
    putstatic i->j:Z
    return
    iconst_0
    putstatic i->j:Z
    return
.end method

.method public final a()Ljava/lang/String;
    .limit stack 7
    .limit locals 2
    aload_0
    iconst_0
    putfield i->r:I
    aload_0
    new javax/microedition/lcdui/TextBox
    dup
    getstatic k->a:[[Ljava/lang/String;
    iconst_3
    aaload
    iconst_4
    aaload
    ldc ''
    bipush 0xc
    iconst_3
    invokespecial javax/microedition/lcdui/TextBox-><init>(Ljava/lang/String;Ljava/lang/String;II)V
    putfield i->a:Ljavax/microedition/lcdui/TextBox;
    aload_0
    new javax/microedition/lcdui/Command
    dup
    getstatic k->a:[[Ljava/lang/String;
    iconst_3
    aaload
    iconst_2
    aaload
    iconst_4
    iconst_1
    invokespecial javax/microedition/lcdui/Command-><init>(Ljava/lang/String;II)V
    putfield i->c:Ljavax/microedition/lcdui/Command;
    aload_0
    new javax/microedition/lcdui/Command
    dup
    getstatic k->a:[[Ljava/lang/String;
    iconst_3
    aaload
    iconst_3
    aaload
    iconst_3
    iconst_2
    invokespecial javax/microedition/lcdui/Command-><init>(Ljava/lang/String;II)V
    putfield i->d:Ljavax/microedition/lcdui/Command;
    aload_0
    getfield i->a:Ljavax/microedition/lcdui/TextBox;
    aload_0
    getfield i->c:Ljavax/microedition/lcdui/Command;
    invokevirtual javax/microedition/lcdui/Displayable->addCommand(Ljavax/microedition/lcdui/Command;)V
    aload_0
    getfield i->a:Ljavax/microedition/lcdui/TextBox;
    aload_0
    getfield i->d:Ljavax/microedition/lcdui/Command;
    invokevirtual javax/microedition/lcdui/Displayable->addCommand(Ljavax/microedition/lcdui/Command;)V
    aload_0
    getfield i->a:Ljavax/microedition/lcdui/TextBox;
    aload_0
    invokevirtual javax/microedition/lcdui/Displayable->setCommandListener(Ljavax/microedition/lcdui/CommandListener;)V
    aload_0
    getfield i->i:B
    istore_1
    aload_0
    bipush 0xfe
    putfield i->i:B
    aload_0
    getfield i->a:Laow2;
    getfield aow2->a:Ljavax/microedition/lcdui/Display;
    aload_0
    getfield i->a:Ljavax/microedition/lcdui/TextBox;
    invokevirtual javax/microedition/lcdui/Display->setCurrent(Ljavax/microedition/lcdui/Displayable;)V
    aload_0
    getfield i->r:I
    ifne 0xc
    ldc2_w 30
    invokestatic a->a(J)V
    goto -0xd
    aload_0
    getfield i->a:Laow2;
    getfield aow2->a:Ljavax/microedition/lcdui/Display;
    aload_0
    invokevirtual javax/microedition/lcdui/Display->setCurrent(Ljavax/microedition/lcdui/Displayable;)V
    aload_0
    aconst_null
    putfield i->a:Ljavax/microedition/lcdui/TextBox;
    aload_0
    aload_0
    aconst_null
    dup_x1
    putfield i->d:Ljavax/microedition/lcdui/Command;
    putfield i->c:Ljavax/microedition/lcdui/Command;
    invokestatic a->e()V
    aload_0
    iload_1
    putfield i->i:B
    aload_0
    getfield i->c:Ljava/lang/String;
    areturn
.end method

.method private static a(Ljavax/microedition/midlet/MIDlet;Ljava/util/Hashtable;Ljava/lang/String;I)I
    .limit stack 5
    .limit locals 8
    invokestatic f->a()I
    istore 0x4
    new java/lang/String
    dup
    getstatic f->j:[B
    invokespecial java/lang/String-><init>([B)V
    invokestatic java/lang/System->getProperty(Ljava/lang/String;)Ljava/lang/String;
    astore 0x5
    aload_0
    new java/lang/String
    dup
    getstatic f->k:[B
    invokespecial java/lang/String-><init>([B)V
    invokevirtual javax/microedition/midlet/MIDlet->getAppProperty(Ljava/lang/String;)Ljava/lang/String;
    astore 0x6
    aload 0x5
    ifnonnull 0x8
    aload 0x6
    goto 0x5
    aload 0x5
    astore 0x5
    getstatic a->a:Ljava/util/Hashtable;
    aload_2
    invokevirtual java/util/Hashtable->get(Ljava/lang/Object;)Ljava/lang/Object;
    checkcast java/lang/String
    dup
    astore_2
    ifnonnull 0x2e
    iload 0x4
    ineg
    istore 0x4
    aload_1
    new java/lang/String
    dup
    getstatic f->j:[B
    invokespecial java/lang/String-><init>([B)V
    new java/lang/StringBuffer
    dup
    invokespecial java/lang/StringBuffer-><init>()V
    ldc ''
    invokevirtual java/lang/StringBuffer->append(Ljava/lang/String;)Ljava/lang/StringBuffer;
    iload 0x4
    invokevirtual java/lang/StringBuffer->append(I)Ljava/lang/StringBuffer;
    invokevirtual java/lang/StringBuffer->toString()Ljava/lang/String;
    invokevirtual java/util/Hashtable->put(Ljava/lang/Object;Ljava/lang/Object;)Ljava/lang/Object;
    pop
    iload 0x4
    ireturn
    aload_2
    ifnull 0x6
    iload 0x4
    ireturn
    new java/lang/String
    dup
    aload_2
    iload_3
    iconst_0
    invokestatic e->a(Ljava/lang/String;IZ)[B
    invokespecial java/lang/String-><init>([B)V
    bipush 0x40
    invokestatic a->a(Ljava/lang/String;C)[Ljava/lang/String;
    astore_2
    iconst_0
    istore_3
    iconst_0
    istore 0x7
    iload 0x7
    aload_2
    arraylength
    iconst_1
    isub
    if_icmpge 0x1a
    aload 0x5
    aload_2
    iload 0x7
    aaload
    invokevirtual java/lang/String->startsWith(Ljava/lang/String;)Z
    ifeq 0x8
    iconst_1
    istore_3
    goto 0x9
    iinc 0x7 0x1
    goto -0x1d
    iload_3
    ifne 0x24
    iconst_0
    istore 0x7
    iload 0x7
    aload_2
    arraylength
    if_icmpge 0x1a
    aload_2
    iload 0x7
    aaload
    aload 0x5
    invokevirtual java/lang/String->equals(Ljava/lang/Object;)Z
    ifeq 0x8
    iconst_1
    istore_3
    goto 0x9
    iinc 0x7 0x1
    goto -0x1b
    iload_3
    ifeq 0x33
    aload_1
    new java/lang/String
    dup
    getstatic f->j:[B
    invokespecial java/lang/String-><init>([B)V
    new java/lang/StringBuffer
    dup
    invokespecial java/lang/StringBuffer-><init>()V
    ldc ''
    invokevirtual java/lang/StringBuffer->append(Ljava/lang/String;)Ljava/lang/StringBuffer;
    iload_3
    ifeq 0x9
    iload 0x4
    ineg
    goto 0x5
    iload 0x4
    dup
    istore 0x4
    invokevirtual java/lang/StringBuffer->append(I)Ljava/lang/StringBuffer;
    invokevirtual java/lang/StringBuffer->toString()Ljava/lang/String;
    invokevirtual java/util/Hashtable->put(Ljava/lang/Object;Ljava/lang/Object;)Ljava/lang/Object;
    pop
    new java/lang/String
    dup
    getstatic f->i:[B
    invokespecial java/lang/String-><init>([B)V
    astore 0x7
    aload 0x5
    aload_0
    aload 0x7
    invokevirtual javax/microedition/midlet/MIDlet->getAppProperty(Ljava/lang/String;)Ljava/lang/String;
    invokevirtual java/lang/String->equals(Ljava/lang/Object;)Z
    ifeq 0xb
    invokestatic f->a()I
    istore 0x4
    goto 0x22
    aload_1
    aload 0x6
    new java/lang/StringBuffer
    dup
    invokespecial java/lang/StringBuffer-><init>()V
    ldc ''
    invokevirtual java/lang/StringBuffer->append(Ljava/lang/String;)Ljava/lang/StringBuffer;
    iload 0x4
    invokevirtual java/lang/StringBuffer->append(I)Ljava/lang/StringBuffer;
    invokevirtual java/lang/StringBuffer->toString()Ljava/lang/String;
    invokevirtual java/util/Hashtable->put(Ljava/lang/Object;Ljava/lang/Object;)Ljava/lang/Object;
    pop
    goto 0x4
    pop
    iload 0x4
    ireturn
.end method

.method public static a(Ljava/lang/Object;)Z
    .limit stack 10
    .limit locals 1
    getstatic i->b:Ljava/lang/Object;
    ifnonnull 0x4b
    aload_0
    checkcast java/util/Hashtable
    invokevirtual java/util/Hashtable->elements()Ljava/util/Enumeration;
    invokeinterface java/util/Enumeration->nextElement()Ljava/lang/Object;
    putstatic i->b:Ljava/lang/Object;
    goto 0x2a
    astore_0
    new java/lang/RuntimeException
    dup
    new java/lang/StringBuffer
    dup
    invokespecial java/lang/StringBuffer-><init>()V
    ldc ''
    invokevirtual java/lang/StringBuffer->append(Ljava/lang/String;)Ljava/lang/StringBuffer;
    aload_0
    invokevirtual java/lang/StringBuffer->append(Ljava/lang/Object;)Ljava/lang/StringBuffer;
    ldc ' '
    invokevirtual java/lang/StringBuffer->append(Ljava/lang/String;)Ljava/lang/StringBuffer;
    invokestatic f->a()Ljava/lang/String;
    invokevirtual java/lang/StringBuffer->append(Ljava/lang/String;)Ljava/lang/StringBuffer;
    invokevirtual java/lang/StringBuffer->toString()Ljava/lang/String;
    invokespecial java/lang/RuntimeException-><init>(Ljava/lang/String;)V
    athrow
    getstatic a->a:Ljava/util/Hashtable;
    ifnonnull 0xc
    ldc2_w 40
    invokestatic a->a(J)V
    goto -0xc
    aload_0
    checkcast java/util/Hashtable
    getstatic i->b:Ljava/lang/Object;
    new java/lang/Long
    dup
    getstatic i->a:[J
    bipush 0xa
    dup2
    laload
    lconst_1
    ladd
    dup2_x2
    lastore
    invokespecial java/lang/Long-><init>(J)V
    invokevirtual java/util/Hashtable->put(Ljava/lang/Object;Ljava/lang/Object;)Ljava/lang/Object;
    pop
    aload_0
    ifnonnull 0xb
    getstatic i->b:Ljava/lang/Object;
    ifnonnull 0x5
    iconst_1
    ireturn
    iconst_0
    ireturn
.end method

.method public final a(IIZ)V
    .limit stack 1
    .limit locals 4
    iload_1
    ifeq 0xa
    iload_2
    ifle 0x6
    invokestatic l->f()V
    return
.end method

.method static <clinit>()V
    .limit stack 7
    .limit locals 0
    iconst_0
    putstatic i->i:I
    iconst_0
    putstatic i->j:I
    iconst_0
    putstatic i->k:I
    iconst_0
    putstatic i->l:I
    iconst_0
    putstatic i->n:I
    iconst_0
    putstatic i->j:Z
    aconst_null
    putstatic i->a:Ljavax/microedition/lcdui/Image;
    iconst_0
    putstatic i->p:I
    iconst_0
    putstatic i->q:I
    aconst_null
    putstatic i->a:Ljavax/microedition/lcdui/Command;
    aconst_null
    putstatic i->b:Ljavax/microedition/lcdui/Command;
    aconst_null
    putstatic i->a:Ljava/lang/String;
    iconst_0
    putstatic i->k:Z
    iconst_0
    putstatic i->l:Z
    iconst_0
    putstatic i->g:I
    iconst_2
    putstatic i->h:I
    bipush 0xc
    newarray 0xb
    dup
    iconst_0
    ldc2_w 95
    lastore
    dup
    iconst_1
    ldc2_w 34
    lastore
    dup
    iconst_2
    ldc2_w -55
    lastore
    dup
    iconst_3
    ldc2_w 39
    lastore
    dup
    iconst_4
    ldc2_w 66
    lastore
    dup
    iconst_5
    ldc2_w 454
    lastore
    dup
    bipush 0x6
    ldc2_w 95
    lastore
    dup
    bipush 0x7
    ldc2_w -54
    lastore
    dup
    bipush 0x8
    ldc2_w 565
    lastore
    dup
    bipush 0x9
    ldc2_w 454
    lastore
    dup
    bipush 0xa
    lconst_0
    lastore
    dup
    bipush 0xb
    ldc2_w -546767
    lastore
    putstatic i->a:[J
    aconst_null
    putstatic i->b:Ljava/lang/Object;
    iconst_3
    newarray 0x8
    dup
    iconst_0
    bipush 0x31
    bastore
    dup
    iconst_1
    bipush 0x38
    bastore
    dup
    iconst_2
    bipush 0x37
    bastore
    putstatic i->a:Ljava/lang/Object;
    iconst_4
    anewarray [B
    dup
    iconst_0
    iconst_2
    newarray 0x8
    dup
    iconst_0
    iconst_0
    bastore
    dup
    iconst_1
    iconst_0
    bastore
    aastore
    dup
    iconst_1
    sipush 0xbd
    newarray 0x8
    dup
    iconst_0
    iconst_0
    bastore
    dup
    iconst_1
    bipush 0xbb
    bastore
    dup
    iconst_2
    bipush 0x54
    bastore
    dup
    iconst_3
    bipush 0x48
    bastore
    dup
    iconst_4
    bipush 0x41
    bastore
    dup
    iconst_5
    bipush 0x4e
    bastore
    dup
    bipush 0x6
    bipush 0x4b
    bastore
    dup
    bipush 0x7
    bipush 0x20
    bastore
    dup
    bipush 0x8
    bipush 0x59
    bastore
    dup
    bipush 0x9
    bipush 0x4f
    bastore
    dup
    bipush 0xa
    bipush 0x55
    bastore
    dup
    bipush 0xb
    bipush 0x20
    bastore
    dup
    bipush 0xc
    bipush 0x46
    bastore
    dup
    bipush 0xd
    bipush 0x4f
    bastore
    dup
    bipush 0xe
    bipush 0x52
    bastore
    dup
    bipush 0xf
    bipush 0x20
    bastore
    dup
    bipush 0x10
    bipush 0x50
    bastore
    dup
    bipush 0x11
    bipush 0x55
    bastore
    dup
    bipush 0x12
    bipush 0x52
    bastore
    dup
    bipush 0x13
    bipush 0x43
    bastore
    dup
    bipush 0x14
    bipush 0x48
    bastore
    dup
    bipush 0x15
    bipush 0x41
    bastore
    dup
    bipush 0x16
    bipush 0x53
    bastore
    dup
    bipush 0x17
    bipush 0x49
    bastore
    dup
    bipush 0x18
    bipush 0x4e
    bastore
    dup
    bipush 0x19
    bipush 0x47
    bastore
    dup
    bipush 0x1a
    bipush 0x20
    bastore
    dup
    bipush 0x1b
    bipush 0x54
    bastore
    dup
    bipush 0x1c
    bipush 0x48
    bastore
    dup
    bipush 0x1d
    bipush 0x49
    bastore
    dup
    bipush 0x1e
    bipush 0x53
    bastore
    dup
    bipush 0x1f
    bipush 0x20
    bastore
    dup
    bipush 0x20
    bipush 0x47
    bastore
    dup
    bipush 0x21
    bipush 0x41
    bastore
    dup
    bipush 0x22
    bipush 0x4d
    bastore
    dup
    bipush 0x23
    bipush 0x45
    bastore
    dup
    bipush 0x24
    bipush 0x2c
    bastore
    dup
    bipush 0x25
    bipush 0x20
    bastore
    dup
    bipush 0x26
    bipush 0x59
    bastore
    dup
    bipush 0x27
    bipush 0x4f
    bastore
    dup
    bipush 0x28
    bipush 0x55
    bastore
    dup
    bipush 0x29
    bipush 0x20
    bastore
    dup
    bipush 0x2a
    bipush 0x57
    bastore
    dup
    bipush 0x2b
    bipush 0x49
    bastore
    dup
    bipush 0x2c
    bipush 0x4c
    bastore
    dup
    bipush 0x2d
    bipush 0x4c
    bastore
    dup
    bipush 0x2e
    bipush 0x20
    bastore
    dup
    bipush 0x2f
    bipush 0x46
    bastore
    dup
    bipush 0x30
    bipush 0x49
    bastore
    dup
    bipush 0x31
    bipush 0x4e
    bastore
    dup
    bipush 0x32
    bipush 0x44
    bastore
    dup
    bipush 0x33
    bipush 0x20
    bastore
    dup
    bipush 0x34
    bipush 0x41
    bastore
    dup
    bipush 0x35
    bipush 0x20
    bastore
    dup
    bipush 0x36
    bipush 0x44
    bastore
    dup
    bipush 0x37
    bipush 0x4f
    bastore
    dup
    bipush 0x38
    bipush 0x57
    bastore
    dup
    bipush 0x39
    bipush 0x4e
    bastore
    dup
    bipush 0x3a
    bipush 0x4c
    bastore
    dup
    bipush 0x3b
    bipush 0x4f
    bastore
    dup
    bipush 0x3c
    bipush 0x41
    bastore
    dup
    bipush 0x3d
    bipush 0x44
    bastore
    dup
    bipush 0x3e
    bipush 0x20
    bastore
    dup
    bipush 0x3f
    bipush 0x4c
    bastore
    dup
    bipush 0x40
    bipush 0x49
    bastore
    dup
    bipush 0x41
    bipush 0x4e
    bastore
    dup
    bipush 0x42
    bipush 0x4b
    bastore
    dup
    bipush 0x43
    bipush 0x20
    bastore
    dup
    bipush 0x44
    bipush 0x49
    bastore
    dup
    bipush 0x45
    bipush 0x4e
    bastore
    dup
    bipush 0x46
    bipush 0x20
    bastore
    dup
    bipush 0x47
    bipush 0x54
    bastore
    dup
    bipush 0x48
    bipush 0x48
    bastore
    dup
    bipush 0x49
    bipush 0x45
    bastore
    dup
    bipush 0x4a
    bipush 0x20
    bastore
    dup
    bipush 0x4b
    bipush 0x53
    bastore
    dup
    bipush 0x4c
    bipush 0x4d
    bastore
    dup
    bipush 0x4d
    bipush 0x53
    bastore
    dup
    bipush 0x4e
    bipush 0x20
    bastore
    dup
    bipush 0x4f
    bipush 0x57
    bastore
    dup
    bipush 0x50
    bipush 0x45
    bastore
    dup
    bipush 0x51
    bipush 0x27
    bastore
    dup
    bipush 0x52
    bipush 0x52
    bastore
    dup
    bipush 0x53
    bipush 0x45
    bastore
    dup
    bipush 0x54
    bipush 0x20
    bastore
    dup
    bipush 0x55
    bipush 0x53
    bastore
    dup
    bipush 0x56
    bipush 0x45
    bastore
    dup
    bipush 0x57
    bipush 0x4e
    bastore
    dup
    bipush 0x58
    bipush 0x44
    bastore
    dup
    bipush 0x59
    bipush 0x49
    bastore
    dup
    bipush 0x5a
    bipush 0x4e
    bastore
    dup
    bipush 0x5b
    bipush 0x47
    bastore
    dup
    bipush 0x5c
    bipush 0x20
    bastore
    dup
    bipush 0x5d
    bipush 0x59
    bastore
    dup
    bipush 0x5e
    bipush 0x4f
    bastore
    dup
    bipush 0x5f
    bipush 0x55
    bastore
    dup
    bipush 0x60
    bipush 0x20
    bastore
    dup
    bipush 0x61
    bipush 0x4e
    bastore
    dup
    bipush 0x62
    bipush 0x4f
    bastore
    dup
    bipush 0x63
    bipush 0x57
    bastore
    dup
    bipush 0x64
    bipush 0x2e
    bastore
    dup
    bipush 0x65
    bipush 0x20
    bastore
    dup
    bipush 0x66
    bipush 0x50
    bastore
    dup
    bipush 0x67
    bipush 0x4c
    bastore
    dup
    bipush 0x68
    bipush 0x45
    bastore
    dup
    bipush 0x69
    bipush 0x41
    bastore
    dup
    bipush 0x6a
    bipush 0x53
    bastore
    dup
    bipush 0x6b
    bipush 0x45
    bastore
    dup
    bipush 0x6c
    bipush 0x2c
    bastore
    dup
    bipush 0x6d
    bipush 0x20
    bastore
    dup
    bipush 0x6e
    bipush 0x55
    bastore
    dup
    bipush 0x6f
    bipush 0x4e
    bastore
    dup
    bipush 0x70
    bipush 0x49
    bastore
    dup
    bipush 0x71
    bipush 0x4e
    bastore
    dup
    bipush 0x72
    bipush 0x53
    bastore
    dup
    bipush 0x73
    bipush 0x54
    bastore
    dup
    bipush 0x74
    bipush 0x41
    bastore
    dup
    bipush 0x75
    bipush 0x4c
    bastore
    dup
    bipush 0x76
    bipush 0x4c
    bastore
    dup
    bipush 0x77
    bipush 0x20
    bastore
    dup
    bipush 0x78
    bipush 0x54
    bastore
    dup
    bipush 0x79
    bipush 0x48
    bastore
    dup
    bipush 0x7a
    bipush 0x49
    bastore
    dup
    bipush 0x7b
    bipush 0x53
    bastore
    dup
    bipush 0x7c
    bipush 0x20
    bastore
    dup
    bipush 0x7d
    bipush 0x56
    bastore
    dup
    bipush 0x7e
    bipush 0x45
    bastore
    dup
    bipush 0x7f
    bipush 0x52
    bastore
    dup
    sipush 0x80
    bipush 0x53
    bastore
    dup
    sipush 0x81
    bipush 0x49
    bastore
    dup
    sipush 0x82
    bipush 0x4f
    bastore
    dup
    sipush 0x83
    bipush 0x4e
    bastore
    dup
    sipush 0x84
    bipush 0x20
    bastore
    dup
    sipush 0x85
    bipush 0x4f
    bastore
    dup
    sipush 0x86
    bipush 0x46
    bastore
    dup
    sipush 0x87
    bipush 0x20
    bastore
    dup
    sipush 0x88
    bipush 0x54
    bastore
    dup
    sipush 0x89
    bipush 0x48
    bastore
    dup
    sipush 0x8a
    bipush 0x45
    bastore
    dup
    sipush 0x8b
    bipush 0x20
    bastore
    dup
    sipush 0x8c
    bipush 0x47
    bastore
    dup
    sipush 0x8d
    bipush 0x41
    bastore
    dup
    sipush 0x8e
    bipush 0x4d
    bastore
    dup
    sipush 0x8f
    bipush 0x45
    bastore
    dup
    sipush 0x90
    bipush 0x20
    bastore
    dup
    sipush 0x91
    bipush 0x42
    bastore
    dup
    sipush 0x92
    bipush 0x45
    bastore
    dup
    sipush 0x93
    bipush 0x46
    bastore
    dup
    sipush 0x94
    bipush 0x4f
    bastore
    dup
    sipush 0x95
    bipush 0x52
    bastore
    dup
    sipush 0x96
    bipush 0x45
    bastore
    dup
    sipush 0x97
    bipush 0x20
    bastore
    dup
    sipush 0x98
    bipush 0x44
    bastore
    dup
    sipush 0x99
    bipush 0x4f
    bastore
    dup
    sipush 0x9a
    bipush 0x57
    bastore
    dup
    sipush 0x9b
    bipush 0x4e
    bastore
    dup
    sipush 0x9c
    bipush 0x4c
    bastore
    dup
    sipush 0x9d
    bipush 0x4f
    bastore
    dup
    sipush 0x9e
    bipush 0x41
    bastore
    dup
    sipush 0x9f
    bipush 0x44
    bastore
    dup
    sipush 0xa0
    bipush 0x49
    bastore
    dup
    sipush 0xa1
    bipush 0x4e
    bastore
    dup
    sipush 0xa2
    bipush 0x47
    bastore
    dup
    sipush 0xa3
    bipush 0x20
    bastore
    dup
    sipush 0xa4
    bipush 0x41
    bastore
    dup
    sipush 0xa5
    bipush 0x4e
    bastore
    dup
    sipush 0xa6
    bipush 0x44
    bastore
    dup
    sipush 0xa7
    bipush 0x20
    bastore
    dup
    sipush 0xa8
    bipush 0x49
    bastore
    dup
    sipush 0xa9
    bipush 0x4e
    bastore
    dup
    sipush 0xaa
    bipush 0x53
    bastore
    dup
    sipush 0xab
    bipush 0x54
    bastore
    dup
    sipush 0xac
    bipush 0x41
    bastore
    dup
    sipush 0xad
    bipush 0x4c
    bastore
    dup
    sipush 0xae
    bipush 0x4c
    bastore
    dup
    sipush 0xaf
    bipush 0x49
    bastore
    dup
    sipush 0xb0
    bipush 0x4e
    bastore
    dup
    sipush 0xb1
    bipush 0x47
    bastore
    dup
    sipush 0xb2
    bipush 0x20
    bastore
    dup
    sipush 0xb3
    bipush 0x41
    bastore
    dup
    sipush 0xb4
    bipush 0x20
    bastore
    dup
    sipush 0xb5
    bipush 0x4e
    bastore
    dup
    sipush 0xb6
    bipush 0x45
    bastore
    dup
    sipush 0xb7
    bipush 0x57
    bastore
    dup
    sipush 0xb8
    bipush 0x20
    bastore
    dup
    sipush 0xb9
    bipush 0x4f
    bastore
    dup
    sipush 0xba
    bipush 0x4e
    bastore
    dup
    sipush 0xbb
    bipush 0x45
    bastore
    dup
    sipush 0xbc
    bipush 0x2e
    bastore
    aastore
    dup
    iconst_2
    sipush 0x81
    newarray 0x8
    dup
    iconst_0
    iconst_0
    bastore
    dup
    iconst_1
    bipush 0x7f
    bastore
    dup
    iconst_2
    bipush 0x49
    bastore
    dup
    iconst_3
    bipush 0x27
    bastore
    dup
    iconst_4
    bipush 0x4d
    bastore
    dup
    iconst_5
    bipush 0x20
    bastore
    dup
    bipush 0x6
    bipush 0x41
    bastore
    dup
    bipush 0x7
    bipush 0x20
    bastore
    dup
    bipush 0x8
    bipush 0x50
    bastore
    dup
    bipush 0x9
    bipush 0x49
    bastore
    dup
    bipush 0xa
    bipush 0x52
    bastore
    dup
    bipush 0xb
    bipush 0x41
    bastore
    dup
    bipush 0xc
    bipush 0x54
    bastore
    dup
    bipush 0xd
    bipush 0x45
    bastore
    dup
    bipush 0xe
    bipush 0x44
    bastore
    dup
    bipush 0xf
    bipush 0x20
    bastore
    dup
    bipush 0x10
    bipush 0x43
    bastore
    dup
    bipush 0x11
    bipush 0x4f
    bastore
    dup
    bipush 0x12
    bipush 0x50
    bastore
    dup
    bipush 0x13
    bipush 0x59
    bastore
    dup
    bipush 0x14
    bipush 0x2c
    bastore
    dup
    bipush 0x15
    bipush 0x20
    bastore
    dup
    bipush 0x16
    bipush 0x49
    bastore
    dup
    bipush 0x17
    bipush 0x20
    bastore
    dup
    bipush 0x18
    bipush 0x57
    bastore
    dup
    bipush 0x19
    bipush 0x4f
    bastore
    dup
    bipush 0x1a
    bipush 0x4e
    bastore
    dup
    bipush 0x1b
    bipush 0x27
    bastore
    dup
    bipush 0x1c
    bipush 0x54
    bastore
    dup
    bipush 0x1d
    bipush 0x20
    bastore
    dup
    bipush 0x1e
    bipush 0x57
    bastore
    dup
    bipush 0x1f
    bipush 0x4f
    bastore
    dup
    bipush 0x20
    bipush 0x52
    bastore
    dup
    bipush 0x21
    bipush 0x4b
    bastore
    dup
    bipush 0x22
    bipush 0x20
    bastore
    dup
    bipush 0x23
    bipush 0x41
    bastore
    dup
    bipush 0x24
    bipush 0x4e
    bastore
    dup
    bipush 0x25
    bipush 0x59
    bastore
    dup
    bipush 0x26
    bipush 0x20
    bastore
    dup
    bipush 0x27
    bipush 0x4d
    bastore
    dup
    bipush 0x28
    bipush 0x4f
    bastore
    dup
    bipush 0x29
    bipush 0x52
    bastore
    dup
    bipush 0x2a
    bipush 0x45
    bastore
    dup
    bipush 0x2b
    bipush 0x2c
    bastore
    dup
    bipush 0x2c
    bipush 0x20
    bastore
    dup
    bipush 0x2d
    bipush 0x50
    bastore
    dup
    bipush 0x2e
    bipush 0x4c
    bastore
    dup
    bipush 0x2f
    bipush 0x45
    bastore
    dup
    bipush 0x30
    bipush 0x41
    bastore
    dup
    bipush 0x31
    bipush 0x53
    bastore
    dup
    bipush 0x32
    bipush 0x45
    bastore
    dup
    bipush 0x33
    bipush 0x20
    bastore
    dup
    bipush 0x34
    bipush 0x55
    bastore
    dup
    bipush 0x35
    bipush 0x4e
    bastore
    dup
    bipush 0x36
    bipush 0x49
    bastore
    dup
    bipush 0x37
    bipush 0x4e
    bastore
    dup
    bipush 0x38
    bipush 0x53
    bastore
    dup
    bipush 0x39
    bipush 0x54
    bastore
    dup
    bipush 0x3a
    bipush 0x41
    bastore
    dup
    bipush 0x3b
    bipush 0x4c
    bastore
    dup
    bipush 0x3c
    bipush 0x4c
    bastore
    dup
    bipush 0x3d
    bipush 0x20
    bastore
    dup
    bipush 0x3e
    bipush 0x54
    bastore
    dup
    bipush 0x3f
    bipush 0x48
    bastore
    dup
    bipush 0x40
    bipush 0x49
    bastore
    dup
    bipush 0x41
    bipush 0x53
    bastore
    dup
    bipush 0x42
    bipush 0x20
    bastore
    dup
    bipush 0x43
    bipush 0x56
    bastore
    dup
    bipush 0x44
    bipush 0x45
    bastore
    dup
    bipush 0x45
    bipush 0x52
    bastore
    dup
    bipush 0x46
    bipush 0x53
    bastore
    dup
    bipush 0x47
    bipush 0x49
    bastore
    dup
    bipush 0x48
    bipush 0x4f
    bastore
    dup
    bipush 0x49
    bipush 0x4e
    bastore
    dup
    bipush 0x4a
    bipush 0x20
    bastore
    dup
    bipush 0x4b
    bipush 0x41
    bastore
    dup
    bipush 0x4c
    bipush 0x4e
    bastore
    dup
    bipush 0x4d
    bipush 0x44
    bastore
    dup
    bipush 0x4e
    bipush 0x20
    bastore
    dup
    bipush 0x4f
    bipush 0x42
    bastore
    dup
    bipush 0x50
    bipush 0x55
    bastore
    dup
    bipush 0x51
    bipush 0x59
    bastore
    dup
    bipush 0x52
    bipush 0x20
    bastore
    dup
    bipush 0x53
    bipush 0x41
    bastore
    dup
    bipush 0x54
    bipush 0x20
    bastore
    dup
    bipush 0x55
    bipush 0x4c
    bastore
    dup
    bipush 0x56
    bipush 0x45
    bastore
    dup
    bipush 0x57
    bipush 0x47
    bastore
    dup
    bipush 0x58
    bipush 0x41
    bastore
    dup
    bipush 0x59
    bipush 0x4c
    bastore
    dup
    bipush 0x5a
    bipush 0x20
    bastore
    dup
    bipush 0x5b
    bipush 0x56
    bastore
    dup
    bipush 0x5c
    bipush 0x45
    bastore
    dup
    bipush 0x5d
    bipush 0x52
    bastore
    dup
    bipush 0x5e
    bipush 0x53
    bastore
    dup
    bipush 0x5f
    bipush 0x49
    bastore
    dup
    bipush 0x60
    bipush 0x4f
    bastore
    dup
    bipush 0x61
    bipush 0x4e
    bastore
    dup
    bipush 0x62
    bipush 0x20
    bastore
    dup
    bipush 0x63
    bipush 0x4f
    bastore
    dup
    bipush 0x64
    bipush 0x46
    bastore
    dup
    bipush 0x65
    bipush 0x20
    bastore
    dup
    bipush 0x66
    bipush 0x4d
    bastore
    dup
    bipush 0x67
    bipush 0x45
    bastore
    dup
    bipush 0x68
    bipush 0x20
    bastore
    dup
    bipush 0x69
    bipush 0x46
    bastore
    dup
    bipush 0x6a
    bipush 0x52
    bastore
    dup
    bipush 0x6b
    bipush 0x4f
    bastore
    dup
    bipush 0x6c
    bipush 0x4d
    bastore
    dup
    bipush 0x6d
    bipush 0x20
    bastore
    dup
    bipush 0x6e
    bipush 0x54
    bastore
    dup
    bipush 0x6f
    bipush 0x48
    bastore
    dup
    bipush 0x70
    bipush 0x45
    bastore
    dup
    bipush 0x71
    bipush 0x20
    bastore
    dup
    bipush 0x72
    bipush 0x41
    bastore
    dup
    bipush 0x73
    bipush 0x4e
    bastore
    dup
    bipush 0x74
    bipush 0x44
    bastore
    dup
    bipush 0x75
    bipush 0x52
    bastore
    dup
    bipush 0x76
    bipush 0x4f
    bastore
    dup
    bipush 0x77
    bipush 0x49
    bastore
    dup
    bipush 0x78
    bipush 0x44
    bastore
    dup
    bipush 0x79
    bipush 0x20
    bastore
    dup
    bipush 0x7a
    bipush 0x4d
    bastore
    dup
    bipush 0x7b
    bipush 0x41
    bastore
    dup
    bipush 0x7c
    bipush 0x52
    bastore
    dup
    bipush 0x7d
    bipush 0x4b
    bastore
    dup
    bipush 0x7e
    bipush 0x45
    bastore
    dup
    bipush 0x7f
    bipush 0x54
    bastore
    dup
    sipush 0x80
    bipush 0x2e
    bastore
    aastore
    dup
    iconst_3
    iconst_4
    newarray 0x8
    dup
    iconst_0
    iconst_0
    bastore
    dup
    iconst_1
    iconst_2
    bastore
    dup
    iconst_2
    bipush 0x4f
    bastore
    dup
    iconst_3
    bipush 0x4b
    bastore
    aastore
    putstatic i->j:[[B
    return
.end method
